Workbook

Sheet Start Here
B1: Business Control Center
B2: Bookkeeping and management workbook for a Sri Lankan service business. Financial year April 2026 – March 2027.
B4: HOW THE WORKBOOK FITS TOGETHER
B5: 1. Setup | C5: Fill once: business details, opening balances, your categories.
B6: 2. Transactions | C6: THE ONLY PLACE YOU TYPE MONEY. Every payment in or out, one row each. Everything else is calculated from here.
B7: 3. Invoices | C7: Every invoice you send, and whether it is paid. Shows who owes you.
B8: 4. Clients | C8: Your client list, with revenue and amount owed per client.
B9: 5. Monthly P&L | C9: Automatic. Profit and loss by month: revenue, costs, profit, margins.
B10: 6. Cash Flow | C10: Automatic. Cash in and out by month. Closing cash must match your bank.
B11: 7. Dashboard | C11: Automatic. One-page health check for any month, with warning signs.
B12: 8. Service Pricing | C12: Work out what each service really earns and what to charge.
B13: 9. Forecast | C13: Plan revenue and costs for Oct 2026 – Mar 2027 and compare with actuals.
B14: 10. Sales Pipeline | C14: Every lead, until it is won or lost.
B15: 11. Weekly Review | C15: Your 30-minute weekly check-in, one row per week of the 90 days.
B16: 12. 90-Day Plan | C16: Your crash-course task list, with progress tracking.
B17: 13. Tax Calendar | C17: Sri Lankan deadlines and thresholds to confirm with your accountant.
B19: COLOUR LEGEND
B20: Yellow cell / blue text | C20: You type here.
B21: Grey cell / black text | C21: Calculated automatically. Do not type over it.
B22: Green text | C22: Pulled from another sheet.
B23: Orange row | C23: An example to show the format. Overwrite or delete it.
B25: THE 5 GOLDEN RULES
B26: Rule 1 | C26: Business money and personal money never mix. Pay yourself a fixed salary (Owner drawings) instead of taking cash when needed.
B27: Rule 2 | C27: Every rupee gets a row. If it left or entered an account, it goes on Transactions with a category.
B28: Rule 3 | C28: No receipt, no record. Photograph every receipt the same day; note its number in the Reference column.
B29: Rule 4 | C29: Match the bank every month. Cash Flow closing cash must equal the real balance (Difference row = 0).
B30: Rule 5 | C30: Look at the numbers weekly. 30 minutes every week on the Weekly Review beats 3 days of panic at tax time.
B32: DAILY 10-MINUTE ROUTINE | C32: Open the bank app → enter yesterday's payments on Transactions → save receipts → mark any paid invoices.
B33: MONTHLY CLOSE (1–2 h) | C33: Enter everything → type real balances on Cash Flow row 23 → fix differences → chase overdue invoices → read P&L and Dashboard → move tax reserve.

Sheet Setup
A1: Setup: your business profile, accounts and categories
A2: Fill the yellow cells once. Everything else in the workbook reads from here.
A3: BUSINESS PROFILE
A4: Business name | B4: Your Business Name | D4: Trading name used on invoices.
A5: Owner(s) | B5: Owner name | D5: Who owns the business.
A6: Financial year starts | B6: 46113 | D6: Sri Lanka tax year runs 1 April – 31 March. The P&L and Cash Flow start here.
A7: Currency | B7: LKR (Rs) | D7: All amounts in Sri Lankan rupees.
A8: Tax reserve (% of net profit) | B8: 0.1 | D8: Assumption: move this % of each month's profit to a separate tax savings account. Ask your accountant for the right % for you.
A9: Target owner salary per month (Rs) | B9: 0 | D9: Fixed amount you pay yourself each month (set this in Week 4).
A10: Default invoice payment terms (days) | B10: 14 | D10: Used on the Invoices sheet when terms are left blank.
A12: MONEY ACCOUNTS (where money is kept)
A13: Account name | B13: Opening balance on FY start (Rs) | C13: Account number (last 4) | D13: Notes
A14: Business bank account | B14: 0 | D14: Main account for the business. All client payments should come here.
A15: Cash in hand | B15: 0 | D15: Physical cash kept for the business.
A16: Owner personal account (temporary) | B16: 0 | D16: Only while business money still passes through a personal account. Aim to stop using it.
A17: Tax savings account | B17: 0 | D17: Separate savings account where you keep the tax reserve.
A20: Total opening balance | B20: =SUM(B14:B19)
A22: CATEGORIES (the chart of accounts)
A23: Category | B23: Type (do not change) | C23: Report section | D23: What goes here
A24: Service fees – main service | B24: Income | C24: Revenue | D24: Fees for your main service. Rename to your service, e.g. "Web design projects".
A25: Service fees – second service | B25: Income | C25: Revenue | D25: Rename to your second service, or leave unused.
A26: Retainer / monthly fees | B26: Income | C26: Revenue | D26: Fixed monthly fees from ongoing clients.
A27: Other income | B27: Income | C27: Revenue | D27: Small one-off income (interest, sale of scrap, etc.).
B28: Income | C28: Revenue | D28: Spare: type a new income category here.
A29: Freelancers & subcontractors | B29: Direct Cost | C29: Cost of delivering services | D29: People paid to deliver client work.
A30: Project staff wages | B30: Direct Cost | C30: Cost of delivering services | D30: Wages of staff who do client work.
A31: Project tools & materials | B31: Direct Cost | C31: Cost of delivering services | D31: Software, materials or printing bought for a specific client job.
A32: Project travel | B32: Direct Cost | C32: Cost of delivering services | D32: Travel to deliver client work.
B33: Direct Cost | C33: Cost of delivering services | D33: Spare: type a new direct cost here.
A34: Salaries – admin & sales | B34: Operating Expense | C34: Overheads (running costs) | D34: Staff not directly doing client work.
A35: EPF / ETF (employer share) | B35: Operating Expense | C35: Overheads (running costs) | D35: Employer EPF 12% and ETF 3% on staff salaries.
A36: Rent | B36: Operating Expense | C36: Overheads (running costs) | D36: Office or workspace rent.
A37: Electricity & water | B37: Operating Expense | C37: Overheads (running costs) | D37: Utility bills.
A38: Internet & phone | B38: Operating Expense | C38: Overheads (running costs) | D38: Broadband, mobile bills, data.
A39: Software & subscriptions | B39: Operating Expense | C39: Overheads (running costs) | D39: Tools used to run the business (not for one client).
A40: Marketing & advertising | B40: Operating Expense | C40: Overheads (running costs) | D40: Ads, printing, sponsored posts, website.
A41: Professional fees | B41: Operating Expense | C41: Overheads (running costs) | D41: Accountant, lawyer, consultants.
A42: Bank charges | B42: Operating Expense | C42: Overheads (running costs) | D42: Fees, card charges, transfer fees.
A43: Transport & fuel | B43: Operating Expense | C43: Overheads (running costs) | D43: Business travel not linked to one client.
A44: Office supplies | B44: Operating Expense | C44: Overheads (running costs) | D44: Stationery, small office items.
A45: Training & books | B45: Operating Expense | C45: Overheads (running costs) | D45: Courses and books to build your skills.
... A49: Other expenses | B49: Operating Expense | C49: Overheads (running costs) | D49: Anything that doesn't fit above. Keep this small.
B50: Operating Expense | C50: Overheads (running costs) | D50: Spare
B51: Operating Expense | C51: Overheads (running costs) | D51: Spare
A52: Owner drawings / salary | B52: Owner Drawings | C52: Not in P&L: owner | D52: Money the owner takes out for personal use. NOT a business expense.
A53: Owner capital introduced | B53: Owner Capital | C53: Not in P&L: owner | D53: Owner's own money put into the business.
A54: Loan received | B54: Loan In | C54: Not in P&L: financing | D54: Money borrowed (bank or person).
A55: Loan repayment | B55: Loan Repayment | C55: Not in P&L: financing | D55: Paying back a loan (put interest under Bank charges).
A56: Equipment & asset purchases | B56: Asset Purchase | C56: Not in P&L: assets | D56: Laptops, cameras, furniture: items used for years.
A57: Income tax paid | B57: Tax Payment | C57: Not in P&L: tax | D57: Income tax instalments and final payments to IRD.
A58: VAT / SSCL paid | B58: Tax Payment | C58: Not in P&L: tax | D58: Only if you are registered for VAT or SSCL.
A59: Transfer between own accounts | B59: Transfer | C59: Not in P&L: movement | D59: Moving money between your own accounts. Enter TWO rows: money out of one account, money in to the other.
A61: Tip: rename the yellow category names to match your business, but never change the Type column. The reports group your money by Type.

Sheet Transactions
A1: Transactions: the cash book (every rupee in and out)
A2: One row per payment. Yellow = you type. Grey = calculated. Enter money IN or money OUT, never both on one row.
A3: Legend: | B3: Blue text = you type · Grey = automatic · Orange = example row (overwrite it)
A4: Date | B4: Description | C4: Client / Supplier | D4: Category | E4: Money IN (Rs) | F4: Money OUT (Rs) | G4: Account | H4: Method | I4: Reference (invoice / receipt no.) | J4: Receipt saved? | K4: Type (auto) | L4: Month (auto) | M4: Net (auto) | N4: Notes
A5: 46115 | B5: EXAMPLE: Website project, 50% advance | C5: ABC Holdings (Pvt) Ltd | D5: Service fees – main service | E5: 150000 | G5: Business bank account | H5: Bank transfer | I5: INV-001 | J5: Yes | K5: =IF(D5="","",IFERROR(INDEX(Setup!$B$24:$B$59,MATCH(D5,Setup!$A$24:$A$59,0)),"Check category")) | L5: =IF(A5="","",DATE(YEAR(A5),MONTH(A5),1)) | M5: =IF(AND(E5="",F5=""),"",N(E5)-N(F5)) | N5: Example row: replace or delete it
K6: =IF(D6="","",IFERROR(INDEX(Setup!$B$24:$B$59,MATCH(D6,Setup!$A$24:$A$59,0)),"Check category")) | L6: =IF(A6="","",DATE(YEAR(A6),MONTH(A6),1)) | M6: =IF(AND(E6="",F6=""),"",N(E6)-N(F6))
K7: =IF(D7="","",IFERROR(INDEX(Setup!$B$24:$B$59,MATCH(D7,Setup!$A$24:$A$59,0)),"Check category")) | L7: =IF(A7="","",DATE(YEAR(A7),MONTH(A7),1)) | M7: =IF(AND(E7="",F7=""),"",N(E7)-N(F7))
K8: =IF(D8="","",IFERROR(INDEX(Setup!$B$24:$B$59,MATCH(D8,Setup!$A$24:$A$59,0)),"Check category")) | L8: =IF(A8="","",DATE(YEAR(A8),MONTH(A8),1)) | M8: =IF(AND(E8="",F8=""),"",N(E8)-N(F8))
K9: =IF(D9="","",IFERROR(INDEX(Setup!$B$24:$B$59,MATCH(D9,Setup!$A$24:$A$59,0)),"Check category")) | L9: =IF(A9="","",DATE(YEAR(A9),MONTH(A9),1)) | M9: =IF(AND(E9="",F9=""),"",N(E9)-N(F9))
K10: =IF(D10="","",IFERROR(INDEX(Setup!$B$24:$B$59,MATCH(D10,Setup!$A$24:$A$59,0)),"Check category")) | L10: =IF(A10="","",DATE(YEAR(A10),MONTH(A10),1)) | M10: =IF(AND(E10="",F10=""),"",N(E10)-N(F10))
K11: =IF(D11="","",IFERROR(INDEX(Setup!$B$24:$B$59,MATCH(D11,Setup!$A$24:$A$59,0)),"Check category")) | L11: =IF(A11="","",DATE(YEAR(A11),MONTH(A11),1)) | M11: =IF(AND(E11="",F11=""),"",N(E11)-N(F11))
K12: =IF(D12="","",IFERROR(INDEX(Setup!$B$24:$B$59,MATCH(D12,Setup!$A$24:$A$59,0)),"Check category")) | L12: =IF(A12="","",DATE(YEAR(A12),MONTH(A12),1)) | M12: =IF(AND(E12="",F12=""),"",N(E12)-N(F12))
K13: =IF(D13="","",IFERROR(INDEX(Setup!$B$24:$B$59,MATCH(D13,Setup!$A$24:$A$59,0)),"Check category")) | L13: =IF(A13="","",DATE(YEAR(A13),MONTH(A13),1)) | M13: =IF(AND(E13="",F13=""),"",N(E13)-N(F13))
K14: =IF(D14="","",IFERROR(INDEX(Setup!$B$24:$B$59,MATCH(D14,Setup!$A$24:$A$59,0)),"Check category")) | L14: =IF(A14="","",DATE(YEAR(A14),MONTH(A14),1)) | M14: =IF(AND(E14="",F14=""),"",N(E14)-N(F14))
K15: =IF(D15="","",IFERROR(INDEX(Setup!$B$24:$B$59,MATCH(D15,Setup!$A$24:$A$59,0)),"Check category")) | L15: =IF(A15="","",DATE(YEAR(A15),MONTH(A15),1)) | M15: =IF(AND(E15="",F15=""),"",N(E15)-N(F15))
K16: =IF(D16="","",IFERROR(INDEX(Setup!$B$24:$B$59,MATCH(D16,Setup!$A$24:$A$59,0)),"Check category")) | L16: =IF(A16="","",DATE(YEAR(A16),MONTH(A16),1)) | M16: =IF(AND(E16="",F16=""),"",N(E16)-N(F16))
K17: =IF(D17="","",IFERROR(INDEX(Setup!$B$24:$B$59,MATCH(D17,Setup!$A$24:$A$59,0)),"Check category")) | L17: =IF(A17="","",DATE(YEAR(A17),MONTH(A17),1)) | M17: =IF(AND(E17="",F17=""),"",N(E17)-N(F17))
... K1504: =IF(D1504="","",IFERROR(INDEX(Setup!$B$24:$B$59,MATCH(D1504,Setup!$A$24:$A$59,0)),"Check category")) | L1504: =IF(A1504="","",DATE(YEAR(A1504),MONTH(A1504),1)) | M1504: =IF(AND(E1504="",F1504=""),"",N(E1504)-N(F1504))

Sheet Invoices
A1: Invoices: who owes us money?
A2: Add every invoice you send. When it is paid, fill Amount paid + Paid date, AND record the payment on Transactions.
A3: Total outstanding: | C3: =SUM(I5:I404) | D3: Overdue: | F3: =SUMIFS(I5:I404,K5:K404,"Overdue")
A4: Invoice no. | B4: Client | C4: Service | D4: Issue date | E4: Terms (days) | F4: Due date (auto) | G4: Amount (Rs) | H4: Amount paid (Rs) | I4: Balance due (auto) | J4: Paid date | K4: Status (auto) | L4: Days overdue (auto) | M4: Notes / follow-up
A5: INV-001 | B5: ABC Holdings (Pvt) Ltd | C5: Website project | D5: 46113 | E5: 14 | F5: =IF(D5="","",D5+IF(E5="",Setup!$B$10,E5)) | G5: 300000 | H5: 150000 | I5: =IF(G5="","",G5-N(H5)) | K5: =IF(G5="","",IF(I5<=0,"Paid",IF(TODAY()>F5,"Overdue","Open"))) | L5: =IF(K5="Overdue",TODAY()-F5,"") | M5: Example row: replace or delete
F6: =IF(D6="","",D6+IF(E6="",Setup!$B$10,E6)) | I6: =IF(G6="","",G6-N(H6)) | K6: =IF(G6="","",IF(I6<=0,"Paid",IF(TODAY()>F6,"Overdue","Open"))) | L6: =IF(K6="Overdue",TODAY()-F6,"")
F7: =IF(D7="","",D7+IF(E7="",Setup!$B$10,E7)) | I7: =IF(G7="","",G7-N(H7)) | K7: =IF(G7="","",IF(I7<=0,"Paid",IF(TODAY()>F7,"Overdue","Open"))) | L7: =IF(K7="Overdue",TODAY()-F7,"")
F8: =IF(D8="","",D8+IF(E8="",Setup!$B$10,E8)) | I8: =IF(G8="","",G8-N(H8)) | K8: =IF(G8="","",IF(I8<=0,"Paid",IF(TODAY()>F8,"Overdue","Open"))) | L8: =IF(K8="Overdue",TODAY()-F8,"")
F9: =IF(D9="","",D9+IF(E9="",Setup!$B$10,E9)) | I9: =IF(G9="","",G9-N(H9)) | K9: =IF(G9="","",IF(I9<=0,"Paid",IF(TODAY()>F9,"Overdue","Open"))) | L9: =IF(K9="Overdue",TODAY()-F9,"")
F10: =IF(D10="","",D10+IF(E10="",Setup!$B$10,E10)) | I10: =IF(G10="","",G10-N(H10)) | K10: =IF(G10="","",IF(I10<=0,"Paid",IF(TODAY()>F10,"Overdue","Open"))) | L10: =IF(K10="Overdue",TODAY()-F10,"")
F11: =IF(D11="","",D11+IF(E11="",Setup!$B$10,E11)) | I11: =IF(G11="","",G11-N(H11)) | K11: =IF(G11="","",IF(I11<=0,"Paid",IF(TODAY()>F11,"Overdue","Open"))) | L11: =IF(K11="Overdue",TODAY()-F11,"")
F12: =IF(D12="","",D12+IF(E12="",Setup!$B$10,E12)) | I12: =IF(G12="","",G12-N(H12)) | K12: =IF(G12="","",IF(I12<=0,"Paid",IF(TODAY()>F12,"Overdue","Open"))) | L12: =IF(K12="Overdue",TODAY()-F12,"")
F13: =IF(D13="","",D13+IF(E13="",Setup!$B$10,E13)) | I13: =IF(G13="","",G13-N(H13)) | K13: =IF(G13="","",IF(I13<=0,"Paid",IF(TODAY()>F13,"Overdue","Open"))) | L13: =IF(K13="Overdue",TODAY()-F13,"")
F14: =IF(D14="","",D14+IF(E14="",Setup!$B$10,E14)) | I14: =IF(G14="","",G14-N(H14)) | K14: =IF(G14="","",IF(I14<=0,"Paid",IF(TODAY()>F14,"Overdue","Open"))) | L14: =IF(K14="Overdue",TODAY()-F14,"")
F15: =IF(D15="","",D15+IF(E15="",Setup!$B$10,E15)) | I15: =IF(G15="","",G15-N(H15)) | K15: =IF(G15="","",IF(I15<=0,"Paid",IF(TODAY()>F15,"Overdue","Open"))) | L15: =IF(K15="Overdue",TODAY()-F15,"")
F16: =IF(D16="","",D16+IF(E16="",Setup!$B$10,E16)) | I16: =IF(G16="","",G16-N(H16)) | K16: =IF(G16="","",IF(I16<=0,"Paid",IF(TODAY()>F16,"Overdue","Open"))) | L16: =IF(K16="Overdue",TODAY()-F16,"")
F17: =IF(D17="","",D17+IF(E17="",Setup!$B$10,E17)) | I17: =IF(G17="","",G17-N(H17)) | K17: =IF(G17="","",IF(I17<=0,"Paid",IF(TODAY()>F17,"Overdue","Open"))) | L17: =IF(K17="Overdue",TODAY()-F17,"")
... F404: =IF(D404="","",D404+IF(E404="",Setup!$B$10,E404)) | I404: =IF(G404="","",G404-N(H404)) | K404: =IF(G404="","",IF(I404<=0,"Paid",IF(TODAY()>F404,"Overdue","Open"))) | L404: =IF(K404="Overdue",TODAY()-F404,"")

Sheet Clients
A1: Clients: who pays us, and how much?
A2: Type each client once, spelled exactly as on Transactions and Invoices. Revenue and balances fill in automatically.
A3: Red share = this client is more than 30% of revenue (concentration risk).
A4: Client name | B4: Contact person | C4: Phone / email | D4: Main service | E4: Client since | F4: Revenue this FY (auto) | G4: Share of revenue (auto) | H4: Owed to us (auto) | I4: Notes
A5: ABC Holdings (Pvt) Ltd | B5: Mr. Perera | C5: perera@example.lk | D5: Website project | E5: 46113 | F5: =IF(A5="","",SUMIFS(Transactions!$E$5:$E$1504,Transactions!$C$5:$C$1504,A5,Transactions!$K$5:$K$1504,"Income")-SUMIFS(Transactions!$F$5:$F$1504,Transactions!$C$5:$C$1504,A5,Transactions!$K$5:$K$1504,"Income")) | G5: =IF(A5="","",IF('Monthly P&L'!$N$11=0,0,F5/'Monthly P&L'!$N$11)) | H5: =IF(A5="","",SUMIFS(Invoices!$I$5:$I$404,Invoices!$B$5:$B$404,A5)) | I5: Example row: replace or delete
F6: =IF(A6="","",SUMIFS(Transactions!$E$5:$E$1504,Transactions!$C$5:$C$1504,A6,Transactions!$K$5:$K$1504,"Income")-SUMIFS(Transactions!$F$5:$F$1504,Transactions!$C$5:$C$1504,A6,Transactions!$K$5:$K$1504,"Income")) | G6: =IF(A6="","",IF('Monthly P&L'!$N$11=0,0,F6/'Monthly P&L'!$N$11)) | H6: =IF(A6="","",SUMIFS(Invoices!$I$5:$I$404,Invoices!$B$5:$B$404,A6))
F7: =IF(A7="","",SUMIFS(Transactions!$E$5:$E$1504,Transactions!$C$5:$C$1504,A7,Transactions!$K$5:$K$1504,"Income")-SUMIFS(Transactions!$F$5:$F$1504,Transactions!$C$5:$C$1504,A7,Transactions!$K$5:$K$1504,"Income")) | G7: =IF(A7="","",IF('Monthly P&L'!$N$11=0,0,F7/'Monthly P&L'!$N$11)) | H7: =IF(A7="","",SUMIFS(Invoices!$I$5:$I$404,Invoices!$B$5:$B$404,A7))
F8: =IF(A8="","",SUMIFS(Transactions!$E$5:$E$1504,Transactions!$C$5:$C$1504,A8,Transactions!$K$5:$K$1504,"Income")-SUMIFS(Transactions!$F$5:$F$1504,Transactions!$C$5:$C$1504,A8,Transactions!$K$5:$K$1504,"Income")) | G8: =IF(A8="","",IF('Monthly P&L'!$N$11=0,0,F8/'Monthly P&L'!$N$11)) | H8: =IF(A8="","",SUMIFS(Invoices!$I$5:$I$404,Invoices!$B$5:$B$404,A8))
F9: =IF(A9="","",SUMIFS(Transactions!$E$5:$E$1504,Transactions!$C$5:$C$1504,A9,Transactions!$K$5:$K$1504,"Income")-SUMIFS(Transactions!$F$5:$F$1504,Transactions!$C$5:$C$1504,A9,Transactions!$K$5:$K$1504,"Income")) | G9: =IF(A9="","",IF('Monthly P&L'!$N$11=0,0,F9/'Monthly P&L'!$N$11)) | H9: =IF(A9="","",SUMIFS(Invoices!$I$5:$I$404,Invoices!$B$5:$B$404,A9))
F10: =IF(A10="","",SUMIFS(Transactions!$E$5:$E$1504,Transactions!$C$5:$C$1504,A10,Transactions!$K$5:$K$1504,"Income")-SUMIFS(Transactions!$F$5:$F$1504,Transactions!$C$5:$C$1504,A10,Transactions!$K$5:$K$1504,"Income")) | G10: =IF(A10="","",IF('Monthly P&L'!$N$11=0,0,F10/'Monthly P&L'!$N$11)) | H10: =IF(A10="","",SUMIFS(Invoices!$I$5:$I$404,Invoices!$B$5:$B$404,A10))
F11: =IF(A11="","",SUMIFS(Transactions!$E$5:$E$1504,Transactions!$C$5:$C$1504,A11,Transactions!$K$5:$K$1504,"Income")-SUMIFS(Transactions!$F$5:$F$1504,Transactions!$C$5:$C$1504,A11,Transactions!$K$5:$K$1504,"Income")) | G11: =IF(A11="","",IF('Monthly P&L'!$N$11=0,0,F11/'Monthly P&L'!$N$11)) | H11: =IF(A11="","",SUMIFS(Invoices!$I$5:$I$404,Invoices!$B$5:$B$404,A11))
F12: =IF(A12="","",SUMIFS(Transactions!$E$5:$E$1504,Transactions!$C$5:$C$1504,A12,Transactions!$K$5:$K$1504,"Income")-SUMIFS(Transactions!$F$5:$F$1504,Transactions!$C$5:$C$1504,A12,Transactions!$K$5:$K$1504,"Income")) | G12: =IF(A12="","",IF('Monthly P&L'!$N$11=0,0,F12/'Monthly P&L'!$N$11)) | H12: =IF(A12="","",SUMIFS(Invoices!$I$5:$I$404,Invoices!$B$5:$B$404,A12))
F13: =IF(A13="","",SUMIFS(Transactions!$E$5:$E$1504,Transactions!$C$5:$C$1504,A13,Transactions!$K$5:$K$1504,"Income")-SUMIFS(Transactions!$F$5:$F$1504,Transactions!$C$5:$C$1504,A13,Transactions!$K$5:$K$1504,"Income")) | G13: =IF(A13="","",IF('Monthly P&L'!$N$11=0,0,F13/'Monthly P&L'!$N$11)) | H13: =IF(A13="","",SUMIFS(Invoices!$I$5:$I$404,Invoices!$B$5:$B$404,A13))
F14: =IF(A14="","",SUMIFS(Transactions!$E$5:$E$1504,Transactions!$C$5:$C$1504,A14,Transactions!$K$5:$K$1504,"Income")-SUMIFS(Transactions!$F$5:$F$1504,Transactions!$C$5:$C$1504,A14,Transactions!$K$5:$K$1504,"Income")) | G14: =IF(A14="","",IF('Monthly P&L'!$N$11=0,0,F14/'Monthly P&L'!$N$11)) | H14: =IF(A14="","",SUMIFS(Invoices!$I$5:$I$404,Invoices!$B$5:$B$404,A14))
F15: =IF(A15="","",SUMIFS(Transactions!$E$5:$E$1504,Transactions!$C$5:$C$1504,A15,Transactions!$K$5:$K$1504,"Income")-SUMIFS(Transactions!$F$5:$F$1504,Transactions!$C$5:$C$1504,A15,Transactions!$K$5:$K$1504,"Income")) | G15: =IF(A15="","",IF('Monthly P&L'!$N$11=0,0,F15/'Monthly P&L'!$N$11)) | H15: =IF(A15="","",SUMIFS(Invoices!$I$5:$I$404,Invoices!$B$5:$B$404,A15))
F16: =IF(A16="","",SUMIFS(Transactions!$E$5:$E$1504,Transactions!$C$5:$C$1504,A16,Transactions!$K$5:$K$1504,"Income")-SUMIFS(Transactions!$F$5:$F$1504,Transactions!$C$5:$C$1504,A16,Transactions!$K$5:$K$1504,"Income")) | G16: =IF(A16="","",IF('Monthly P&L'!$N$11=0,0,F16/'Monthly P&L'!$N$11)) | H16: =IF(A16="","",SUMIFS(Invoices!$I$5:$I$404,Invoices!$B$5:$B$404,A16))
F17: =IF(A17="","",SUMIFS(Transactions!$E$5:$E$1504,Transactions!$C$5:$C$1504,A17,Transactions!$K$5:$K$1504,"Income")-SUMIFS(Transactions!$F$5:$F$1504,Transactions!$C$5:$C$1504,A17,Transactions!$K$5:$K$1504,"Income")) | G17: =IF(A17="","",IF('Monthly P&L'!$N$11=0,0,F17/'Monthly P&L'!$N$11)) | H17: =IF(A17="","",SUMIFS(Invoices!$I$5:$I$404,Invoices!$B$5:$B$404,A17))
... F104: =IF(A104="","",SUMIFS(Transactions!$E$5:$E$1504,Transactions!$C$5:$C$1504,A104,Transactions!$K$5:$K$1504,"Income")-SUMIFS(Transactions!$F$5:$F$1504,Transactions!$C$5:$C$1504,A104,Transactions!$K$5:$K$1504,"Income")) | G104: =IF(A104="","",IF('Monthly P&L'!$N$11=0,0,F104/'Monthly P&L'!$N$11)) | H104: =IF(A104="","",SUMIFS(Invoices!$I$5:$I$404,Invoices!$B$5:$B$404,A104))

Sheet Monthly P&L
A1: Profit & Loss: did we make money each month?
A2: Fully automatic from the Transactions sheet. Financial year April–March.
A4: Line item (Rs) | B4: =Setup!$B$6 | C4: =EDATE(B4,1) | D4: =EDATE(C4,1) | E4: =EDATE(D4,1) | F4: =EDATE(E4,1) | G4: =EDATE(F4,1) | H4: =EDATE(G4,1) | I4: =EDATE(H4,1) | J4: =EDATE(I4,1) | ... M4: =EDATE(L4,1) | N4: FY total
A5: REVENUE (sales)
A6: =IF(Setup!$A$24="","",Setup!$A$24) | B6: =IF($A6="",0,SUMIFS(Transactions!$E$5:$E$1504,Transactions!$D$5:$D$1504,$A6,Transactions!$L$5:$L$1504,B$4)-SUMIFS(Transactions!$F$5:$F$1504,Transactions!$D$5:$D$1504,$A6,Transactions!$L$5:$L$1504,B$4)) | C6: =IF($A6="",0,SUMIFS(Transactions!$E$5:$E$1504,Transactions!$D$5:$D$1504,$A6,Transactions!$L$5:$L$1504,C$4)-SUMIFS(Transactions!$F$5:$F$1504,Transactions!$D$5:$D$1504,$A6,Transactions!$L$5:$L$1504,C$4)) | D6: =IF($A6="",0,SUMIFS(Transactions!$E$5:$E$1504,Transactions!$D$5:$D$1504,$A6,Transactions!$L$5:$L$1504,D$4)-SUMIFS(Transactions!$F$5:$F$1504,Transactions!$D$5:$D$1504,$A6,Transactions!$L$5:$L$1504,D$4)) | E6: =IF($A6="",0,SUMIFS(Transactions!$E$5:$E$1504,Transactions!$D$5:$D$1504,$A6,Transactions!$L$5:$L$1504,E$4)-SUMIFS(Transactions!$F$5:$F$1504,Transactions!$D$5:$D$1504,$A6,Transactions!$L$5:$L$1504,E$4)) | F6: =IF($A6="",0,SUMIFS(Transactions!$E$5:$E$1504,Transactions!$D$5:$D$1504,$A6,Transactions!$L$5:$L$1504,F$4)-SUMIFS(Transactions!$F$5:$F$1504,Transactions!$D$5:$D$1504,$A6,Transactions!$L$5:$L$1504,F$4)) | G6: =IF($A6="",0,SUMIFS(Transactions!$E$5:$E$1504,Transactions!$D$5:$D$1504,$A6,Transactions!$L$5:$L$1504,G$4)-SUMIFS(Transactions!$F$5:$F$1504,Transactions!$D$5:$D$1504,$A6,Transactions!$L$5:$L$1504,G$4)) | H6: =IF($A6="",0,SUMIFS(Transactions!$E$5:$E$1504,Transactions!$D$5:$D$1504,$A6,Transactions!$L$5:$L$1504,H$4)-SUMIFS(Transactions!$F$5:$F$1504,Transactions!$D$5:$D$1504,$A6,Transactions!$L$5:$L$1504,H$4)) | I6: =IF($A6="",0,SUMIFS(Transactions!$E$5:$E$1504,Transactions!$D$5:$D$1504,$A6,Transactions!$L$5:$L$1504,I$4)-SUMIFS(Transactions!$F$5:$F$1504,Transactions!$D$5:$D$1504,$A6,Transactions!$L$5:$L$1504,I$4)) | ... M6: =IF($A6="",0,SUMIFS(Transactions!$E$5:$E$1504,Transactions!$D$5:$D$1504,$A6,Transactions!$L$5:$L$1504,M$4)-SUMIFS(Transactions!$F$5:$F$1504,Transactions!$D$5:$D$1504,$A6,Transactions!$L$5:$L$1504,M$4)) | N6: =SUM(B6:M6)
A7: =IF(Setup!$A$25="","",Setup!$A$25) | B7: =IF($A7="",0,SUMIFS(Transactions!$E$5:$E$1504,Transactions!$D$5:$D$1504,$A7,Transactions!$L$5:$L$1504,B$4)-SUMIFS(Transactions!$F$5:$F$1504,Transactions!$D$5:$D$1504,$A7,Transactions!$L$5:$L$1504,B$4)) | C7: =IF($A7="",0,SUMIFS(Transactions!$E$5:$E$1504,Transactions!$D$5:$D$1504,$A7,Transactions!$L$5:$L$1504,C$4)-SUMIFS(Transactions!$F$5:$F$1504,Transactions!$D$5:$D$1504,$A7,Transactions!$L$5:$L$1504,C$4)) | D7: =IF($A7="",0,SUMIFS(Transactions!$E$5:$E$1504,Transactions!$D$5:$D$1504,$A7,Transactions!$L$5:$L$1504,D$4)-SUMIFS(Transactions!$F$5:$F$1504,Transactions!$D$5:$D$1504,$A7,Transactions!$L$5:$L$1504,D$4)) | E7: =IF($A7="",0,SUMIFS(Transactions!$E$5:$E$1504,Transactions!$D$5:$D$1504,$A7,Transactions!$L$5:$L$1504,E$4)-SUMIFS(Transactions!$F$5:$F$1504,Transactions!$D$5:$D$1504,$A7,Transactions!$L$5:$L$1504,E$4)) | F7: =IF($A7="",0,SUMIFS(Transactions!$E$5:$E$1504,Transactions!$D$5:$D$1504,$A7,Transactions!$L$5:$L$1504,F$4)-SUMIFS(Transactions!$F$5:$F$1504,Transactions!$D$5:$D$1504,$A7,Transactions!$L$5:$L$1504,F$4)) | G7: =IF($A7="",0,SUMIFS(Transactions!$E$5:$E$1504,Transactions!$D$5:$D$1504,$A7,Transactions!$L$5:$L$1504,G$4)-SUMIFS(Transactions!$F$5:$F$1504,Transactions!$D$5:$D$1504,$A7,Transactions!$L$5:$L$1504,G$4)) | H7: =IF($A7="",0,SUMIFS(Transactions!$E$5:$E$1504,Transactions!$D$5:$D$1504,$A7,Transactions!$L$5:$L$1504,H$4)-SUMIFS(Transactions!$F$5:$F$1504,Transactions!$D$5:$D$1504,$A7,Transactions!$L$5:$L$1504,H$4)) | I7: =IF($A7="",0,SUMIFS(Transactions!$E$5:$E$1504,Transactions!$D$5:$D$1504,$A7,Transactions!$L$5:$L$1504,I$4)-SUMIFS(Transactions!$F$5:$F$1504,Transactions!$D$5:$D$1504,$A7,Transactions!$L$5:$L$1504,I$4)) | ... M7: =IF($A7="",0,SUMIFS(Transactions!$E$5:$E$1504,Transactions!$D$5:$D$1504,$A7,Transactions!$L$5:$L$1504,M$4)-SUMIFS(Transactions!$F$5:$F$1504,Transactions!$D$5:$D$1504,$A7,Transactions!$L$5:$L$1504,M$4)) | N7: =SUM(B7:M7)
A8: =IF(Setup!$A$26="","",Setup!$A$26) | B8: =IF($A8="",0,SUMIFS(Transactions!$E$5:$E$1504,Transactions!$D$5:$D$1504,$A8,Transactions!$L$5:$L$1504,B$4)-SUMIFS(Transactions!$F$5:$F$1504,Transactions!$D$5:$D$1504,$A8,Transactions!$L$5:$L$1504,B$4)) | C8: =IF($A8="",0,SUMIFS(Transactions!$E$5:$E$1504,Transactions!$D$5:$D$1504,$A8,Transactions!$L$5:$L$1504,C$4)-SUMIFS(Transactions!$F$5:$F$1504,Transactions!$D$5:$D$1504,$A8,Transactions!$L$5:$L$1504,C$4)) | D8: =IF($A8="",0,SUMIFS(Transactions!$E$5:$E$1504,Transactions!$D$5:$D$1504,$A8,Transactions!$L$5:$L$1504,D$4)-SUMIFS(Transactions!$F$5:$F$1504,Transactions!$D$5:$D$1504,$A8,Transactions!$L$5:$L$1504,D$4)) | E8: =IF($A8="",0,SUMIFS(Transactions!$E$5:$E$1504,Transactions!$D$5:$D$1504,$A8,Transactions!$L$5:$L$1504,E$4)-SUMIFS(Transactions!$F$5:$F$1504,Transactions!$D$5:$D$1504,$A8,Transactions!$L$5:$L$1504,E$4)) | F8: =IF($A8="",0,SUMIFS(Transactions!$E$5:$E$1504,Transactions!$D$5:$D$1504,$A8,Transactions!$L$5:$L$1504,F$4)-SUMIFS(Transactions!$F$5:$F$1504,Transactions!$D$5:$D$1504,$A8,Transactions!$L$5:$L$1504,F$4)) | G8: =IF($A8="",0,SUMIFS(Transactions!$E$5:$E$1504,Transactions!$D$5:$D$1504,$A8,Transactions!$L$5:$L$1504,G$4)-SUMIFS(Transactions!$F$5:$F$1504,Transactions!$D$5:$D$1504,$A8,Transactions!$L$5:$L$1504,G$4)) | H8: =IF($A8="",0,SUMIFS(Transactions!$E$5:$E$1504,Transactions!$D$5:$D$1504,$A8,Transactions!$L$5:$L$1504,H$4)-SUMIFS(Transactions!$F$5:$F$1504,Transactions!$D$5:$D$1504,$A8,Transactions!$L$5:$L$1504,H$4)) | I8: =IF($A8="",0,SUMIFS(Transactions!$E$5:$E$1504,Transactions!$D$5:$D$1504,$A8,Transactions!$L$5:$L$1504,I$4)-SUMIFS(Transactions!$F$5:$F$1504,Transactions!$D$5:$D$1504,$A8,Transactions!$L$5:$L$1504,I$4)) | ... M8: =IF($A8="",0,SUMIFS(Transactions!$E$5:$E$1504,Transactions!$D$5:$D$1504,$A8,Transactions!$L$5:$L$1504,M$4)-SUMIFS(Transactions!$F$5:$F$1504,Transactions!$D$5:$D$1504,$A8,Transactions!$L$5:$L$1504,M$4)) | N8: =SUM(B8:M8)
A9: =IF(Setup!$A$27="","",Setup!$A$27) | B9: =IF($A9="",0,SUMIFS(Transactions!$E$5:$E$1504,Transactions!$D$5:$D$1504,$A9,Transactions!$L$5:$L$1504,B$4)-SUMIFS(Transactions!$F$5:$F$1504,Transactions!$D$5:$D$1504,$A9,Transactions!$L$5:$L$1504,B$4)) | C9: =IF($A9="",0,SUMIFS(Transactions!$E$5:$E$1504,Transactions!$D$5:$D$1504,$A9,Transactions!$L$5:$L$1504,C$4)-SUMIFS(Transactions!$F$5:$F$1504,Transactions!$D$5:$D$1504,$A9,Transactions!$L$5:$L$1504,C$4)) | D9: =IF($A9="",0,SUMIFS(Transactions!$E$5:$E$1504,Transactions!$D$5:$D$1504,$A9,Transactions!$L$5:$L$1504,D$4)-SUMIFS(Transactions!$F$5:$F$1504,Transactions!$D$5:$D$1504,$A9,Transactions!$L$5:$L$1504,D$4)) | E9: =IF($A9="",0,SUMIFS(Transactions!$E$5:$E$1504,Transactions!$D$5:$D$1504,$A9,Transactions!$L$5:$L$1504,E$4)-SUMIFS(Transactions!$F$5:$F$1504,Transactions!$D$5:$D$1504,$A9,Transactions!$L$5:$L$1504,E$4)) | F9: =IF($A9="",0,SUMIFS(Transactions!$E$5:$E$1504,Transactions!$D$5:$D$1504,$A9,Transactions!$L$5:$L$1504,F$4)-SUMIFS(Transactions!$F$5:$F$1504,Transactions!$D$5:$D$1504,$A9,Transactions!$L$5:$L$1504,F$4)) | G9: =IF($A9="",0,SUMIFS(Transactions!$E$5:$E$1504,Transactions!$D$5:$D$1504,$A9,Transactions!$L$5:$L$1504,G$4)-SUMIFS(Transactions!$F$5:$F$1504,Transactions!$D$5:$D$1504,$A9,Transactions!$L$5:$L$1504,G$4)) | H9: =IF($A9="",0,SUMIFS(Transactions!$E$5:$E$1504,Transactions!$D$5:$D$1504,$A9,Transactions!$L$5:$L$1504,H$4)-SUMIFS(Transactions!$F$5:$F$1504,Transactions!$D$5:$D$1504,$A9,Transactions!$L$5:$L$1504,H$4)) | I9: =IF($A9="",0,SUMIFS(Transactions!$E$5:$E$1504,Transactions!$D$5:$D$1504,$A9,Transactions!$L$5:$L$1504,I$4)-SUMIFS(Transactions!$F$5:$F$1504,Transactions!$D$5:$D$1504,$A9,Transactions!$L$5:$L$1504,I$4)) | ... M9: =IF($A9="",0,SUMIFS(Transactions!$E$5:$E$1504,Transactions!$D$5:$D$1504,$A9,Transactions!$L$5:$L$1504,M$4)-SUMIFS(Transactions!$F$5:$F$1504,Transactions!$D$5:$D$1504,$A9,Transactions!$L$5:$L$1504,M$4)) | N9: =SUM(B9:M9)
A10: =IF(Setup!$A$28="","",Setup!$A$28) | B10: =IF($A10="",0,SUMIFS(Transactions!$E$5:$E$1504,Transactions!$D$5:$D$1504,$A10,Transactions!$L$5:$L$1504,B$4)-SUMIFS(Transactions!$F$5:$F$1504,Transactions!$D$5:$D$1504,$A10,Transactions!$L$5:$L$1504,B$4)) | C10: =IF($A10="",0,SUMIFS(Transactions!$E$5:$E$1504,Transactions!$D$5:$D$1504,$A10,Transactions!$L$5:$L$1504,C$4)-SUMIFS(Transactions!$F$5:$F$1504,Transactions!$D$5:$D$1504,$A10,Transactions!$L$5:$L$1504,C$4)) | D10: =IF($A10="",0,SUMIFS(Transactions!$E$5:$E$1504,Transactions!$D$5:$D$1504,$A10,Transactions!$L$5:$L$1504,D$4)-SUMIFS(Transactions!$F$5:$F$1504,Transactions!$D$5:$D$1504,$A10,Transactions!$L$5:$L$1504,D$4)) | E10: =IF($A10="",0,SUMIFS(Transactions!$E$5:$E$1504,Transactions!$D$5:$D$1504,$A10,Transactions!$L$5:$L$1504,E$4)-SUMIFS(Transactions!$F$5:$F$1504,Transactions!$D$5:$D$1504,$A10,Transactions!$L$5:$L$1504,E$4)) | F10: =IF($A10="",0,SUMIFS(Transactions!$E$5:$E$1504,Transactions!$D$5:$D$1504,$A10,Transactions!$L$5:$L$1504,F$4)-SUMIFS(Transactions!$F$5:$F$1504,Transactions!$D$5:$D$1504,$A10,Transactions!$L$5:$L$1504,F$4)) | G10: =IF($A10="",0,SUMIFS(Transactions!$E$5:$E$1504,Transactions!$D$5:$D$1504,$A10,Transactions!$L$5:$L$1504,G$4)-SUMIFS(Transactions!$F$5:$F$1504,Transactions!$D$5:$D$1504,$A10,Transactions!$L$5:$L$1504,G$4)) | H10: =IF($A10="",0,SUMIFS(Transactions!$E$5:$E$1504,Transactions!$D$5:$D$1504,$A10,Transactions!$L$5:$L$1504,H$4)-SUMIFS(Transactions!$F$5:$F$1504,Transactions!$D$5:$D$1504,$A10,Transactions!$L$5:$L$1504,H$4)) | I10: =IF($A10="",0,SUMIFS(Transactions!$E$5:$E$1504,Transactions!$D$5:$D$1504,$A10,Transactions!$L$5:$L$1504,I$4)-SUMIFS(Transactions!$F$5:$F$1504,Transactions!$D$5:$D$1504,$A10,Transactions!$L$5:$L$1504,I$4)) | ... M10: =IF($A10="",0,SUMIFS(Transactions!$E$5:$E$1504,Transactions!$D$5:$D$1504,$A10,Transactions!$L$5:$L$1504,M$4)-SUMIFS(Transactions!$F$5:$F$1504,Transactions!$D$5:$D$1504,$A10,Transactions!$L$5:$L$1504,M$4)) | N10: =SUM(B10:M10)
A11: Total revenue | B11: =SUM(B6:B10) | C11: =SUM(C6:C10) | D11: =SUM(D6:D10) | E11: =SUM(E6:E10) | F11: =SUM(F6:F10) | G11: =SUM(G6:G10) | H11: =SUM(H6:H10) | I11: =SUM(I6:I10) | ... N11: =SUM(N6:N10)
A13: DIRECT COSTS (cost of delivering the service)
A14: =IF(Setup!$A$29="","",Setup!$A$29) | B14: =IF($A14="",0,SUMIFS(Transactions!$F$5:$F$1504,Transactions!$D$5:$D$1504,$A14,Transactions!$L$5:$L$1504,B$4)-SUMIFS(Transactions!$E$5:$E$1504,Transactions!$D$5:$D$1504,$A14,Transactions!$L$5:$L$1504,B$4)) | C14: =IF($A14="",0,SUMIFS(Transactions!$F$5:$F$1504,Transactions!$D$5:$D$1504,$A14,Transactions!$L$5:$L$1504,C$4)-SUMIFS(Transactions!$E$5:$E$1504,Transactions!$D$5:$D$1504,$A14,Transactions!$L$5:$L$1504,C$4)) | D14: =IF($A14="",0,SUMIFS(Transactions!$F$5:$F$1504,Transactions!$D$5:$D$1504,$A14,Transactions!$L$5:$L$1504,D$4)-SUMIFS(Transactions!$E$5:$E$1504,Transactions!$D$5:$D$1504,$A14,Transactions!$L$5:$L$1504,D$4)) | E14: =IF($A14="",0,SUMIFS(Transactions!$F$5:$F$1504,Transactions!$D$5:$D$1504,$A14,Transactions!$L$5:$L$1504,E$4)-SUMIFS(Transactions!$E$5:$E$1504,Transactions!$D$5:$D$1504,$A14,Transactions!$L$5:$L$1504,E$4)) | F14: =IF($A14="",0,SUMIFS(Transactions!$F$5:$F$1504,Transactions!$D$5:$D$1504,$A14,Transactions!$L$5:$L$1504,F$4)-SUMIFS(Transactions!$E$5:$E$1504,Transactions!$D$5:$D$1504,$A14,Transactions!$L$5:$L$1504,F$4)) | G14: =IF($A14="",0,SUMIFS(Transactions!$F$5:$F$1504,Transactions!$D$5:$D$1504,$A14,Transactions!$L$5:$L$1504,G$4)-SUMIFS(Transactions!$E$5:$E$1504,Transactions!$D$5:$D$1504,$A14,Transactions!$L$5:$L$1504,G$4)) | H14: =IF($A14="",0,SUMIFS(Transactions!$F$5:$F$1504,Transactions!$D$5:$D$1504,$A14,Transactions!$L$5:$L$1504,H$4)-SUMIFS(Transactions!$E$5:$E$1504,Transactions!$D$5:$D$1504,$A14,Transactions!$L$5:$L$1504,H$4)) | I14: =IF($A14="",0,SUMIFS(Transactions!$F$5:$F$1504,Transactions!$D$5:$D$1504,$A14,Transactions!$L$5:$L$1504,I$4)-SUMIFS(Transactions!$E$5:$E$1504,Transactions!$D$5:$D$1504,$A14,Transactions!$L$5:$L$1504,I$4)) | ... M14: =IF($A14="",0,SUMIFS(Transactions!$F$5:$F$1504,Transactions!$D$5:$D$1504,$A14,Transactions!$L$5:$L$1504,M$4)-SUMIFS(Transactions!$E$5:$E$1504,Transactions!$D$5:$D$1504,$A14,Transactions!$L$5:$L$1504,M$4)) | N14: =SUM(B14:M14)
A15: =IF(Setup!$A$30="","",Setup!$A$30) | B15: =IF($A15="",0,SUMIFS(Transactions!$F$5:$F$1504,Transactions!$D$5:$D$1504,$A15,Transactions!$L$5:$L$1504,B$4)-SUMIFS(Transactions!$E$5:$E$1504,Transactions!$D$5:$D$1504,$A15,Transactions!$L$5:$L$1504,B$4)) | C15: =IF($A15="",0,SUMIFS(Transactions!$F$5:$F$1504,Transactions!$D$5:$D$1504,$A15,Transactions!$L$5:$L$1504,C$4)-SUMIFS(Transactions!$E$5:$E$1504,Transactions!$D$5:$D$1504,$A15,Transactions!$L$5:$L$1504,C$4)) | D15: =IF($A15="",0,SUMIFS(Transactions!$F$5:$F$1504,Transactions!$D$5:$D$1504,$A15,Transactions!$L$5:$L$1504,D$4)-SUMIFS(Transactions!$E$5:$E$1504,Transactions!$D$5:$D$1504,$A15,Transactions!$L$5:$L$1504,D$4)) | E15: =IF($A15="",0,SUMIFS(Transactions!$F$5:$F$1504,Transactions!$D$5:$D$1504,$A15,Transactions!$L$5:$L$1504,E$4)-SUMIFS(Transactions!$E$5:$E$1504,Transactions!$D$5:$D$1504,$A15,Transactions!$L$5:$L$1504,E$4)) | F15: =IF($A15="",0,SUMIFS(Transactions!$F$5:$F$1504,Transactions!$D$5:$D$1504,$A15,Transactions!$L$5:$L$1504,F$4)-SUMIFS(Transactions!$E$5:$E$1504,Transactions!$D$5:$D$1504,$A15,Transactions!$L$5:$L$1504,F$4)) | G15: =IF($A15="",0,SUMIFS(Transactions!$F$5:$F$1504,Transactions!$D$5:$D$1504,$A15,Transactions!$L$5:$L$1504,G$4)-SUMIFS(Transactions!$E$5:$E$1504,Transactions!$D$5:$D$1504,$A15,Transactions!$L$5:$L$1504,G$4)) | H15: =IF($A15="",0,SUMIFS(Transactions!$F$5:$F$1504,Transactions!$D$5:$D$1504,$A15,Transactions!$L$5:$L$1504,H$4)-SUMIFS(Transactions!$E$5:$E$1504,Transactions!$D$5:$D$1504,$A15,Transactions!$L$5:$L$1504,H$4)) | I15: =IF($A15="",0,SUMIFS(Transactions!$F$5:$F$1504,Transactions!$D$5:$D$1504,$A15,Transactions!$L$5:$L$1504,I$4)-SUMIFS(Transactions!$E$5:$E$1504,Transactions!$D$5:$D$1504,$A15,Transactions!$L$5:$L$1504,I$4)) | ... M15: =IF($A15="",0,SUMIFS(Transactions!$F$5:$F$1504,Transactions!$D$5:$D$1504,$A15,Transactions!$L$5:$L$1504,M$4)-SUMIFS(Transactions!$E$5:$E$1504,Transactions!$D$5:$D$1504,$A15,Transactions!$L$5:$L$1504,M$4)) | N15: =SUM(B15:M15)
A16: =IF(Setup!$A$31="","",Setup!$A$31) | B16: =IF($A16="",0,SUMIFS(Transactions!$F$5:$F$1504,Transactions!$D$5:$D$1504,$A16,Transactions!$L$5:$L$1504,B$4)-SUMIFS(Transactions!$E$5:$E$1504,Transactions!$D$5:$D$1504,$A16,Transactions!$L$5:$L$1504,B$4)) | C16: =IF($A16="",0,SUMIFS(Transactions!$F$5:$F$1504,Transactions!$D$5:$D$1504,$A16,Transactions!$L$5:$L$1504,C$4)-SUMIFS(Transactions!$E$5:$E$1504,Transactions!$D$5:$D$1504,$A16,Transactions!$L$5:$L$1504,C$4)) | D16: =IF($A16="",0,SUMIFS(Transactions!$F$5:$F$1504,Transactions!$D$5:$D$1504,$A16,Transactions!$L$5:$L$1504,D$4)-SUMIFS(Transactions!$E$5:$E$1504,Transactions!$D$5:$D$1504,$A16,Transactions!$L$5:$L$1504,D$4)) | E16: =IF($A16="",0,SUMIFS(Transactions!$F$5:$F$1504,Transactions!$D$5:$D$1504,$A16,Transactions!$L$5:$L$1504,E$4)-SUMIFS(Transactions!$E$5:$E$1504,Transactions!$D$5:$D$1504,$A16,Transactions!$L$5:$L$1504,E$4)) | F16: =IF($A16="",0,SUMIFS(Transactions!$F$5:$F$1504,Transactions!$D$5:$D$1504,$A16,Transactions!$L$5:$L$1504,F$4)-SUMIFS(Transactions!$E$5:$E$1504,Transactions!$D$5:$D$1504,$A16,Transactions!$L$5:$L$1504,F$4)) | G16: =IF($A16="",0,SUMIFS(Transactions!$F$5:$F$1504,Transactions!$D$5:$D$1504,$A16,Transactions!$L$5:$L$1504,G$4)-SUMIFS(Transactions!$E$5:$E$1504,Transactions!$D$5:$D$1504,$A16,Transactions!$L$5:$L$1504,G$4)) | H16: =IF($A16="",0,SUMIFS(Transactions!$F$5:$F$1504,Transactions!$D$5:$D$1504,$A16,Transactions!$L$5:$L$1504,H$4)-SUMIFS(Transactions!$E$5:$E$1504,Transactions!$D$5:$D$1504,$A16,Transactions!$L$5:$L$1504,H$4)) | I16: =IF($A16="",0,SUMIFS(Transactions!$F$5:$F$1504,Transactions!$D$5:$D$1504,$A16,Transactions!$L$5:$L$1504,I$4)-SUMIFS(Transactions!$E$5:$E$1504,Transactions!$D$5:$D$1504,$A16,Transactions!$L$5:$L$1504,I$4)) | ... M16: =IF($A16="",0,SUMIFS(Transactions!$F$5:$F$1504,Transactions!$D$5:$D$1504,$A16,Transactions!$L$5:$L$1504,M$4)-SUMIFS(Transactions!$E$5:$E$1504,Transactions!$D$5:$D$1504,$A16,Transactions!$L$5:$L$1504,M$4)) | N16: =SUM(B16:M16)
A17: =IF(Setup!$A$32="","",Setup!$A$32) | B17: =IF($A17="",0,SUMIFS(Transactions!$F$5:$F$1504,Transactions!$D$5:$D$1504,$A17,Transactions!$L$5:$L$1504,B$4)-SUMIFS(Transactions!$E$5:$E$1504,Transactions!$D$5:$D$1504,$A17,Transactions!$L$5:$L$1504,B$4)) | C17: =IF($A17="",0,SUMIFS(Transactions!$F$5:$F$1504,Transactions!$D$5:$D$1504,$A17,Transactions!$L$5:$L$1504,C$4)-SUMIFS(Transactions!$E$5:$E$1504,Transactions!$D$5:$D$1504,$A17,Transactions!$L$5:$L$1504,C$4)) | D17: =IF($A17="",0,SUMIFS(Transactions!$F$5:$F$1504,Transactions!$D$5:$D$1504,$A17,Transactions!$L$5:$L$1504,D$4)-SUMIFS(Transactions!$E$5:$E$1504,Transactions!$D$5:$D$1504,$A17,Transactions!$L$5:$L$1504,D$4)) | E17: =IF($A17="",0,SUMIFS(Transactions!$F$5:$F$1504,Transactions!$D$5:$D$1504,$A17,Transactions!$L$5:$L$1504,E$4)-SUMIFS(Transactions!$E$5:$E$1504,Transactions!$D$5:$D$1504,$A17,Transactions!$L$5:$L$1504,E$4)) | F17: =IF($A17="",0,SUMIFS(Transactions!$F$5:$F$1504,Transactions!$D$5:$D$1504,$A17,Transactions!$L$5:$L$1504,F$4)-SUMIFS(Transactions!$E$5:$E$1504,Transactions!$D$5:$D$1504,$A17,Transactions!$L$5:$L$1504,F$4)) | G17: =IF($A17="",0,SUMIFS(Transactions!$F$5:$F$1504,Transactions!$D$5:$D$1504,$A17,Transactions!$L$5:$L$1504,G$4)-SUMIFS(Transactions!$E$5:$E$1504,Transactions!$D$5:$D$1504,$A17,Transactions!$L$5:$L$1504,G$4)) | H17: =IF($A17="",0,SUMIFS(Transactions!$F$5:$F$1504,Transactions!$D$5:$D$1504,$A17,Transactions!$L$5:$L$1504,H$4)-SUMIFS(Transactions!$E$5:$E$1504,Transactions!$D$5:$D$1504,$A17,Transactions!$L$5:$L$1504,H$4)) | I17: =IF($A17="",0,SUMIFS(Transactions!$F$5:$F$1504,Transactions!$D$5:$D$1504,$A17,Transactions!$L$5:$L$1504,I$4)-SUMIFS(Transactions!$E$5:$E$1504,Transactions!$D$5:$D$1504,$A17,Transactions!$L$5:$L$1504,I$4)) | ... M17: =IF($A17="",0,SUMIFS(Transactions!$F$5:$F$1504,Transactions!$D$5:$D$1504,$A17,Transactions!$L$5:$L$1504,M$4)-SUMIFS(Transactions!$E$5:$E$1504,Transactions!$D$5:$D$1504,$A17,Transactions!$L$5:$L$1504,M$4)) | N17: =SUM(B17:M17)
A18: =IF(Setup!$A$33="","",Setup!$A$33) | B18: =IF($A18="",0,SUMIFS(Transactions!$F$5:$F$1504,Transactions!$D$5:$D$1504,$A18,Transactions!$L$5:$L$1504,B$4)-SUMIFS(Transactions!$E$5:$E$1504,Transactions!$D$5:$D$1504,$A18,Transactions!$L$5:$L$1504,B$4)) | C18: =IF($A18="",0,SUMIFS(Transactions!$F$5:$F$1504,Transactions!$D$5:$D$1504,$A18,Transactions!$L$5:$L$1504,C$4)-SUMIFS(Transactions!$E$5:$E$1504,Transactions!$D$5:$D$1504,$A18,Transactions!$L$5:$L$1504,C$4)) | D18: =IF($A18="",0,SUMIFS(Transactions!$F$5:$F$1504,Transactions!$D$5:$D$1504,$A18,Transactions!$L$5:$L$1504,D$4)-SUMIFS(Transactions!$E$5:$E$1504,Transactions!$D$5:$D$1504,$A18,Transactions!$L$5:$L$1504,D$4)) | E18: =IF($A18="",0,SUMIFS(Transactions!$F$5:$F$1504,Transactions!$D$5:$D$1504,$A18,Transactions!$L$5:$L$1504,E$4)-SUMIFS(Transactions!$E$5:$E$1504,Transactions!$D$5:$D$1504,$A18,Transactions!$L$5:$L$1504,E$4)) | F18: =IF($A18="",0,SUMIFS(Transactions!$F$5:$F$1504,Transactions!$D$5:$D$1504,$A18,Transactions!$L$5:$L$1504,F$4)-SUMIFS(Transactions!$E$5:$E$1504,Transactions!$D$5:$D$1504,$A18,Transactions!$L$5:$L$1504,F$4)) | G18: =IF($A18="",0,SUMIFS(Transactions!$F$5:$F$1504,Transactions!$D$5:$D$1504,$A18,Transactions!$L$5:$L$1504,G$4)-SUMIFS(Transactions!$E$5:$E$1504,Transactions!$D$5:$D$1504,$A18,Transactions!$L$5:$L$1504,G$4)) | H18: =IF($A18="",0,SUMIFS(Transactions!$F$5:$F$1504,Transactions!$D$5:$D$1504,$A18,Transactions!$L$5:$L$1504,H$4)-SUMIFS(Transactions!$E$5:$E$1504,Transactions!$D$5:$D$1504,$A18,Transactions!$L$5:$L$1504,H$4)) | I18: =IF($A18="",0,SUMIFS(Transactions!$F$5:$F$1504,Transactions!$D$5:$D$1504,$A18,Transactions!$L$5:$L$1504,I$4)-SUMIFS(Transactions!$E$5:$E$1504,Transactions!$D$5:$D$1504,$A18,Transactions!$L$5:$L$1504,I$4)) | ... M18: =IF($A18="",0,SUMIFS(Transactions!$F$5:$F$1504,Transactions!$D$5:$D$1504,$A18,Transactions!$L$5:$L$1504,M$4)-SUMIFS(Transactions!$E$5:$E$1504,Transactions!$D$5:$D$1504,$A18,Transactions!$L$5:$L$1504,M$4)) | N18: =SUM(B18:M18)
A19: Total direct costs | B19: =SUM(B14:B18) | C19: =SUM(C14:C18) | D19: =SUM(D14:D18) | E19: =SUM(E14:E18) | F19: =SUM(F14:F18) | G19: =SUM(G14:G18) | H19: =SUM(H14:H18) | I19: =SUM(I14:I18) | ... N19: =SUM(N14:N18)
A21: GROSS PROFIT (revenue − direct costs) | B21: =B11-B19 | C21: =C11-C19 | D21: =D11-D19 | E21: =E11-E19 | F21: =F11-F19 | G21: =G11-G19 | H21: =H11-H19 | I21: =I11-I19 | ... N21: =N11-N19
A22: Gross margin % | B22: =IF(B11=0,0,B21/B11) | C22: =IF(C11=0,0,C21/C11) | D22: =IF(D11=0,0,D21/D11) | E22: =IF(E11=0,0,E21/E11) | F22: =IF(F11=0,0,F21/F11) | G22: =IF(G11=0,0,G21/G11) | H22: =IF(H11=0,0,H21/H11) | I22: =IF(I11=0,0,I21/I11) | ... N22: =IF(N11=0,0,N21/N11)
A24: OPERATING EXPENSES (overheads)
A25: =IF(Setup!$A$34="","",Setup!$A$34) | B25: =IF($A25="",0,SUMIFS(Transactions!$F$5:$F$1504,Transactions!$D$5:$D$1504,$A25,Transactions!$L$5:$L$1504,B$4)-SUMIFS(Transactions!$E$5:$E$1504,Transactions!$D$5:$D$1504,$A25,Transactions!$L$5:$L$1504,B$4)) | C25: =IF($A25="",0,SUMIFS(Transactions!$F$5:$F$1504,Transactions!$D$5:$D$1504,$A25,Transactions!$L$5:$L$1504,C$4)-SUMIFS(Transactions!$E$5:$E$1504,Transactions!$D$5:$D$1504,$A25,Transactions!$L$5:$L$1504,C$4)) | D25: =IF($A25="",0,SUMIFS(Transactions!$F$5:$F$1504,Transactions!$D$5:$D$1504,$A25,Transactions!$L$5:$L$1504,D$4)-SUMIFS(Transactions!$E$5:$E$1504,Transactions!$D$5:$D$1504,$A25,Transactions!$L$5:$L$1504,D$4)) | E25: =IF($A25="",0,SUMIFS(Transactions!$F$5:$F$1504,Transactions!$D$5:$D$1504,$A25,Transactions!$L$5:$L$1504,E$4)-SUMIFS(Transactions!$E$5:$E$1504,Transactions!$D$5:$D$1504,$A25,Transactions!$L$5:$L$1504,E$4)) | F25: =IF($A25="",0,SUMIFS(Transactions!$F$5:$F$1504,Transactions!$D$5:$D$1504,$A25,Transactions!$L$5:$L$1504,F$4)-SUMIFS(Transactions!$E$5:$E$1504,Transactions!$D$5:$D$1504,$A25,Transactions!$L$5:$L$1504,F$4)) | G25: =IF($A25="",0,SUMIFS(Transactions!$F$5:$F$1504,Transactions!$D$5:$D$1504,$A25,Transactions!$L$5:$L$1504,G$4)-SUMIFS(Transactions!$E$5:$E$1504,Transactions!$D$5:$D$1504,$A25,Transactions!$L$5:$L$1504,G$4)) | H25: =IF($A25="",0,SUMIFS(Transactions!$F$5:$F$1504,Transactions!$D$5:$D$1504,$A25,Transactions!$L$5:$L$1504,H$4)-SUMIFS(Transactions!$E$5:$E$1504,Transactions!$D$5:$D$1504,$A25,Transactions!$L$5:$L$1504,H$4)) | I25: =IF($A25="",0,SUMIFS(Transactions!$F$5:$F$1504,Transactions!$D$5:$D$1504,$A25,Transactions!$L$5:$L$1504,I$4)-SUMIFS(Transactions!$E$5:$E$1504,Transactions!$D$5:$D$1504,$A25,Transactions!$L$5:$L$1504,I$4)) | ... M25: =IF($A25="",0,SUMIFS(Transactions!$F$5:$F$1504,Transactions!$D$5:$D$1504,$A25,Transactions!$L$5:$L$1504,M$4)-SUMIFS(Transactions!$E$5:$E$1504,Transactions!$D$5:$D$1504,$A25,Transactions!$L$5:$L$1504,M$4)) | N25: =SUM(B25:M25)
A26: =IF(Setup!$A$35="","",Setup!$A$35) | B26: =IF($A26="",0,SUMIFS(Transactions!$F$5:$F$1504,Transactions!$D$5:$D$1504,$A26,Transactions!$L$5:$L$1504,B$4)-SUMIFS(Transactions!$E$5:$E$1504,Transactions!$D$5:$D$1504,$A26,Transactions!$L$5:$L$1504,B$4)) | C26: =IF($A26="",0,SUMIFS(Transactions!$F$5:$F$1504,Transactions!$D$5:$D$1504,$A26,Transactions!$L$5:$L$1504,C$4)-SUMIFS(Transactions!$E$5:$E$1504,Transactions!$D$5:$D$1504,$A26,Transactions!$L$5:$L$1504,C$4)) | D26: =IF($A26="",0,SUMIFS(Transactions!$F$5:$F$1504,Transactions!$D$5:$D$1504,$A26,Transactions!$L$5:$L$1504,D$4)-SUMIFS(Transactions!$E$5:$E$1504,Transactions!$D$5:$D$1504,$A26,Transactions!$L$5:$L$1504,D$4)) | E26: =IF($A26="",0,SUMIFS(Transactions!$F$5:$F$1504,Transactions!$D$5:$D$1504,$A26,Transactions!$L$5:$L$1504,E$4)-SUMIFS(Transactions!$E$5:$E$1504,Transactions!$D$5:$D$1504,$A26,Transactions!$L$5:$L$1504,E$4)) | F26: =IF($A26="",0,SUMIFS(Transactions!$F$5:$F$1504,Transactions!$D$5:$D$1504,$A26,Transactions!$L$5:$L$1504,F$4)-SUMIFS(Transactions!$E$5:$E$1504,Transactions!$D$5:$D$1504,$A26,Transactions!$L$5:$L$1504,F$4)) | G26: =IF($A26="",0,SUMIFS(Transactions!$F$5:$F$1504,Transactions!$D$5:$D$1504,$A26,Transactions!$L$5:$L$1504,G$4)-SUMIFS(Transactions!$E$5:$E$1504,Transactions!$D$5:$D$1504,$A26,Transactions!$L$5:$L$1504,G$4)) | H26: =IF($A26="",0,SUMIFS(Transactions!$F$5:$F$1504,Transactions!$D$5:$D$1504,$A26,Transactions!$L$5:$L$1504,H$4)-SUMIFS(Transactions!$E$5:$E$1504,Transactions!$D$5:$D$1504,$A26,Transactions!$L$5:$L$1504,H$4)) | I26: =IF($A26="",0,SUMIFS(Transactions!$F$5:$F$1504,Transactions!$D$5:$D$1504,$A26,Transactions!$L$5:$L$1504,I$4)-SUMIFS(Transactions!$E$5:$E$1504,Transactions!$D$5:$D$1504,$A26,Transactions!$L$5:$L$1504,I$4)) | ... M26: =IF($A26="",0,SUMIFS(Transactions!$F$5:$F$1504,Transactions!$D$5:$D$1504,$A26,Transactions!$L$5:$L$1504,M$4)-SUMIFS(Transactions!$E$5:$E$1504,Transactions!$D$5:$D$1504,$A26,Transactions!$L$5:$L$1504,M$4)) | N26: =SUM(B26:M26)
A27: =IF(Setup!$A$36="","",Setup!$A$36) | B27: =IF($A27="",0,SUMIFS(Transactions!$F$5:$F$1504,Transactions!$D$5:$D$1504,$A27,Transactions!$L$5:$L$1504,B$4)-SUMIFS(Transactions!$E$5:$E$1504,Transactions!$D$5:$D$1504,$A27,Transactions!$L$5:$L$1504,B$4)) | C27: =IF($A27="",0,SUMIFS(Transactions!$F$5:$F$1504,Transactions!$D$5:$D$1504,$A27,Transactions!$L$5:$L$1504,C$4)-SUMIFS(Transactions!$E$5:$E$1504,Transactions!$D$5:$D$1504,$A27,Transactions!$L$5:$L$1504,C$4)) | D27: =IF($A27="",0,SUMIFS(Transactions!$F$5:$F$1504,Transactions!$D$5:$D$1504,$A27,Transactions!$L$5:$L$1504,D$4)-SUMIFS(Transactions!$E$5:$E$1504,Transactions!$D$5:$D$1504,$A27,Transactions!$L$5:$L$1504,D$4)) | E27: =IF($A27="",0,SUMIFS(Transactions!$F$5:$F$1504,Transactions!$D$5:$D$1504,$A27,Transactions!$L$5:$L$1504,E$4)-SUMIFS(Transactions!$E$5:$E$1504,Transactions!$D$5:$D$1504,$A27,Transactions!$L$5:$L$1504,E$4)) | F27: =IF($A27="",0,SUMIFS(Transactions!$F$5:$F$1504,Transactions!$D$5:$D$1504,$A27,Transactions!$L$5:$L$1504,F$4)-SUMIFS(Transactions!$E$5:$E$1504,Transactions!$D$5:$D$1504,$A27,Transactions!$L$5:$L$1504,F$4)) | G27: =IF($A27="",0,SUMIFS(Transactions!$F$5:$F$1504,Transactions!$D$5:$D$1504,$A27,Transactions!$L$5:$L$1504,G$4)-SUMIFS(Transactions!$E$5:$E$1504,Transactions!$D$5:$D$1504,$A27,Transactions!$L$5:$L$1504,G$4)) | H27: =IF($A27="",0,SUMIFS(Transactions!$F$5:$F$1504,Transactions!$D$5:$D$1504,$A27,Transactions!$L$5:$L$1504,H$4)-SUMIFS(Transactions!$E$5:$E$1504,Transactions!$D$5:$D$1504,$A27,Transactions!$L$5:$L$1504,H$4)) | I27: =IF($A27="",0,SUMIFS(Transactions!$F$5:$F$1504,Transactions!$D$5:$D$1504,$A27,Transactions!$L$5:$L$1504,I$4)-SUMIFS(Transactions!$E$5:$E$1504,Transactions!$D$5:$D$1504,$A27,Transactions!$L$5:$L$1504,I$4)) | ... M27: =IF($A27="",0,SUMIFS(Transactions!$F$5:$F$1504,Transactions!$D$5:$D$1504,$A27,Transactions!$L$5:$L$1504,M$4)-SUMIFS(Transactions!$E$5:$E$1504,Transactions!$D$5:$D$1504,$A27,Transactions!$L$5:$L$1504,M$4)) | N27: =SUM(B27:M27)
A28: =IF(Setup!$A$37="","",Setup!$A$37) | B28: =IF($A28="",0,SUMIFS(Transactions!$F$5:$F$1504,Transactions!$D$5:$D$1504,$A28,Transactions!$L$5:$L$1504,B$4)-SUMIFS(Transactions!$E$5:$E$1504,Transactions!$D$5:$D$1504,$A28,Transactions!$L$5:$L$1504,B$4)) | C28: =IF($A28="",0,SUMIFS(Transactions!$F$5:$F$1504,Transactions!$D$5:$D$1504,$A28,Transactions!$L$5:$L$1504,C$4)-SUMIFS(Transactions!$E$5:$E$1504,Transactions!$D$5:$D$1504,$A28,Transactions!$L$5:$L$1504,C$4)) | D28: =IF($A28="",0,SUMIFS(Transactions!$F$5:$F$1504,Transactions!$D$5:$D$1504,$A28,Transactions!$L$5:$L$1504,D$4)-SUMIFS(Transactions!$E$5:$E$1504,Transactions!$D$5:$D$1504,$A28,Transactions!$L$5:$L$1504,D$4)) | E28: =IF($A28="",0,SUMIFS(Transactions!$F$5:$F$1504,Transactions!$D$5:$D$1504,$A28,Transactions!$L$5:$L$1504,E$4)-SUMIFS(Transactions!$E$5:$E$1504,Transactions!$D$5:$D$1504,$A28,Transactions!$L$5:$L$1504,E$4)) | F28: =IF($A28="",0,SUMIFS(Transactions!$F$5:$F$1504,Transactions!$D$5:$D$1504,$A28,Transactions!$L$5:$L$1504,F$4)-SUMIFS(Transactions!$E$5:$E$1504,Transactions!$D$5:$D$1504,$A28,Transactions!$L$5:$L$1504,F$4)) | G28: =IF($A28="",0,SUMIFS(Transactions!$F$5:$F$1504,Transactions!$D$5:$D$1504,$A28,Transactions!$L$5:$L$1504,G$4)-SUMIFS(Transactions!$E$5:$E$1504,Transactions!$D$5:$D$1504,$A28,Transactions!$L$5:$L$1504,G$4)) | H28: =IF($A28="",0,SUMIFS(Transactions!$F$5:$F$1504,Transactions!$D$5:$D$1504,$A28,Transactions!$L$5:$L$1504,H$4)-SUMIFS(Transactions!$E$5:$E$1504,Transactions!$D$5:$D$1504,$A28,Transactions!$L$5:$L$1504,H$4)) | I28: =IF($A28="",0,SUMIFS(Transactions!$F$5:$F$1504,Transactions!$D$5:$D$1504,$A28,Transactions!$L$5:$L$1504,I$4)-SUMIFS(Transactions!$E$5:$E$1504,Transactions!$D$5:$D$1504,$A28,Transactions!$L$5:$L$1504,I$4)) | ... M28: =IF($A28="",0,SUMIFS(Transactions!$F$5:$F$1504,Transactions!$D$5:$D$1504,$A28,Transactions!$L$5:$L$1504,M$4)-SUMIFS(Transactions!$E$5:$E$1504,Transactions!$D$5:$D$1504,$A28,Transactions!$L$5:$L$1504,M$4)) | N28: =SUM(B28:M28)
A29: =IF(Setup!$A$38="","",Setup!$A$38) | B29: =IF($A29="",0,SUMIFS(Transactions!$F$5:$F$1504,Transactions!$D$5:$D$1504,$A29,Transactions!$L$5:$L$1504,B$4)-SUMIFS(Transactions!$E$5:$E$1504,Transactions!$D$5:$D$1504,$A29,Transactions!$L$5:$L$1504,B$4)) | C29: =IF($A29="",0,SUMIFS(Transactions!$F$5:$F$1504,Transactions!$D$5:$D$1504,$A29,Transactions!$L$5:$L$1504,C$4)-SUMIFS(Transactions!$E$5:$E$1504,Transactions!$D$5:$D$1504,$A29,Transactions!$L$5:$L$1504,C$4)) | D29: =IF($A29="",0,SUMIFS(Transactions!$F$5:$F$1504,Transactions!$D$5:$D$1504,$A29,Transactions!$L$5:$L$1504,D$4)-SUMIFS(Transactions!$E$5:$E$1504,Transactions!$D$5:$D$1504,$A29,Transactions!$L$5:$L$1504,D$4)) | E29: =IF($A29="",0,SUMIFS(Transactions!$F$5:$F$1504,Transactions!$D$5:$D$1504,$A29,Transactions!$L$5:$L$1504,E$4)-SUMIFS(Transactions!$E$5:$E$1504,Transactions!$D$5:$D$1504,$A29,Transactions!$L$5:$L$1504,E$4)) | F29: =IF($A29="",0,SUMIFS(Transactions!$F$5:$F$1504,Transactions!$D$5:$D$1504,$A29,Transactions!$L$5:$L$1504,F$4)-SUMIFS(Transactions!$E$5:$E$1504,Transactions!$D$5:$D$1504,$A29,Transactions!$L$5:$L$1504,F$4)) | G29: =IF($A29="",0,SUMIFS(Transactions!$F$5:$F$1504,Transactions!$D$5:$D$1504,$A29,Transactions!$L$5:$L$1504,G$4)-SUMIFS(Transactions!$E$5:$E$1504,Transactions!$D$5:$D$1504,$A29,Transactions!$L$5:$L$1504,G$4)) | H29: =IF($A29="",0,SUMIFS(Transactions!$F$5:$F$1504,Transactions!$D$5:$D$1504,$A29,Transactions!$L$5:$L$1504,H$4)-SUMIFS(Transactions!$E$5:$E$1504,Transactions!$D$5:$D$1504,$A29,Transactions!$L$5:$L$1504,H$4)) | I29: =IF($A29="",0,SUMIFS(Transactions!$F$5:$F$1504,Transactions!$D$5:$D$1504,$A29,Transactions!$L$5:$L$1504,I$4)-SUMIFS(Transactions!$E$5:$E$1504,Transactions!$D$5:$D$1504,$A29,Transactions!$L$5:$L$1504,I$4)) | ... M29: =IF($A29="",0,SUMIFS(Transactions!$F$5:$F$1504,Transactions!$D$5:$D$1504,$A29,Transactions!$L$5:$L$1504,M$4)-SUMIFS(Transactions!$E$5:$E$1504,Transactions!$D$5:$D$1504,$A29,Transactions!$L$5:$L$1504,M$4)) | N29: =SUM(B29:M29)
A30: =IF(Setup!$A$39="","",Setup!$A$39) | B30: =IF($A30="",0,SUMIFS(Transactions!$F$5:$F$1504,Transactions!$D$5:$D$1504,$A30,Transactions!$L$5:$L$1504,B$4)-SUMIFS(Transactions!$E$5:$E$1504,Transactions!$D$5:$D$1504,$A30,Transactions!$L$5:$L$1504,B$4)) | C30: =IF($A30="",0,SUMIFS(Transactions!$F$5:$F$1504,Transactions!$D$5:$D$1504,$A30,Transactions!$L$5:$L$1504,C$4)-SUMIFS(Transactions!$E$5:$E$1504,Transactions!$D$5:$D$1504,$A30,Transactions!$L$5:$L$1504,C$4)) | D30: =IF($A30="",0,SUMIFS(Transactions!$F$5:$F$1504,Transactions!$D$5:$D$1504,$A30,Transactions!$L$5:$L$1504,D$4)-SUMIFS(Transactions!$E$5:$E$1504,Transactions!$D$5:$D$1504,$A30,Transactions!$L$5:$L$1504,D$4)) | E30: =IF($A30="",0,SUMIFS(Transactions!$F$5:$F$1504,Transactions!$D$5:$D$1504,$A30,Transactions!$L$5:$L$1504,E$4)-SUMIFS(Transactions!$E$5:$E$1504,Transactions!$D$5:$D$1504,$A30,Transactions!$L$5:$L$1504,E$4)) | F30: =IF($A30="",0,SUMIFS(Transactions!$F$5:$F$1504,Transactions!$D$5:$D$1504,$A30,Transactions!$L$5:$L$1504,F$4)-SUMIFS(Transactions!$E$5:$E$1504,Transactions!$D$5:$D$1504,$A30,Transactions!$L$5:$L$1504,F$4)) | G30: =IF($A30="",0,SUMIFS(Transactions!$F$5:$F$1504,Transactions!$D$5:$D$1504,$A30,Transactions!$L$5:$L$1504,G$4)-SUMIFS(Transactions!$E$5:$E$1504,Transactions!$D$5:$D$1504,$A30,Transactions!$L$5:$L$1504,G$4)) | H30: =IF($A30="",0,SUMIFS(Transactions!$F$5:$F$1504,Transactions!$D$5:$D$1504,$A30,Transactions!$L$5:$L$1504,H$4)-SUMIFS(Transactions!$E$5:$E$1504,Transactions!$D$5:$D$1504,$A30,Transactions!$L$5:$L$1504,H$4)) | I30: =IF($A30="",0,SUMIFS(Transactions!$F$5:$F$1504,Transactions!$D$5:$D$1504,$A30,Transactions!$L$5:$L$1504,I$4)-SUMIFS(Transactions!$E$5:$E$1504,Transactions!$D$5:$D$1504,$A30,Transactions!$L$5:$L$1504,I$4)) | ... M30: =IF($A30="",0,SUMIFS(Transactions!$F$5:$F$1504,Transactions!$D$5:$D$1504,$A30,Transactions!$L$5:$L$1504,M$4)-SUMIFS(Transactions!$E$5:$E$1504,Transactions!$D$5:$D$1504,$A30,Transactions!$L$5:$L$1504,M$4)) | N30: =SUM(B30:M30)
A31: =IF(Setup!$A$40="","",Setup!$A$40) | B31: =IF($A31="",0,SUMIFS(Transactions!$F$5:$F$1504,Transactions!$D$5:$D$1504,$A31,Transactions!$L$5:$L$1504,B$4)-SUMIFS(Transactions!$E$5:$E$1504,Transactions!$D$5:$D$1504,$A31,Transactions!$L$5:$L$1504,B$4)) | C31: =IF($A31="",0,SUMIFS(Transactions!$F$5:$F$1504,Transactions!$D$5:$D$1504,$A31,Transactions!$L$5:$L$1504,C$4)-SUMIFS(Transactions!$E$5:$E$1504,Transactions!$D$5:$D$1504,$A31,Transactions!$L$5:$L$1504,C$4)) | D31: =IF($A31="",0,SUMIFS(Transactions!$F$5:$F$1504,Transactions!$D$5:$D$1504,$A31,Transactions!$L$5:$L$1504,D$4)-SUMIFS(Transactions!$E$5:$E$1504,Transactions!$D$5:$D$1504,$A31,Transactions!$L$5:$L$1504,D$4)) | E31: =IF($A31="",0,SUMIFS(Transactions!$F$5:$F$1504,Transactions!$D$5:$D$1504,$A31,Transactions!$L$5:$L$1504,E$4)-SUMIFS(Transactions!$E$5:$E$1504,Transactions!$D$5:$D$1504,$A31,Transactions!$L$5:$L$1504,E$4)) | F31: =IF($A31="",0,SUMIFS(Transactions!$F$5:$F$1504,Transactions!$D$5:$D$1504,$A31,Transactions!$L$5:$L$1504,F$4)-SUMIFS(Transactions!$E$5:$E$1504,Transactions!$D$5:$D$1504,$A31,Transactions!$L$5:$L$1504,F$4)) | G31: =IF($A31="",0,SUMIFS(Transactions!$F$5:$F$1504,Transactions!$D$5:$D$1504,$A31,Transactions!$L$5:$L$1504,G$4)-SUMIFS(Transactions!$E$5:$E$1504,Transactions!$D$5:$D$1504,$A31,Transactions!$L$5:$L$1504,G$4)) | H31: =IF($A31="",0,SUMIFS(Transactions!$F$5:$F$1504,Transactions!$D$5:$D$1504,$A31,Transactions!$L$5:$L$1504,H$4)-SUMIFS(Transactions!$E$5:$E$1504,Transactions!$D$5:$D$1504,$A31,Transactions!$L$5:$L$1504,H$4)) | I31: =IF($A31="",0,SUMIFS(Transactions!$F$5:$F$1504,Transactions!$D$5:$D$1504,$A31,Transactions!$L$5:$L$1504,I$4)-SUMIFS(Transactions!$E$5:$E$1504,Transactions!$D$5:$D$1504,$A31,Transactions!$L$5:$L$1504,I$4)) | ... M31: =IF($A31="",0,SUMIFS(Transactions!$F$5:$F$1504,Transactions!$D$5:$D$1504,$A31,Transactions!$L$5:$L$1504,M$4)-SUMIFS(Transactions!$E$5:$E$1504,Transactions!$D$5:$D$1504,$A31,Transactions!$L$5:$L$1504,M$4)) | N31: =SUM(B31:M31)
A32: =IF(Setup!$A$41="","",Setup!$A$41) | B32: =IF($A32="",0,SUMIFS(Transactions!$F$5:$F$1504,Transactions!$D$5:$D$1504,$A32,Transactions!$L$5:$L$1504,B$4)-SUMIFS(Transactions!$E$5:$E$1504,Transactions!$D$5:$D$1504,$A32,Transactions!$L$5:$L$1504,B$4)) | C32: =IF($A32="",0,SUMIFS(Transactions!$F$5:$F$1504,Transactions!$D$5:$D$1504,$A32,Transactions!$L$5:$L$1504,C$4)-SUMIFS(Transactions!$E$5:$E$1504,Transactions!$D$5:$D$1504,$A32,Transactions!$L$5:$L$1504,C$4)) | D32: =IF($A32="",0,SUMIFS(Transactions!$F$5:$F$1504,Transactions!$D$5:$D$1504,$A32,Transactions!$L$5:$L$1504,D$4)-SUMIFS(Transactions!$E$5:$E$1504,Transactions!$D$5:$D$1504,$A32,Transactions!$L$5:$L$1504,D$4)) | E32: =IF($A32="",0,SUMIFS(Transactions!$F$5:$F$1504,Transactions!$D$5:$D$1504,$A32,Transactions!$L$5:$L$1504,E$4)-SUMIFS(Transactions!$E$5:$E$1504,Transactions!$D$5:$D$1504,$A32,Transactions!$L$5:$L$1504,E$4)) | F32: =IF($A32="",0,SUMIFS(Transactions!$F$5:$F$1504,Transactions!$D$5:$D$1504,$A32,Transactions!$L$5:$L$1504,F$4)-SUMIFS(Transactions!$E$5:$E$1504,Transactions!$D$5:$D$1504,$A32,Transactions!$L$5:$L$1504,F$4)) | G32: =IF($A32="",0,SUMIFS(Transactions!$F$5:$F$1504,Transactions!$D$5:$D$1504,$A32,Transactions!$L$5:$L$1504,G$4)-SUMIFS(Transactions!$E$5:$E$1504,Transactions!$D$5:$D$1504,$A32,Transactions!$L$5:$L$1504,G$4)) | H32: =IF($A32="",0,SUMIFS(Transactions!$F$5:$F$1504,Transactions!$D$5:$D$1504,$A32,Transactions!$L$5:$L$1504,H$4)-SUMIFS(Transactions!$E$5:$E$1504,Transactions!$D$5:$D$1504,$A32,Transactions!$L$5:$L$1504,H$4)) | I32: =IF($A32="",0,SUMIFS(Transactions!$F$5:$F$1504,Transactions!$D$5:$D$1504,$A32,Transactions!$L$5:$L$1504,I$4)-SUMIFS(Transactions!$E$5:$E$1504,Transactions!$D$5:$D$1504,$A32,Transactions!$L$5:$L$1504,I$4)) | ... M32: =IF($A32="",0,SUMIFS(Transactions!$F$5:$F$1504,Transactions!$D$5:$D$1504,$A32,Transactions!$L$5:$L$1504,M$4)-SUMIFS(Transactions!$E$5:$E$1504,Transactions!$D$5:$D$1504,$A32,Transactions!$L$5:$L$1504,M$4)) | N32: =SUM(B32:M32)
A33: =IF(Setup!$A$42="","",Setup!$A$42) | B33: =IF($A33="",0,SUMIFS(Transactions!$F$5:$F$1504,Transactions!$D$5:$D$1504,$A33,Transactions!$L$5:$L$1504,B$4)-SUMIFS(Transactions!$E$5:$E$1504,Transactions!$D$5:$D$1504,$A33,Transactions!$L$5:$L$1504,B$4)) | C33: =IF($A33="",0,SUMIFS(Transactions!$F$5:$F$1504,Transactions!$D$5:$D$1504,$A33,Transactions!$L$5:$L$1504,C$4)-SUMIFS(Transactions!$E$5:$E$1504,Transactions!$D$5:$D$1504,$A33,Transactions!$L$5:$L$1504,C$4)) | D33: =IF($A33="",0,SUMIFS(Transactions!$F$5:$F$1504,Transactions!$D$5:$D$1504,$A33,Transactions!$L$5:$L$1504,D$4)-SUMIFS(Transactions!$E$5:$E$1504,Transactions!$D$5:$D$1504,$A33,Transactions!$L$5:$L$1504,D$4)) | E33: =IF($A33="",0,SUMIFS(Transactions!$F$5:$F$1504,Transactions!$D$5:$D$1504,$A33,Transactions!$L$5:$L$1504,E$4)-SUMIFS(Transactions!$E$5:$E$1504,Transactions!$D$5:$D$1504,$A33,Transactions!$L$5:$L$1504,E$4)) | F33: =IF($A33="",0,SUMIFS(Transactions!$F$5:$F$1504,Transactions!$D$5:$D$1504,$A33,Transactions!$L$5:$L$1504,F$4)-SUMIFS(Transactions!$E$5:$E$1504,Transactions!$D$5:$D$1504,$A33,Transactions!$L$5:$L$1504,F$4)) | G33: =IF($A33="",0,SUMIFS(Transactions!$F$5:$F$1504,Transactions!$D$5:$D$1504,$A33,Transactions!$L$5:$L$1504,G$4)-SUMIFS(Transactions!$E$5:$E$1504,Transactions!$D$5:$D$1504,$A33,Transactions!$L$5:$L$1504,G$4)) | H33: =IF($A33="",0,SUMIFS(Transactions!$F$5:$F$1504,Transactions!$D$5:$D$1504,$A33,Transactions!$L$5:$L$1504,H$4)-SUMIFS(Transactions!$E$5:$E$1504,Transactions!$D$5:$D$1504,$A33,Transactions!$L$5:$L$1504,H$4)) | I33: =IF($A33="",0,SUMIFS(Transactions!$F$5:$F$1504,Transactions!$D$5:$D$1504,$A33,Transactions!$L$5:$L$1504,I$4)-SUMIFS(Transactions!$E$5:$E$1504,Transactions!$D$5:$D$1504,$A33,Transactions!$L$5:$L$1504,I$4)) | ... M33: =IF($A33="",0,SUMIFS(Transactions!$F$5:$F$1504,Transactions!$D$5:$D$1504,$A33,Transactions!$L$5:$L$1504,M$4)-SUMIFS(Transactions!$E$5:$E$1504,Transactions!$D$5:$D$1504,$A33,Transactions!$L$5:$L$1504,M$4)) | N33: =SUM(B33:M33)
A34: =IF(Setup!$A$43="","",Setup!$A$43) | B34: =IF($A34="",0,SUMIFS(Transactions!$F$5:$F$1504,Transactions!$D$5:$D$1504,$A34,Transactions!$L$5:$L$1504,B$4)-SUMIFS(Transactions!$E$5:$E$1504,Transactions!$D$5:$D$1504,$A34,Transactions!$L$5:$L$1504,B$4)) | C34: =IF($A34="",0,SUMIFS(Transactions!$F$5:$F$1504,Transactions!$D$5:$D$1504,$A34,Transactions!$L$5:$L$1504,C$4)-SUMIFS(Transactions!$E$5:$E$1504,Transactions!$D$5:$D$1504,$A34,Transactions!$L$5:$L$1504,C$4)) | D34: =IF($A34="",0,SUMIFS(Transactions!$F$5:$F$1504,Transactions!$D$5:$D$1504,$A34,Transactions!$L$5:$L$1504,D$4)-SUMIFS(Transactions!$E$5:$E$1504,Transactions!$D$5:$D$1504,$A34,Transactions!$L$5:$L$1504,D$4)) | E34: =IF($A34="",0,SUMIFS(Transactions!$F$5:$F$1504,Transactions!$D$5:$D$1504,$A34,Transactions!$L$5:$L$1504,E$4)-SUMIFS(Transactions!$E$5:$E$1504,Transactions!$D$5:$D$1504,$A34,Transactions!$L$5:$L$1504,E$4)) | F34: =IF($A34="",0,SUMIFS(Transactions!$F$5:$F$1504,Transactions!$D$5:$D$1504,$A34,Transactions!$L$5:$L$1504,F$4)-SUMIFS(Transactions!$E$5:$E$1504,Transactions!$D$5:$D$1504,$A34,Transactions!$L$5:$L$1504,F$4)) | G34: =IF($A34="",0,SUMIFS(Transactions!$F$5:$F$1504,Transactions!$D$5:$D$1504,$A34,Transactions!$L$5:$L$1504,G$4)-SUMIFS(Transactions!$E$5:$E$1504,Transactions!$D$5:$D$1504,$A34,Transactions!$L$5:$L$1504,G$4)) | H34: =IF($A34="",0,SUMIFS(Transactions!$F$5:$F$1504,Transactions!$D$5:$D$1504,$A34,Transactions!$L$5:$L$1504,H$4)-SUMIFS(Transactions!$E$5:$E$1504,Transactions!$D$5:$D$1504,$A34,Transactions!$L$5:$L$1504,H$4)) | I34: =IF($A34="",0,SUMIFS(Transactions!$F$5:$F$1504,Transactions!$D$5:$D$1504,$A34,Transactions!$L$5:$L$1504,I$4)-SUMIFS(Transactions!$E$5:$E$1504,Transactions!$D$5:$D$1504,$A34,Transactions!$L$5:$L$1504,I$4)) | ... M34: =IF($A34="",0,SUMIFS(Transactions!$F$5:$F$1504,Transactions!$D$5:$D$1504,$A34,Transactions!$L$5:$L$1504,M$4)-SUMIFS(Transactions!$E$5:$E$1504,Transactions!$D$5:$D$1504,$A34,Transactions!$L$5:$L$1504,M$4)) | N34: =SUM(B34:M34)
A35: =IF(Setup!$A$44="","",Setup!$A$44) | B35: =IF($A35="",0,SUMIFS(Transactions!$F$5:$F$1504,Transactions!$D$5:$D$1504,$A35,Transactions!$L$5:$L$1504,B$4)-SUMIFS(Transactions!$E$5:$E$1504,Transactions!$D$5:$D$1504,$A35,Transactions!$L$5:$L$1504,B$4)) | C35: =IF($A35="",0,SUMIFS(Transactions!$F$5:$F$1504,Transactions!$D$5:$D$1504,$A35,Transactions!$L$5:$L$1504,C$4)-SUMIFS(Transactions!$E$5:$E$1504,Transactions!$D$5:$D$1504,$A35,Transactions!$L$5:$L$1504,C$4)) | D35: =IF($A35="",0,SUMIFS(Transactions!$F$5:$F$1504,Transactions!$D$5:$D$1504,$A35,Transactions!$L$5:$L$1504,D$4)-SUMIFS(Transactions!$E$5:$E$1504,Transactions!$D$5:$D$1504,$A35,Transactions!$L$5:$L$1504,D$4)) | E35: =IF($A35="",0,SUMIFS(Transactions!$F$5:$F$1504,Transactions!$D$5:$D$1504,$A35,Transactions!$L$5:$L$1504,E$4)-SUMIFS(Transactions!$E$5:$E$1504,Transactions!$D$5:$D$1504,$A35,Transactions!$L$5:$L$1504,E$4)) | F35: =IF($A35="",0,SUMIFS(Transactions!$F$5:$F$1504,Transactions!$D$5:$D$1504,$A35,Transactions!$L$5:$L$1504,F$4)-SUMIFS(Transactions!$E$5:$E$1504,Transactions!$D$5:$D$1504,$A35,Transactions!$L$5:$L$1504,F$4)) | G35: =IF($A35="",0,SUMIFS(Transactions!$F$5:$F$1504,Transactions!$D$5:$D$1504,$A35,Transactions!$L$5:$L$1504,G$4)-SUMIFS(Transactions!$E$5:$E$1504,Transactions!$D$5:$D$1504,$A35,Transactions!$L$5:$L$1504,G$4)) | H35: =IF($A35="",0,SUMIFS(Transactions!$F$5:$F$1504,Transactions!$D$5:$D$1504,$A35,Transactions!$L$5:$L$1504,H$4)-SUMIFS(Transactions!$E$5:$E$1504,Transactions!$D$5:$D$1504,$A35,Transactions!$L$5:$L$1504,H$4)) | I35: =IF($A35="",0,SUMIFS(Transactions!$F$5:$F$1504,Transactions!$D$5:$D$1504,$A35,Transactions!$L$5:$L$1504,I$4)-SUMIFS(Transactions!$E$5:$E$1504,Transactions!$D$5:$D$1504,$A35,Transactions!$L$5:$L$1504,I$4)) | ... M35: =IF($A35="",0,SUMIFS(Transactions!$F$5:$F$1504,Transactions!$D$5:$D$1504,$A35,Transactions!$L$5:$L$1504,M$4)-SUMIFS(Transactions!$E$5:$E$1504,Transactions!$D$5:$D$1504,$A35,Transactions!$L$5:$L$1504,M$4)) | N35: =SUM(B35:M35)
A36: =IF(Setup!$A$45="","",Setup!$A$45) | B36: =IF($A36="",0,SUMIFS(Transactions!$F$5:$F$1504,Transactions!$D$5:$D$1504,$A36,Transactions!$L$5:$L$1504,B$4)-SUMIFS(Transactions!$E$5:$E$1504,Transactions!$D$5:$D$1504,$A36,Transactions!$L$5:$L$1504,B$4)) | C36: =IF($A36="",0,SUMIFS(Transactions!$F$5:$F$1504,Transactions!$D$5:$D$1504,$A36,Transactions!$L$5:$L$1504,C$4)-SUMIFS(Transactions!$E$5:$E$1504,Transactions!$D$5:$D$1504,$A36,Transactions!$L$5:$L$1504,C$4)) | D36: =IF($A36="",0,SUMIFS(Transactions!$F$5:$F$1504,Transactions!$D$5:$D$1504,$A36,Transactions!$L$5:$L$1504,D$4)-SUMIFS(Transactions!$E$5:$E$1504,Transactions!$D$5:$D$1504,$A36,Transactions!$L$5:$L$1504,D$4)) | E36: =IF($A36="",0,SUMIFS(Transactions!$F$5:$F$1504,Transactions!$D$5:$D$1504,$A36,Transactions!$L$5:$L$1504,E$4)-SUMIFS(Transactions!$E$5:$E$1504,Transactions!$D$5:$D$1504,$A36,Transactions!$L$5:$L$1504,E$4)) | F36: =IF($A36="",0,SUMIFS(Transactions!$F$5:$F$1504,Transactions!$D$5:$D$1504,$A36,Transactions!$L$5:$L$1504,F$4)-SUMIFS(Transactions!$E$5:$E$1504,Transactions!$D$5:$D$1504,$A36,Transactions!$L$5:$L$1504,F$4)) | G36: =IF($A36="",0,SUMIFS(Transactions!$F$5:$F$1504,Transactions!$D$5:$D$1504,$A36,Transactions!$L$5:$L$1504,G$4)-SUMIFS(Transactions!$E$5:$E$1504,Transactions!$D$5:$D$1504,$A36,Transactions!$L$5:$L$1504,G$4)) | H36: =IF($A36="",0,SUMIFS(Transactions!$F$5:$F$1504,Transactions!$D$5:$D$1504,$A36,Transactions!$L$5:$L$1504,H$4)-SUMIFS(Transactions!$E$5:$E$1504,Transactions!$D$5:$D$1504,$A36,Transactions!$L$5:$L$1504,H$4)) | I36: =IF($A36="",0,SUMIFS(Transactions!$F$5:$F$1504,Transactions!$D$5:$D$1504,$A36,Transactions!$L$5:$L$1504,I$4)-SUMIFS(Transactions!$E$5:$E$1504,Transactions!$D$5:$D$1504,$A36,Transactions!$L$5:$L$1504,I$4)) | ... M36: =IF($A36="",0,SUMIFS(Transactions!$F$5:$F$1504,Transactions!$D$5:$D$1504,$A36,Transactions!$L$5:$L$1504,M$4)-SUMIFS(Transactions!$E$5:$E$1504,Transactions!$D$5:$D$1504,$A36,Transactions!$L$5:$L$1504,M$4)) | N36: =SUM(B36:M36)
A37: =IF(Setup!$A$46="","",Setup!$A$46) | B37: =IF($A37="",0,SUMIFS(Transactions!$F$5:$F$1504,Transactions!$D$5:$D$1504,$A37,Transactions!$L$5:$L$1504,B$4)-SUMIFS(Transactions!$E$5:$E$1504,Transactions!$D$5:$D$1504,$A37,Transactions!$L$5:$L$1504,B$4)) | C37: =IF($A37="",0,SUMIFS(Transactions!$F$5:$F$1504,Transactions!$D$5:$D$1504,$A37,Transactions!$L$5:$L$1504,C$4)-SUMIFS(Transactions!$E$5:$E$1504,Transactions!$D$5:$D$1504,$A37,Transactions!$L$5:$L$1504,C$4)) | D37: =IF($A37="",0,SUMIFS(Transactions!$F$5:$F$1504,Transactions!$D$5:$D$1504,$A37,Transactions!$L$5:$L$1504,D$4)-SUMIFS(Transactions!$E$5:$E$1504,Transactions!$D$5:$D$1504,$A37,Transactions!$L$5:$L$1504,D$4)) | E37: =IF($A37="",0,SUMIFS(Transactions!$F$5:$F$1504,Transactions!$D$5:$D$1504,$A37,Transactions!$L$5:$L$1504,E$4)-SUMIFS(Transactions!$E$5:$E$1504,Transactions!$D$5:$D$1504,$A37,Transactions!$L$5:$L$1504,E$4)) | F37: =IF($A37="",0,SUMIFS(Transactions!$F$5:$F$1504,Transactions!$D$5:$D$1504,$A37,Transactions!$L$5:$L$1504,F$4)-SUMIFS(Transactions!$E$5:$E$1504,Transactions!$D$5:$D$1504,$A37,Transactions!$L$5:$L$1504,F$4)) | G37: =IF($A37="",0,SUMIFS(Transactions!$F$5:$F$1504,Transactions!$D$5:$D$1504,$A37,Transactions!$L$5:$L$1504,G$4)-SUMIFS(Transactions!$E$5:$E$1504,Transactions!$D$5:$D$1504,$A37,Transactions!$L$5:$L$1504,G$4)) | H37: =IF($A37="",0,SUMIFS(Transactions!$F$5:$F$1504,Transactions!$D$5:$D$1504,$A37,Transactions!$L$5:$L$1504,H$4)-SUMIFS(Transactions!$E$5:$E$1504,Transactions!$D$5:$D$1504,$A37,Transactions!$L$5:$L$1504,H$4)) | I37: =IF($A37="",0,SUMIFS(Transactions!$F$5:$F$1504,Transactions!$D$5:$D$1504,$A37,Transactions!$L$5:$L$1504,I$4)-SUMIFS(Transactions!$E$5:$E$1504,Transactions!$D$5:$D$1504,$A37,Transactions!$L$5:$L$1504,I$4)) | ... M37: =IF($A37="",0,SUMIFS(Transactions!$F$5:$F$1504,Transactions!$D$5:$D$1504,$A37,Transactions!$L$5:$L$1504,M$4)-SUMIFS(Transactions!$E$5:$E$1504,Transactions!$D$5:$D$1504,$A37,Transactions!$L$5:$L$1504,M$4)) | N37: =SUM(B37:M37)
A38: =IF(Setup!$A$47="","",Setup!$A$47) | B38: =IF($A38="",0,SUMIFS(Transactions!$F$5:$F$1504,Transactions!$D$5:$D$1504,$A38,Transactions!$L$5:$L$1504,B$4)-SUMIFS(Transactions!$E$5:$E$1504,Transactions!$D$5:$D$1504,$A38,Transactions!$L$5:$L$1504,B$4)) | C38: =IF($A38="",0,SUMIFS(Transactions!$F$5:$F$1504,Transactions!$D$5:$D$1504,$A38,Transactions!$L$5:$L$1504,C$4)-SUMIFS(Transactions!$E$5:$E$1504,Transactions!$D$5:$D$1504,$A38,Transactions!$L$5:$L$1504,C$4)) | D38: =IF($A38="",0,SUMIFS(Transactions!$F$5:$F$1504,Transactions!$D$5:$D$1504,$A38,Transactions!$L$5:$L$1504,D$4)-SUMIFS(Transactions!$E$5:$E$1504,Transactions!$D$5:$D$1504,$A38,Transactions!$L$5:$L$1504,D$4)) | E38: =IF($A38="",0,SUMIFS(Transactions!$F$5:$F$1504,Transactions!$D$5:$D$1504,$A38,Transactions!$L$5:$L$1504,E$4)-SUMIFS(Transactions!$E$5:$E$1504,Transactions!$D$5:$D$1504,$A38,Transactions!$L$5:$L$1504,E$4)) | F38: =IF($A38="",0,SUMIFS(Transactions!$F$5:$F$1504,Transactions!$D$5:$D$1504,$A38,Transactions!$L$5:$L$1504,F$4)-SUMIFS(Transactions!$E$5:$E$1504,Transactions!$D$5:$D$1504,$A38,Transactions!$L$5:$L$1504,F$4)) | G38: =IF($A38="",0,SUMIFS(Transactions!$F$5:$F$1504,Transactions!$D$5:$D$1504,$A38,Transactions!$L$5:$L$1504,G$4)-SUMIFS(Transactions!$E$5:$E$1504,Transactions!$D$5:$D$1504,$A38,Transactions!$L$5:$L$1504,G$4)) | H38: =IF($A38="",0,SUMIFS(Transactions!$F$5:$F$1504,Transactions!$D$5:$D$1504,$A38,Transactions!$L$5:$L$1504,H$4)-SUMIFS(Transactions!$E$5:$E$1504,Transactions!$D$5:$D$1504,$A38,Transactions!$L$5:$L$1504,H$4)) | I38: =IF($A38="",0,SUMIFS(Transactions!$F$5:$F$1504,Transactions!$D$5:$D$1504,$A38,Transactions!$L$5:$L$1504,I$4)-SUMIFS(Transactions!$E$5:$E$1504,Transactions!$D$5:$D$1504,$A38,Transactions!$L$5:$L$1504,I$4)) | ... M38: =IF($A38="",0,SUMIFS(Transactions!$F$5:$F$1504,Transactions!$D$5:$D$1504,$A38,Transactions!$L$5:$L$1504,M$4)-SUMIFS(Transactions!$E$5:$E$1504,Transactions!$D$5:$D$1504,$A38,Transactions!$L$5:$L$1504,M$4)) | N38: =SUM(B38:M38)
A39: =IF(Setup!$A$48="","",Setup!$A$48) | B39: =IF($A39="",0,SUMIFS(Transactions!$F$5:$F$1504,Transactions!$D$5:$D$1504,$A39,Transactions!$L$5:$L$1504,B$4)-SUMIFS(Transactions!$E$5:$E$1504,Transactions!$D$5:$D$1504,$A39,Transactions!$L$5:$L$1504,B$4)) | C39: =IF($A39="",0,SUMIFS(Transactions!$F$5:$F$1504,Transactions!$D$5:$D$1504,$A39,Transactions!$L$5:$L$1504,C$4)-SUMIFS(Transactions!$E$5:$E$1504,Transactions!$D$5:$D$1504,$A39,Transactions!$L$5:$L$1504,C$4)) | D39: =IF($A39="",0,SUMIFS(Transactions!$F$5:$F$1504,Transactions!$D$5:$D$1504,$A39,Transactions!$L$5:$L$1504,D$4)-SUMIFS(Transactions!$E$5:$E$1504,Transactions!$D$5:$D$1504,$A39,Transactions!$L$5:$L$1504,D$4)) | E39: =IF($A39="",0,SUMIFS(Transactions!$F$5:$F$1504,Transactions!$D$5:$D$1504,$A39,Transactions!$L$5:$L$1504,E$4)-SUMIFS(Transactions!$E$5:$E$1504,Transactions!$D$5:$D$1504,$A39,Transactions!$L$5:$L$1504,E$4)) | F39: =IF($A39="",0,SUMIFS(Transactions!$F$5:$F$1504,Transactions!$D$5:$D$1504,$A39,Transactions!$L$5:$L$1504,F$4)-SUMIFS(Transactions!$E$5:$E$1504,Transactions!$D$5:$D$1504,$A39,Transactions!$L$5:$L$1504,F$4)) | G39: =IF($A39="",0,SUMIFS(Transactions!$F$5:$F$1504,Transactions!$D$5:$D$1504,$A39,Transactions!$L$5:$L$1504,G$4)-SUMIFS(Transactions!$E$5:$E$1504,Transactions!$D$5:$D$1504,$A39,Transactions!$L$5:$L$1504,G$4)) | H39: =IF($A39="",0,SUMIFS(Transactions!$F$5:$F$1504,Transactions!$D$5:$D$1504,$A39,Transactions!$L$5:$L$1504,H$4)-SUMIFS(Transactions!$E$5:$E$1504,Transactions!$D$5:$D$1504,$A39,Transactions!$L$5:$L$1504,H$4)) | I39: =IF($A39="",0,SUMIFS(Transactions!$F$5:$F$1504,Transactions!$D$5:$D$1504,$A39,Transactions!$L$5:$L$1504,I$4)-SUMIFS(Transactions!$E$5:$E$1504,Transactions!$D$5:$D$1504,$A39,Transactions!$L$5:$L$1504,I$4)) | ... M39: =IF($A39="",0,SUMIFS(Transactions!$F$5:$F$1504,Transactions!$D$5:$D$1504,$A39,Transactions!$L$5:$L$1504,M$4)-SUMIFS(Transactions!$E$5:$E$1504,Transactions!$D$5:$D$1504,$A39,Transactions!$L$5:$L$1504,M$4)) | N39: =SUM(B39:M39)
A40: =IF(Setup!$A$49="","",Setup!$A$49) | B40: =IF($A40="",0,SUMIFS(Transactions!$F$5:$F$1504,Transactions!$D$5:$D$1504,$A40,Transactions!$L$5:$L$1504,B$4)-SUMIFS(Transactions!$E$5:$E$1504,Transactions!$D$5:$D$1504,$A40,Transactions!$L$5:$L$1504,B$4)) | C40: =IF($A40="",0,SUMIFS(Transactions!$F$5:$F$1504,Transactions!$D$5:$D$1504,$A40,Transactions!$L$5:$L$1504,C$4)-SUMIFS(Transactions!$E$5:$E$1504,Transactions!$D$5:$D$1504,$A40,Transactions!$L$5:$L$1504,C$4)) | D40: =IF($A40="",0,SUMIFS(Transactions!$F$5:$F$1504,Transactions!$D$5:$D$1504,$A40,Transactions!$L$5:$L$1504,D$4)-SUMIFS(Transactions!$E$5:$E$1504,Transactions!$D$5:$D$1504,$A40,Transactions!$L$5:$L$1504,D$4)) | E40: =IF($A40="",0,SUMIFS(Transactions!$F$5:$F$1504,Transactions!$D$5:$D$1504,$A40,Transactions!$L$5:$L$1504,E$4)-SUMIFS(Transactions!$E$5:$E$1504,Transactions!$D$5:$D$1504,$A40,Transactions!$L$5:$L$1504,E$4)) | F40: =IF($A40="",0,SUMIFS(Transactions!$F$5:$F$1504,Transactions!$D$5:$D$1504,$A40,Transactions!$L$5:$L$1504,F$4)-SUMIFS(Transactions!$E$5:$E$1504,Transactions!$D$5:$D$1504,$A40,Transactions!$L$5:$L$1504,F$4)) | G40: =IF($A40="",0,SUMIFS(Transactions!$F$5:$F$1504,Transactions!$D$5:$D$1504,$A40,Transactions!$L$5:$L$1504,G$4)-SUMIFS(Transactions!$E$5:$E$1504,Transactions!$D$5:$D$1504,$A40,Transactions!$L$5:$L$1504,G$4)) | H40: =IF($A40="",0,SUMIFS(Transactions!$F$5:$F$1504,Transactions!$D$5:$D$1504,$A40,Transactions!$L$5:$L$1504,H$4)-SUMIFS(Transactions!$E$5:$E$1504,Transactions!$D$5:$D$1504,$A40,Transactions!$L$5:$L$1504,H$4)) | I40: =IF($A40="",0,SUMIFS(Transactions!$F$5:$F$1504,Transactions!$D$5:$D$1504,$A40,Transactions!$L$5:$L$1504,I$4)-SUMIFS(Transactions!$E$5:$E$1504,Transactions!$D$5:$D$1504,$A40,Transactions!$L$5:$L$1504,I$4)) | ... M40: =IF($A40="",0,SUMIFS(Transactions!$F$5:$F$1504,Transactions!$D$5:$D$1504,$A40,Transactions!$L$5:$L$1504,M$4)-SUMIFS(Transactions!$E$5:$E$1504,Transactions!$D$5:$D$1504,$A40,Transactions!$L$5:$L$1504,M$4)) | N40: =SUM(B40:M40)
A41: =IF(Setup!$A$50="","",Setup!$A$50) | B41: =IF($A41="",0,SUMIFS(Transactions!$F$5:$F$1504,Transactions!$D$5:$D$1504,$A41,Transactions!$L$5:$L$1504,B$4)-SUMIFS(Transactions!$E$5:$E$1504,Transactions!$D$5:$D$1504,$A41,Transactions!$L$5:$L$1504,B$4)) | C41: =IF($A41="",0,SUMIFS(Transactions!$F$5:$F$1504,Transactions!$D$5:$D$1504,$A41,Transactions!$L$5:$L$1504,C$4)-SUMIFS(Transactions!$E$5:$E$1504,Transactions!$D$5:$D$1504,$A41,Transactions!$L$5:$L$1504,C$4)) | D41: =IF($A41="",0,SUMIFS(Transactions!$F$5:$F$1504,Transactions!$D$5:$D$1504,$A41,Transactions!$L$5:$L$1504,D$4)-SUMIFS(Transactions!$E$5:$E$1504,Transactions!$D$5:$D$1504,$A41,Transactions!$L$5:$L$1504,D$4)) | E41: =IF($A41="",0,SUMIFS(Transactions!$F$5:$F$1504,Transactions!$D$5:$D$1504,$A41,Transactions!$L$5:$L$1504,E$4)-SUMIFS(Transactions!$E$5:$E$1504,Transactions!$D$5:$D$1504,$A41,Transactions!$L$5:$L$1504,E$4)) | F41: =IF($A41="",0,SUMIFS(Transactions!$F$5:$F$1504,Transactions!$D$5:$D$1504,$A41,Transactions!$L$5:$L$1504,F$4)-SUMIFS(Transactions!$E$5:$E$1504,Transactions!$D$5:$D$1504,$A41,Transactions!$L$5:$L$1504,F$4)) | G41: =IF($A41="",0,SUMIFS(Transactions!$F$5:$F$1504,Transactions!$D$5:$D$1504,$A41,Transactions!$L$5:$L$1504,G$4)-SUMIFS(Transactions!$E$5:$E$1504,Transactions!$D$5:$D$1504,$A41,Transactions!$L$5:$L$1504,G$4)) | H41: =IF($A41="",0,SUMIFS(Transactions!$F$5:$F$1504,Transactions!$D$5:$D$1504,$A41,Transactions!$L$5:$L$1504,H$4)-SUMIFS(Transactions!$E$5:$E$1504,Transactions!$D$5:$D$1504,$A41,Transactions!$L$5:$L$1504,H$4)) | I41: =IF($A41="",0,SUMIFS(Transactions!$F$5:$F$1504,Transactions!$D$5:$D$1504,$A41,Transactions!$L$5:$L$1504,I$4)-SUMIFS(Transactions!$E$5:$E$1504,Transactions!$D$5:$D$1504,$A41,Transactions!$L$5:$L$1504,I$4)) | ... M41: =IF($A41="",0,SUMIFS(Transactions!$F$5:$F$1504,Transactions!$D$5:$D$1504,$A41,Transactions!$L$5:$L$1504,M$4)-SUMIFS(Transactions!$E$5:$E$1504,Transactions!$D$5:$D$1504,$A41,Transactions!$L$5:$L$1504,M$4)) | N41: =SUM(B41:M41)
A42: =IF(Setup!$A$51="","",Setup!$A$51) | B42: =IF($A42="",0,SUMIFS(Transactions!$F$5:$F$1504,Transactions!$D$5:$D$1504,$A42,Transactions!$L$5:$L$1504,B$4)-SUMIFS(Transactions!$E$5:$E$1504,Transactions!$D$5:$D$1504,$A42,Transactions!$L$5:$L$1504,B$4)) | C42: =IF($A42="",0,SUMIFS(Transactions!$F$5:$F$1504,Transactions!$D$5:$D$1504,$A42,Transactions!$L$5:$L$1504,C$4)-SUMIFS(Transactions!$E$5:$E$1504,Transactions!$D$5:$D$1504,$A42,Transactions!$L$5:$L$1504,C$4)) | D42: =IF($A42="",0,SUMIFS(Transactions!$F$5:$F$1504,Transactions!$D$5:$D$1504,$A42,Transactions!$L$5:$L$1504,D$4)-SUMIFS(Transactions!$E$5:$E$1504,Transactions!$D$5:$D$1504,$A42,Transactions!$L$5:$L$1504,D$4)) | E42: =IF($A42="",0,SUMIFS(Transactions!$F$5:$F$1504,Transactions!$D$5:$D$1504,$A42,Transactions!$L$5:$L$1504,E$4)-SUMIFS(Transactions!$E$5:$E$1504,Transactions!$D$5:$D$1504,$A42,Transactions!$L$5:$L$1504,E$4)) | F42: =IF($A42="",0,SUMIFS(Transactions!$F$5:$F$1504,Transactions!$D$5:$D$1504,$A42,Transactions!$L$5:$L$1504,F$4)-SUMIFS(Transactions!$E$5:$E$1504,Transactions!$D$5:$D$1504,$A42,Transactions!$L$5:$L$1504,F$4)) | G42: =IF($A42="",0,SUMIFS(Transactions!$F$5:$F$1504,Transactions!$D$5:$D$1504,$A42,Transactions!$L$5:$L$1504,G$4)-SUMIFS(Transactions!$E$5:$E$1504,Transactions!$D$5:$D$1504,$A42,Transactions!$L$5:$L$1504,G$4)) | H42: =IF($A42="",0,SUMIFS(Transactions!$F$5:$F$1504,Transactions!$D$5:$D$1504,$A42,Transactions!$L$5:$L$1504,H$4)-SUMIFS(Transactions!$E$5:$E$1504,Transactions!$D$5:$D$1504,$A42,Transactions!$L$5:$L$1504,H$4)) | I42: =IF($A42="",0,SUMIFS(Transactions!$F$5:$F$1504,Transactions!$D$5:$D$1504,$A42,Transactions!$L$5:$L$1504,I$4)-SUMIFS(Transactions!$E$5:$E$1504,Transactions!$D$5:$D$1504,$A42,Transactions!$L$5:$L$1504,I$4)) | ... M42: =IF($A42="",0,SUMIFS(Transactions!$F$5:$F$1504,Transactions!$D$5:$D$1504,$A42,Transactions!$L$5:$L$1504,M$4)-SUMIFS(Transactions!$E$5:$E$1504,Transactions!$D$5:$D$1504,$A42,Transactions!$L$5:$L$1504,M$4)) | N42: =SUM(B42:M42)
A43: Total operating expenses | B43: =SUM(B25:B42) | C43: =SUM(C25:C42) | D43: =SUM(D25:D42) | E43: =SUM(E25:E42) | F43: =SUM(F25:F42) | G43: =SUM(G25:G42) | H43: =SUM(H25:H42) | I43: =SUM(I25:I42) | ... N43: =SUM(N25:N42)
A45: NET PROFIT (before owner drawings & tax) | B45: =B21-B43 | C45: =C21-C43 | D45: =D21-D43 | E45: =E21-E43 | F45: =F21-F43 | G45: =G21-G43 | H45: =H21-H43 | I45: =I21-I43 | ... N45: =N21-N43
A46: Net margin % | B46: =IF(B11=0,0,B45/B11) | C46: =IF(C11=0,0,C45/C11) | D46: =IF(D11=0,0,D45/D11) | E46: =IF(E11=0,0,E45/E11) | F46: =IF(F11=0,0,F45/F11) | G46: =IF(G11=0,0,G45/G11) | H46: =IF(H11=0,0,H45/H11) | I46: =IF(I11=0,0,I45/I11) | ... N46: =IF(N11=0,0,N45/N11)
A47: Suggested tax reserve (Setup %) | B47: =MAX(0,B45)*Setup!$B$8 | C47: =MAX(0,C45)*Setup!$B$8 | D47: =MAX(0,D45)*Setup!$B$8 | E47: =MAX(0,E45)*Setup!$B$8 | F47: =MAX(0,F45)*Setup!$B$8 | G47: =MAX(0,G45)*Setup!$B$8 | H47: =MAX(0,H45)*Setup!$B$8 | I47: =MAX(0,I45)*Setup!$B$8 | ... N47: =MAX(0,N45)*Setup!$B$8
A49: MEMO: money that is NOT profit or cost
A50: Owner drawings taken | B50: =SUMIFS(Transactions!$F$5:$F$1504,Transactions!$K$5:$K$1504,"Owner Drawings",Transactions!$L$5:$L$1504,B$4)-SUMIFS(Transactions!$E$5:$E$1504,Transactions!$K$5:$K$1504,"Owner Drawings",Transactions!$L$5:$L$1504,B$4) | C50: =SUMIFS(Transactions!$F$5:$F$1504,Transactions!$K$5:$K$1504,"Owner Drawings",Transactions!$L$5:$L$1504,C$4)-SUMIFS(Transactions!$E$5:$E$1504,Transactions!$K$5:$K$1504,"Owner Drawings",Transactions!$L$5:$L$1504,C$4) | D50: =SUMIFS(Transactions!$F$5:$F$1504,Transactions!$K$5:$K$1504,"Owner Drawings",Transactions!$L$5:$L$1504,D$4)-SUMIFS(Transactions!$E$5:$E$1504,Transactions!$K$5:$K$1504,"Owner Drawings",Transactions!$L$5:$L$1504,D$4) | E50: =SUMIFS(Transactions!$F$5:$F$1504,Transactions!$K$5:$K$1504,"Owner Drawings",Transactions!$L$5:$L$1504,E$4)-SUMIFS(Transactions!$E$5:$E$1504,Transactions!$K$5:$K$1504,"Owner Drawings",Transactions!$L$5:$L$1504,E$4) | F50: =SUMIFS(Transactions!$F$5:$F$1504,Transactions!$K$5:$K$1504,"Owner Drawings",Transactions!$L$5:$L$1504,F$4)-SUMIFS(Transactions!$E$5:$E$1504,Transactions!$K$5:$K$1504,"Owner Drawings",Transactions!$L$5:$L$1504,F$4) | G50: =SUMIFS(Transactions!$F$5:$F$1504,Transactions!$K$5:$K$1504,"Owner Drawings",Transactions!$L$5:$L$1504,G$4)-SUMIFS(Transactions!$E$5:$E$1504,Transactions!$K$5:$K$1504,"Owner Drawings",Transactions!$L$5:$L$1504,G$4) | H50: =SUMIFS(Transactions!$F$5:$F$1504,Transactions!$K$5:$K$1504,"Owner Drawings",Transactions!$L$5:$L$1504,H$4)-SUMIFS(Transactions!$E$5:$E$1504,Transactions!$K$5:$K$1504,"Owner Drawings",Transactions!$L$5:$L$1504,H$4) | I50: =SUMIFS(Transactions!$F$5:$F$1504,Transactions!$K$5:$K$1504,"Owner Drawings",Transactions!$L$5:$L$1504,I$4)-SUMIFS(Transactions!$E$5:$E$1504,Transactions!$K$5:$K$1504,"Owner Drawings",Transactions!$L$5:$L$1504,I$4) | ... M50: =SUMIFS(Transactions!$F$5:$F$1504,Transactions!$K$5:$K$1504,"Owner Drawings",Transactions!$L$5:$L$1504,M$4)-SUMIFS(Transactions!$E$5:$E$1504,Transactions!$K$5:$K$1504,"Owner Drawings",Transactions!$L$5:$L$1504,M$4) | N50: =SUM(B50:M50)
A51: Owner capital put in | B51: =SUMIFS(Transactions!$E$5:$E$1504,Transactions!$K$5:$K$1504,"Owner Capital",Transactions!$L$5:$L$1504,B$4)-SUMIFS(Transactions!$F$5:$F$1504,Transactions!$K$5:$K$1504,"Owner Capital",Transactions!$L$5:$L$1504,B$4) | C51: =SUMIFS(Transactions!$E$5:$E$1504,Transactions!$K$5:$K$1504,"Owner Capital",Transactions!$L$5:$L$1504,C$4)-SUMIFS(Transactions!$F$5:$F$1504,Transactions!$K$5:$K$1504,"Owner Capital",Transactions!$L$5:$L$1504,C$4) | D51: =SUMIFS(Transactions!$E$5:$E$1504,Transactions!$K$5:$K$1504,"Owner Capital",Transactions!$L$5:$L$1504,D$4)-SUMIFS(Transactions!$F$5:$F$1504,Transactions!$K$5:$K$1504,"Owner Capital",Transactions!$L$5:$L$1504,D$4) | E51: =SUMIFS(Transactions!$E$5:$E$1504,Transactions!$K$5:$K$1504,"Owner Capital",Transactions!$L$5:$L$1504,E$4)-SUMIFS(Transactions!$F$5:$F$1504,Transactions!$K$5:$K$1504,"Owner Capital",Transactions!$L$5:$L$1504,E$4) | F51: =SUMIFS(Transactions!$E$5:$E$1504,Transactions!$K$5:$K$1504,"Owner Capital",Transactions!$L$5:$L$1504,F$4)-SUMIFS(Transactions!$F$5:$F$1504,Transactions!$K$5:$K$1504,"Owner Capital",Transactions!$L$5:$L$1504,F$4) | G51: =SUMIFS(Transactions!$E$5:$E$1504,Transactions!$K$5:$K$1504,"Owner Capital",Transactions!$L$5:$L$1504,G$4)-SUMIFS(Transactions!$F$5:$F$1504,Transactions!$K$5:$K$1504,"Owner Capital",Transactions!$L$5:$L$1504,G$4) | H51: =SUMIFS(Transactions!$E$5:$E$1504,Transactions!$K$5:$K$1504,"Owner Capital",Transactions!$L$5:$L$1504,H$4)-SUMIFS(Transactions!$F$5:$F$1504,Transactions!$K$5:$K$1504,"Owner Capital",Transactions!$L$5:$L$1504,H$4) | I51: =SUMIFS(Transactions!$E$5:$E$1504,Transactions!$K$5:$K$1504,"Owner Capital",Transactions!$L$5:$L$1504,I$4)-SUMIFS(Transactions!$F$5:$F$1504,Transactions!$K$5:$K$1504,"Owner Capital",Transactions!$L$5:$L$1504,I$4) | ... M51: =SUMIFS(Transactions!$E$5:$E$1504,Transactions!$K$5:$K$1504,"Owner Capital",Transactions!$L$5:$L$1504,M$4)-SUMIFS(Transactions!$F$5:$F$1504,Transactions!$K$5:$K$1504,"Owner Capital",Transactions!$L$5:$L$1504,M$4) | N51: =SUM(B51:M51)
A52: Income tax / VAT / SSCL paid | B52: =SUMIFS(Transactions!$F$5:$F$1504,Transactions!$K$5:$K$1504,"Tax Payment",Transactions!$L$5:$L$1504,B$4)-SUMIFS(Transactions!$E$5:$E$1504,Transactions!$K$5:$K$1504,"Tax Payment",Transactions!$L$5:$L$1504,B$4) | C52: =SUMIFS(Transactions!$F$5:$F$1504,Transactions!$K$5:$K$1504,"Tax Payment",Transactions!$L$5:$L$1504,C$4)-SUMIFS(Transactions!$E$5:$E$1504,Transactions!$K$5:$K$1504,"Tax Payment",Transactions!$L$5:$L$1504,C$4) | D52: =SUMIFS(Transactions!$F$5:$F$1504,Transactions!$K$5:$K$1504,"Tax Payment",Transactions!$L$5:$L$1504,D$4)-SUMIFS(Transactions!$E$5:$E$1504,Transactions!$K$5:$K$1504,"Tax Payment",Transactions!$L$5:$L$1504,D$4) | E52: =SUMIFS(Transactions!$F$5:$F$1504,Transactions!$K$5:$K$1504,"Tax Payment",Transactions!$L$5:$L$1504,E$4)-SUMIFS(Transactions!$E$5:$E$1504,Transactions!$K$5:$K$1504,"Tax Payment",Transactions!$L$5:$L$1504,E$4) | F52: =SUMIFS(Transactions!$F$5:$F$1504,Transactions!$K$5:$K$1504,"Tax Payment",Transactions!$L$5:$L$1504,F$4)-SUMIFS(Transactions!$E$5:$E$1504,Transactions!$K$5:$K$1504,"Tax Payment",Transactions!$L$5:$L$1504,F$4) | G52: =SUMIFS(Transactions!$F$5:$F$1504,Transactions!$K$5:$K$1504,"Tax Payment",Transactions!$L$5:$L$1504,G$4)-SUMIFS(Transactions!$E$5:$E$1504,Transactions!$K$5:$K$1504,"Tax Payment",Transactions!$L$5:$L$1504,G$4) | H52: =SUMIFS(Transactions!$F$5:$F$1504,Transactions!$K$5:$K$1504,"Tax Payment",Transactions!$L$5:$L$1504,H$4)-SUMIFS(Transactions!$E$5:$E$1504,Transactions!$K$5:$K$1504,"Tax Payment",Transactions!$L$5:$L$1504,H$4) | I52: =SUMIFS(Transactions!$F$5:$F$1504,Transactions!$K$5:$K$1504,"Tax Payment",Transactions!$L$5:$L$1504,I$4)-SUMIFS(Transactions!$E$5:$E$1504,Transactions!$K$5:$K$1504,"Tax Payment",Transactions!$L$5:$L$1504,I$4) | ... M52: =SUMIFS(Transactions!$F$5:$F$1504,Transactions!$K$5:$K$1504,"Tax Payment",Transactions!$L$5:$L$1504,M$4)-SUMIFS(Transactions!$E$5:$E$1504,Transactions!$K$5:$K$1504,"Tax Payment",Transactions!$L$5:$L$1504,M$4) | N52: =SUM(B52:M52)
A53: Equipment & assets bought | B53: =SUMIFS(Transactions!$F$5:$F$1504,Transactions!$K$5:$K$1504,"Asset Purchase",Transactions!$L$5:$L$1504,B$4)-SUMIFS(Transactions!$E$5:$E$1504,Transactions!$K$5:$K$1504,"Asset Purchase",Transactions!$L$5:$L$1504,B$4) | C53: =SUMIFS(Transactions!$F$5:$F$1504,Transactions!$K$5:$K$1504,"Asset Purchase",Transactions!$L$5:$L$1504,C$4)-SUMIFS(Transactions!$E$5:$E$1504,Transactions!$K$5:$K$1504,"Asset Purchase",Transactions!$L$5:$L$1504,C$4) | D53: =SUMIFS(Transactions!$F$5:$F$1504,Transactions!$K$5:$K$1504,"Asset Purchase",Transactions!$L$5:$L$1504,D$4)-SUMIFS(Transactions!$E$5:$E$1504,Transactions!$K$5:$K$1504,"Asset Purchase",Transactions!$L$5:$L$1504,D$4) | E53: =SUMIFS(Transactions!$F$5:$F$1504,Transactions!$K$5:$K$1504,"Asset Purchase",Transactions!$L$5:$L$1504,E$4)-SUMIFS(Transactions!$E$5:$E$1504,Transactions!$K$5:$K$1504,"Asset Purchase",Transactions!$L$5:$L$1504,E$4) | F53: =SUMIFS(Transactions!$F$5:$F$1504,Transactions!$K$5:$K$1504,"Asset Purchase",Transactions!$L$5:$L$1504,F$4)-SUMIFS(Transactions!$E$5:$E$1504,Transactions!$K$5:$K$1504,"Asset Purchase",Transactions!$L$5:$L$1504,F$4) | G53: =SUMIFS(Transactions!$F$5:$F$1504,Transactions!$K$5:$K$1504,"Asset Purchase",Transactions!$L$5:$L$1504,G$4)-SUMIFS(Transactions!$E$5:$E$1504,Transactions!$K$5:$K$1504,"Asset Purchase",Transactions!$L$5:$L$1504,G$4) | H53: =SUMIFS(Transactions!$F$5:$F$1504,Transactions!$K$5:$K$1504,"Asset Purchase",Transactions!$L$5:$L$1504,H$4)-SUMIFS(Transactions!$E$5:$E$1504,Transactions!$K$5:$K$1504,"Asset Purchase",Transactions!$L$5:$L$1504,H$4) | I53: =SUMIFS(Transactions!$F$5:$F$1504,Transactions!$K$5:$K$1504,"Asset Purchase",Transactions!$L$5:$L$1504,I$4)-SUMIFS(Transactions!$E$5:$E$1504,Transactions!$K$5:$K$1504,"Asset Purchase",Transactions!$L$5:$L$1504,I$4) | ... M53: =SUMIFS(Transactions!$F$5:$F$1504,Transactions!$K$5:$K$1504,"Asset Purchase",Transactions!$L$5:$L$1504,M$4)-SUMIFS(Transactions!$E$5:$E$1504,Transactions!$K$5:$K$1504,"Asset Purchase",Transactions!$L$5:$L$1504,M$4) | N53: =SUM(B53:M53)
A54: Loans received | B54: =SUMIFS(Transactions!$E$5:$E$1504,Transactions!$K$5:$K$1504,"Loan In",Transactions!$L$5:$L$1504,B$4)-SUMIFS(Transactions!$F$5:$F$1504,Transactions!$K$5:$K$1504,"Loan In",Transactions!$L$5:$L$1504,B$4) | C54: =SUMIFS(Transactions!$E$5:$E$1504,Transactions!$K$5:$K$1504,"Loan In",Transactions!$L$5:$L$1504,C$4)-SUMIFS(Transactions!$F$5:$F$1504,Transactions!$K$5:$K$1504,"Loan In",Transactions!$L$5:$L$1504,C$4) | D54: =SUMIFS(Transactions!$E$5:$E$1504,Transactions!$K$5:$K$1504,"Loan In",Transactions!$L$5:$L$1504,D$4)-SUMIFS(Transactions!$F$5:$F$1504,Transactions!$K$5:$K$1504,"Loan In",Transactions!$L$5:$L$1504,D$4) | E54: =SUMIFS(Transactions!$E$5:$E$1504,Transactions!$K$5:$K$1504,"Loan In",Transactions!$L$5:$L$1504,E$4)-SUMIFS(Transactions!$F$5:$F$1504,Transactions!$K$5:$K$1504,"Loan In",Transactions!$L$5:$L$1504,E$4) | F54: =SUMIFS(Transactions!$E$5:$E$1504,Transactions!$K$5:$K$1504,"Loan In",Transactions!$L$5:$L$1504,F$4)-SUMIFS(Transactions!$F$5:$F$1504,Transactions!$K$5:$K$1504,"Loan In",Transactions!$L$5:$L$1504,F$4) | G54: =SUMIFS(Transactions!$E$5:$E$1504,Transactions!$K$5:$K$1504,"Loan In",Transactions!$L$5:$L$1504,G$4)-SUMIFS(Transactions!$F$5:$F$1504,Transactions!$K$5:$K$1504,"Loan In",Transactions!$L$5:$L$1504,G$4) | H54: =SUMIFS(Transactions!$E$5:$E$1504,Transactions!$K$5:$K$1504,"Loan In",Transactions!$L$5:$L$1504,H$4)-SUMIFS(Transactions!$F$5:$F$1504,Transactions!$K$5:$K$1504,"Loan In",Transactions!$L$5:$L$1504,H$4) | I54: =SUMIFS(Transactions!$E$5:$E$1504,Transactions!$K$5:$K$1504,"Loan In",Transactions!$L$5:$L$1504,I$4)-SUMIFS(Transactions!$F$5:$F$1504,Transactions!$K$5:$K$1504,"Loan In",Transactions!$L$5:$L$1504,I$4) | ... M54: =SUMIFS(Transactions!$E$5:$E$1504,Transactions!$K$5:$K$1504,"Loan In",Transactions!$L$5:$L$1504,M$4)-SUMIFS(Transactions!$F$5:$F$1504,Transactions!$K$5:$K$1504,"Loan In",Transactions!$L$5:$L$1504,M$4) | N54: =SUM(B54:M54)
A55: Loan repayments | B55: =SUMIFS(Transactions!$F$5:$F$1504,Transactions!$K$5:$K$1504,"Loan Repayment",Transactions!$L$5:$L$1504,B$4)-SUMIFS(Transactions!$E$5:$E$1504,Transactions!$K$5:$K$1504,"Loan Repayment",Transactions!$L$5:$L$1504,B$4) | C55: =SUMIFS(Transactions!$F$5:$F$1504,Transactions!$K$5:$K$1504,"Loan Repayment",Transactions!$L$5:$L$1504,C$4)-SUMIFS(Transactions!$E$5:$E$1504,Transactions!$K$5:$K$1504,"Loan Repayment",Transactions!$L$5:$L$1504,C$4) | D55: =SUMIFS(Transactions!$F$5:$F$1504,Transactions!$K$5:$K$1504,"Loan Repayment",Transactions!$L$5:$L$1504,D$4)-SUMIFS(Transactions!$E$5:$E$1504,Transactions!$K$5:$K$1504,"Loan Repayment",Transactions!$L$5:$L$1504,D$4) | E55: =SUMIFS(Transactions!$F$5:$F$1504,Transactions!$K$5:$K$1504,"Loan Repayment",Transactions!$L$5:$L$1504,E$4)-SUMIFS(Transactions!$E$5:$E$1504,Transactions!$K$5:$K$1504,"Loan Repayment",Transactions!$L$5:$L$1504,E$4) | F55: =SUMIFS(Transactions!$F$5:$F$1504,Transactions!$K$5:$K$1504,"Loan Repayment",Transactions!$L$5:$L$1504,F$4)-SUMIFS(Transactions!$E$5:$E$1504,Transactions!$K$5:$K$1504,"Loan Repayment",Transactions!$L$5:$L$1504,F$4) | G55: =SUMIFS(Transactions!$F$5:$F$1504,Transactions!$K$5:$K$1504,"Loan Repayment",Transactions!$L$5:$L$1504,G$4)-SUMIFS(Transactions!$E$5:$E$1504,Transactions!$K$5:$K$1504,"Loan Repayment",Transactions!$L$5:$L$1504,G$4) | H55: =SUMIFS(Transactions!$F$5:$F$1504,Transactions!$K$5:$K$1504,"Loan Repayment",Transactions!$L$5:$L$1504,H$4)-SUMIFS(Transactions!$E$5:$E$1504,Transactions!$K$5:$K$1504,"Loan Repayment",Transactions!$L$5:$L$1504,H$4) | I55: =SUMIFS(Transactions!$F$5:$F$1504,Transactions!$K$5:$K$1504,"Loan Repayment",Transactions!$L$5:$L$1504,I$4)-SUMIFS(Transactions!$E$5:$E$1504,Transactions!$K$5:$K$1504,"Loan Repayment",Transactions!$L$5:$L$1504,I$4) | ... M55: =SUMIFS(Transactions!$F$5:$F$1504,Transactions!$K$5:$K$1504,"Loan Repayment",Transactions!$L$5:$L$1504,M$4)-SUMIFS(Transactions!$E$5:$E$1504,Transactions!$K$5:$K$1504,"Loan Repayment",Transactions!$L$5:$L$1504,M$4) | N55: =SUM(B55:M55)
A57: How to read this: Revenue − Direct costs = Gross profit. Gross profit − Overheads = Net profit. Owner drawings and tax come OUT of net profit; they are shown in the memo, not as costs.

Sheet Cash Flow
A1: Cash Flow: where did the money actually go?
A2: Profit is an opinion, cash is a fact. Closing cash should match your real bank + cash balances.
A4: Rs | B4: ='Monthly P&L'!B4 | C4: ='Monthly P&L'!C4 | D4: ='Monthly P&L'!D4 | E4: ='Monthly P&L'!E4 | F4: ='Monthly P&L'!F4 | G4: ='Monthly P&L'!G4 | H4: ='Monthly P&L'!H4 | I4: ='Monthly P&L'!I4 | ... M4: ='Monthly P&L'!M4 | N4: FY total
A5: Opening cash (all accounts) | B5: =Setup!$B$20 | C5: =B22 | D5: =C22 | E5: =D22 | F5: =E22 | G5: =F22 | H5: =G22 | I5: =H22 | J5: =I22 | ... M5: =L22
A6: CASH IN
A7: From clients (revenue) | B7: =SUMIFS(Transactions!$E$5:$E$1504,Transactions!$K$5:$K$1504,"Income",Transactions!$L$5:$L$1504,B$4) | C7: =SUMIFS(Transactions!$E$5:$E$1504,Transactions!$K$5:$K$1504,"Income",Transactions!$L$5:$L$1504,C$4) | D7: =SUMIFS(Transactions!$E$5:$E$1504,Transactions!$K$5:$K$1504,"Income",Transactions!$L$5:$L$1504,D$4) | E7: =SUMIFS(Transactions!$E$5:$E$1504,Transactions!$K$5:$K$1504,"Income",Transactions!$L$5:$L$1504,E$4) | F7: =SUMIFS(Transactions!$E$5:$E$1504,Transactions!$K$5:$K$1504,"Income",Transactions!$L$5:$L$1504,F$4) | G7: =SUMIFS(Transactions!$E$5:$E$1504,Transactions!$K$5:$K$1504,"Income",Transactions!$L$5:$L$1504,G$4) | H7: =SUMIFS(Transactions!$E$5:$E$1504,Transactions!$K$5:$K$1504,"Income",Transactions!$L$5:$L$1504,H$4) | I7: =SUMIFS(Transactions!$E$5:$E$1504,Transactions!$K$5:$K$1504,"Income",Transactions!$L$5:$L$1504,I$4) | ... M7: =SUMIFS(Transactions!$E$5:$E$1504,Transactions!$K$5:$K$1504,"Income",Transactions!$L$5:$L$1504,M$4) | N7: =SUM(B7:M7)
A8: Refunds on costs | B8: =SUMIFS(Transactions!$E$5:$E$1504,Transactions!$K$5:$K$1504,"Direct Cost",Transactions!$L$5:$L$1504,B$4)+SUMIFS(Transactions!$E$5:$E$1504,Transactions!$K$5:$K$1504,"Operating Expense",Transactions!$L$5:$L$1504,B$4)+SUMIFS(Transactions!$E$5:$E$1504,Transactions!$K$5:$K$1504,"Asset Purchase",Transactions!$L$5:$L$1504,B$4)+SUMIFS(Transactions!$E$5:$E$1504,Transactions!$K$5:$K$1504,"Tax Payment",Transactions!$L$5:$L$1504,B$4) | C8: =SUMIFS(Transactions!$E$5:$E$1504,Transactions!$K$5:$K$1504,"Direct Cost",Transactions!$L$5:$L$1504,C$4)+SUMIFS(Transactions!$E$5:$E$1504,Transactions!$K$5:$K$1504,"Operating Expense",Transactions!$L$5:$L$1504,C$4)+SUMIFS(Transactions!$E$5:$E$1504,Transactions!$K$5:$K$1504,"Asset Purchase",Transactions!$L$5:$L$1504,C$4)+SUMIFS(Transactions!$E$5:$E$1504,Transactions!$K$5:$K$1504,"Tax Payment",Transactions!$L$5:$L$1504,C$4) | D8: =SUMIFS(Transactions!$E$5:$E$1504,Transactions!$K$5:$K$1504,"Direct Cost",Transactions!$L$5:$L$1504,D$4)+SUMIFS(Transactions!$E$5:$E$1504,Transactions!$K$5:$K$1504,"Operating Expense",Transactions!$L$5:$L$1504,D$4)+SUMIFS(Transactions!$E$5:$E$1504,Transactions!$K$5:$K$1504,"Asset Purchase",Transactions!$L$5:$L$1504,D$4)+SUMIFS(Transactions!$E$5:$E$1504,Transactions!$K$5:$K$1504,"Tax Payment",Transactions!$L$5:$L$1504,D$4) | E8: =SUMIFS(Transactions!$E$5:$E$1504,Transactions!$K$5:$K$1504,"Direct Cost",Transactions!$L$5:$L$1504,E$4)+SUMIFS(Transactions!$E$5:$E$1504,Transactions!$K$5:$K$1504,"Operating Expense",Transactions!$L$5:$L$1504,E$4)+SUMIFS(Transactions!$E$5:$E$1504,Transactions!$K$5:$K$1504,"Asset Purchase",Transactions!$L$5:$L$1504,E$4)+SUMIFS(Transactions!$E$5:$E$1504,Transactions!$K$5:$K$1504,"Tax Payment",Transactions!$L$5:$L$1504,E$4) | F8: =SUMIFS(Transactions!$E$5:$E$1504,Transactions!$K$5:$K$1504,"Direct Cost",Transactions!$L$5:$L$1504,F$4)+SUMIFS(Transactions!$E$5:$E$1504,Transactions!$K$5:$K$1504,"Operating Expense",Transactions!$L$5:$L$1504,F$4)+SUMIFS(Transactions!$E$5:$E$1504,Transactions!$K$5:$K$1504,"Asset Purchase",Transactions!$L$5:$L$1504,F$4)+SUMIFS(Transactions!$E$5:$E$1504,Transactions!$K$5:$K$1504,"Tax Payment",Transactions!$L$5:$L$1504,F$4) | G8: =SUMIFS(Transactions!$E$5:$E$1504,Transactions!$K$5:$K$1504,"Direct Cost",Transactions!$L$5:$L$1504,G$4)+SUMIFS(Transactions!$E$5:$E$1504,Transactions!$K$5:$K$1504,"Operating Expense",Transactions!$L$5:$L$1504,G$4)+SUMIFS(Transactions!$E$5:$E$1504,Transactions!$K$5:$K$1504,"Asset Purchase",Transactions!$L$5:$L$1504,G$4)+SUMIFS(Transactions!$E$5:$E$1504,Transactions!$K$5:$K$1504,"Tax Payment",Transactions!$L$5:$L$1504,G$4) | H8: =SUMIFS(Transactions!$E$5:$E$1504,Transactions!$K$5:$K$1504,"Direct Cost",Transactions!$L$5:$L$1504,H$4)+SUMIFS(Transactions!$E$5:$E$1504,Transactions!$K$5:$K$1504,"Operating Expense",Transactions!$L$5:$L$1504,H$4)+SUMIFS(Transactions!$E$5:$E$1504,Transactions!$K$5:$K$1504,"Asset Purchase",Transactions!$L$5:$L$1504,H$4)+SUMIFS(Transactions!$E$5:$E$1504,Transactions!$K$5:$K$1504,"Tax Payment",Transactions!$L$5:$L$1504,H$4) | I8: =SUMIFS(Transactions!$E$5:$E$1504,Transactions!$K$5:$K$1504,"Direct Cost",Transactions!$L$5:$L$1504,I$4)+SUMIFS(Transactions!$E$5:$E$1504,Transactions!$K$5:$K$1504,"Operating Expense",Transactions!$L$5:$L$1504,I$4)+SUMIFS(Transactions!$E$5:$E$1504,Transactions!$K$5:$K$1504,"Asset Purchase",Transactions!$L$5:$L$1504,I$4)+SUMIFS(Transactions!$E$5:$E$1504,Transactions!$K$5:$K$1504,"Tax Payment",Transactions!$L$5:$L$1504,I$4) | ... M8: =SUMIFS(Transactions!$E$5:$E$1504,Transactions!$K$5:$K$1504,"Direct Cost",Transactions!$L$5:$L$1504,M$4)+SUMIFS(Transactions!$E$5:$E$1504,Transactions!$K$5:$K$1504,"Operating Expense",Transactions!$L$5:$L$1504,M$4)+SUMIFS(Transactions!$E$5:$E$1504,Transactions!$K$5:$K$1504,"Asset Purchase",Transactions!$L$5:$L$1504,M$4)+SUMIFS(Transactions!$E$5:$E$1504,Transactions!$K$5:$K$1504,"Tax Payment",Transactions!$L$5:$L$1504,M$4) | N8: =SUM(B8:M8)
A9: Owner capital put in | B9: =SUMIFS(Transactions!$E$5:$E$1504,Transactions!$K$5:$K$1504,"Owner Capital",Transactions!$L$5:$L$1504,B$4) | C9: =SUMIFS(Transactions!$E$5:$E$1504,Transactions!$K$5:$K$1504,"Owner Capital",Transactions!$L$5:$L$1504,C$4) | D9: =SUMIFS(Transactions!$E$5:$E$1504,Transactions!$K$5:$K$1504,"Owner Capital",Transactions!$L$5:$L$1504,D$4) | E9: =SUMIFS(Transactions!$E$5:$E$1504,Transactions!$K$5:$K$1504,"Owner Capital",Transactions!$L$5:$L$1504,E$4) | F9: =SUMIFS(Transactions!$E$5:$E$1504,Transactions!$K$5:$K$1504,"Owner Capital",Transactions!$L$5:$L$1504,F$4) | G9: =SUMIFS(Transactions!$E$5:$E$1504,Transactions!$K$5:$K$1504,"Owner Capital",Transactions!$L$5:$L$1504,G$4) | H9: =SUMIFS(Transactions!$E$5:$E$1504,Transactions!$K$5:$K$1504,"Owner Capital",Transactions!$L$5:$L$1504,H$4) | I9: =SUMIFS(Transactions!$E$5:$E$1504,Transactions!$K$5:$K$1504,"Owner Capital",Transactions!$L$5:$L$1504,I$4) | ... M9: =SUMIFS(Transactions!$E$5:$E$1504,Transactions!$K$5:$K$1504,"Owner Capital",Transactions!$L$5:$L$1504,M$4) | N9: =SUM(B9:M9)
A10: Loans received | B10: =SUMIFS(Transactions!$E$5:$E$1504,Transactions!$K$5:$K$1504,"Loan In",Transactions!$L$5:$L$1504,B$4) | C10: =SUMIFS(Transactions!$E$5:$E$1504,Transactions!$K$5:$K$1504,"Loan In",Transactions!$L$5:$L$1504,C$4) | D10: =SUMIFS(Transactions!$E$5:$E$1504,Transactions!$K$5:$K$1504,"Loan In",Transactions!$L$5:$L$1504,D$4) | E10: =SUMIFS(Transactions!$E$5:$E$1504,Transactions!$K$5:$K$1504,"Loan In",Transactions!$L$5:$L$1504,E$4) | F10: =SUMIFS(Transactions!$E$5:$E$1504,Transactions!$K$5:$K$1504,"Loan In",Transactions!$L$5:$L$1504,F$4) | G10: =SUMIFS(Transactions!$E$5:$E$1504,Transactions!$K$5:$K$1504,"Loan In",Transactions!$L$5:$L$1504,G$4) | H10: =SUMIFS(Transactions!$E$5:$E$1504,Transactions!$K$5:$K$1504,"Loan In",Transactions!$L$5:$L$1504,H$4) | I10: =SUMIFS(Transactions!$E$5:$E$1504,Transactions!$K$5:$K$1504,"Loan In",Transactions!$L$5:$L$1504,I$4) | ... M10: =SUMIFS(Transactions!$E$5:$E$1504,Transactions!$K$5:$K$1504,"Loan In",Transactions!$L$5:$L$1504,M$4) | N10: =SUM(B10:M10)
A11: Total cash in | B11: =SUM(B7:B10) | C11: =SUM(C7:C10) | D11: =SUM(D7:D10) | E11: =SUM(E7:E10) | F11: =SUM(F7:F10) | G11: =SUM(G7:G10) | H11: =SUM(H7:H10) | I11: =SUM(I7:I10) | ... M11: =SUM(M7:M10) | N11: =SUM(B11:M11)
A12: CASH OUT
A13: Direct costs paid | B13: =SUMIFS(Transactions!$F$5:$F$1504,Transactions!$K$5:$K$1504,"Direct Cost",Transactions!$L$5:$L$1504,B$4) | C13: =SUMIFS(Transactions!$F$5:$F$1504,Transactions!$K$5:$K$1504,"Direct Cost",Transactions!$L$5:$L$1504,C$4) | D13: =SUMIFS(Transactions!$F$5:$F$1504,Transactions!$K$5:$K$1504,"Direct Cost",Transactions!$L$5:$L$1504,D$4) | E13: =SUMIFS(Transactions!$F$5:$F$1504,Transactions!$K$5:$K$1504,"Direct Cost",Transactions!$L$5:$L$1504,E$4) | F13: =SUMIFS(Transactions!$F$5:$F$1504,Transactions!$K$5:$K$1504,"Direct Cost",Transactions!$L$5:$L$1504,F$4) | G13: =SUMIFS(Transactions!$F$5:$F$1504,Transactions!$K$5:$K$1504,"Direct Cost",Transactions!$L$5:$L$1504,G$4) | H13: =SUMIFS(Transactions!$F$5:$F$1504,Transactions!$K$5:$K$1504,"Direct Cost",Transactions!$L$5:$L$1504,H$4) | I13: =SUMIFS(Transactions!$F$5:$F$1504,Transactions!$K$5:$K$1504,"Direct Cost",Transactions!$L$5:$L$1504,I$4) | ... M13: =SUMIFS(Transactions!$F$5:$F$1504,Transactions!$K$5:$K$1504,"Direct Cost",Transactions!$L$5:$L$1504,M$4) | N13: =SUM(B13:M13)
A14: Overheads paid | B14: =SUMIFS(Transactions!$F$5:$F$1504,Transactions!$K$5:$K$1504,"Operating Expense",Transactions!$L$5:$L$1504,B$4) | C14: =SUMIFS(Transactions!$F$5:$F$1504,Transactions!$K$5:$K$1504,"Operating Expense",Transactions!$L$5:$L$1504,C$4) | D14: =SUMIFS(Transactions!$F$5:$F$1504,Transactions!$K$5:$K$1504,"Operating Expense",Transactions!$L$5:$L$1504,D$4) | E14: =SUMIFS(Transactions!$F$5:$F$1504,Transactions!$K$5:$K$1504,"Operating Expense",Transactions!$L$5:$L$1504,E$4) | F14: =SUMIFS(Transactions!$F$5:$F$1504,Transactions!$K$5:$K$1504,"Operating Expense",Transactions!$L$5:$L$1504,F$4) | G14: =SUMIFS(Transactions!$F$5:$F$1504,Transactions!$K$5:$K$1504,"Operating Expense",Transactions!$L$5:$L$1504,G$4) | H14: =SUMIFS(Transactions!$F$5:$F$1504,Transactions!$K$5:$K$1504,"Operating Expense",Transactions!$L$5:$L$1504,H$4) | I14: =SUMIFS(Transactions!$F$5:$F$1504,Transactions!$K$5:$K$1504,"Operating Expense",Transactions!$L$5:$L$1504,I$4) | ... M14: =SUMIFS(Transactions!$F$5:$F$1504,Transactions!$K$5:$K$1504,"Operating Expense",Transactions!$L$5:$L$1504,M$4) | N14: =SUM(B14:M14)
A15: Owner drawings | B15: =SUMIFS(Transactions!$F$5:$F$1504,Transactions!$K$5:$K$1504,"Owner Drawings",Transactions!$L$5:$L$1504,B$4) | C15: =SUMIFS(Transactions!$F$5:$F$1504,Transactions!$K$5:$K$1504,"Owner Drawings",Transactions!$L$5:$L$1504,C$4) | D15: =SUMIFS(Transactions!$F$5:$F$1504,Transactions!$K$5:$K$1504,"Owner Drawings",Transactions!$L$5:$L$1504,D$4) | E15: =SUMIFS(Transactions!$F$5:$F$1504,Transactions!$K$5:$K$1504,"Owner Drawings",Transactions!$L$5:$L$1504,E$4) | F15: =SUMIFS(Transactions!$F$5:$F$1504,Transactions!$K$5:$K$1504,"Owner Drawings",Transactions!$L$5:$L$1504,F$4) | G15: =SUMIFS(Transactions!$F$5:$F$1504,Transactions!$K$5:$K$1504,"Owner Drawings",Transactions!$L$5:$L$1504,G$4) | H15: =SUMIFS(Transactions!$F$5:$F$1504,Transactions!$K$5:$K$1504,"Owner Drawings",Transactions!$L$5:$L$1504,H$4) | I15: =SUMIFS(Transactions!$F$5:$F$1504,Transactions!$K$5:$K$1504,"Owner Drawings",Transactions!$L$5:$L$1504,I$4) | ... M15: =SUMIFS(Transactions!$F$5:$F$1504,Transactions!$K$5:$K$1504,"Owner Drawings",Transactions!$L$5:$L$1504,M$4) | N15: =SUM(B15:M15)
A16: Tax paid | B16: =SUMIFS(Transactions!$F$5:$F$1504,Transactions!$K$5:$K$1504,"Tax Payment",Transactions!$L$5:$L$1504,B$4) | C16: =SUMIFS(Transactions!$F$5:$F$1504,Transactions!$K$5:$K$1504,"Tax Payment",Transactions!$L$5:$L$1504,C$4) | D16: =SUMIFS(Transactions!$F$5:$F$1504,Transactions!$K$5:$K$1504,"Tax Payment",Transactions!$L$5:$L$1504,D$4) | E16: =SUMIFS(Transactions!$F$5:$F$1504,Transactions!$K$5:$K$1504,"Tax Payment",Transactions!$L$5:$L$1504,E$4) | F16: =SUMIFS(Transactions!$F$5:$F$1504,Transactions!$K$5:$K$1504,"Tax Payment",Transactions!$L$5:$L$1504,F$4) | G16: =SUMIFS(Transactions!$F$5:$F$1504,Transactions!$K$5:$K$1504,"Tax Payment",Transactions!$L$5:$L$1504,G$4) | H16: =SUMIFS(Transactions!$F$5:$F$1504,Transactions!$K$5:$K$1504,"Tax Payment",Transactions!$L$5:$L$1504,H$4) | I16: =SUMIFS(Transactions!$F$5:$F$1504,Transactions!$K$5:$K$1504,"Tax Payment",Transactions!$L$5:$L$1504,I$4) | ... M16: =SUMIFS(Transactions!$F$5:$F$1504,Transactions!$K$5:$K$1504,"Tax Payment",Transactions!$L$5:$L$1504,M$4) | N16: =SUM(B16:M16)
A17: Equipment & assets | B17: =SUMIFS(Transactions!$F$5:$F$1504,Transactions!$K$5:$K$1504,"Asset Purchase",Transactions!$L$5:$L$1504,B$4) | C17: =SUMIFS(Transactions!$F$5:$F$1504,Transactions!$K$5:$K$1504,"Asset Purchase",Transactions!$L$5:$L$1504,C$4) | D17: =SUMIFS(Transactions!$F$5:$F$1504,Transactions!$K$5:$K$1504,"Asset Purchase",Transactions!$L$5:$L$1504,D$4) | E17: =SUMIFS(Transactions!$F$5:$F$1504,Transactions!$K$5:$K$1504,"Asset Purchase",Transactions!$L$5:$L$1504,E$4) | F17: =SUMIFS(Transactions!$F$5:$F$1504,Transactions!$K$5:$K$1504,"Asset Purchase",Transactions!$L$5:$L$1504,F$4) | G17: =SUMIFS(Transactions!$F$5:$F$1504,Transactions!$K$5:$K$1504,"Asset Purchase",Transactions!$L$5:$L$1504,G$4) | H17: =SUMIFS(Transactions!$F$5:$F$1504,Transactions!$K$5:$K$1504,"Asset Purchase",Transactions!$L$5:$L$1504,H$4) | I17: =SUMIFS(Transactions!$F$5:$F$1504,Transactions!$K$5:$K$1504,"Asset Purchase",Transactions!$L$5:$L$1504,I$4) | ... M17: =SUMIFS(Transactions!$F$5:$F$1504,Transactions!$K$5:$K$1504,"Asset Purchase",Transactions!$L$5:$L$1504,M$4) | N17: =SUM(B17:M17)
A18: Loan repayments | B18: =SUMIFS(Transactions!$F$5:$F$1504,Transactions!$K$5:$K$1504,"Loan Repayment",Transactions!$L$5:$L$1504,B$4) | C18: =SUMIFS(Transactions!$F$5:$F$1504,Transactions!$K$5:$K$1504,"Loan Repayment",Transactions!$L$5:$L$1504,C$4) | D18: =SUMIFS(Transactions!$F$5:$F$1504,Transactions!$K$5:$K$1504,"Loan Repayment",Transactions!$L$5:$L$1504,D$4) | E18: =SUMIFS(Transactions!$F$5:$F$1504,Transactions!$K$5:$K$1504,"Loan Repayment",Transactions!$L$5:$L$1504,E$4) | F18: =SUMIFS(Transactions!$F$5:$F$1504,Transactions!$K$5:$K$1504,"Loan Repayment",Transactions!$L$5:$L$1504,F$4) | G18: =SUMIFS(Transactions!$F$5:$F$1504,Transactions!$K$5:$K$1504,"Loan Repayment",Transactions!$L$5:$L$1504,G$4) | H18: =SUMIFS(Transactions!$F$5:$F$1504,Transactions!$K$5:$K$1504,"Loan Repayment",Transactions!$L$5:$L$1504,H$4) | I18: =SUMIFS(Transactions!$F$5:$F$1504,Transactions!$K$5:$K$1504,"Loan Repayment",Transactions!$L$5:$L$1504,I$4) | ... M18: =SUMIFS(Transactions!$F$5:$F$1504,Transactions!$K$5:$K$1504,"Loan Repayment",Transactions!$L$5:$L$1504,M$4) | N18: =SUM(B18:M18)
A19: Refunds to clients | B19: =SUMIFS(Transactions!$F$5:$F$1504,Transactions!$K$5:$K$1504,"Income",Transactions!$L$5:$L$1504,B$4) | C19: =SUMIFS(Transactions!$F$5:$F$1504,Transactions!$K$5:$K$1504,"Income",Transactions!$L$5:$L$1504,C$4) | D19: =SUMIFS(Transactions!$F$5:$F$1504,Transactions!$K$5:$K$1504,"Income",Transactions!$L$5:$L$1504,D$4) | E19: =SUMIFS(Transactions!$F$5:$F$1504,Transactions!$K$5:$K$1504,"Income",Transactions!$L$5:$L$1504,E$4) | F19: =SUMIFS(Transactions!$F$5:$F$1504,Transactions!$K$5:$K$1504,"Income",Transactions!$L$5:$L$1504,F$4) | G19: =SUMIFS(Transactions!$F$5:$F$1504,Transactions!$K$5:$K$1504,"Income",Transactions!$L$5:$L$1504,G$4) | H19: =SUMIFS(Transactions!$F$5:$F$1504,Transactions!$K$5:$K$1504,"Income",Transactions!$L$5:$L$1504,H$4) | I19: =SUMIFS(Transactions!$F$5:$F$1504,Transactions!$K$5:$K$1504,"Income",Transactions!$L$5:$L$1504,I$4) | ... M19: =SUMIFS(Transactions!$F$5:$F$1504,Transactions!$K$5:$K$1504,"Income",Transactions!$L$5:$L$1504,M$4) | N19: =SUM(B19:M19)
A20: Total cash out | B20: =SUM(B13:B19) | C20: =SUM(C13:C19) | D20: =SUM(D13:D19) | E20: =SUM(E13:E19) | F20: =SUM(F13:F19) | G20: =SUM(G13:G19) | H20: =SUM(H13:H19) | I20: =SUM(I13:I19) | ... M20: =SUM(M13:M19) | N20: =SUM(B20:M20)
A21: Net cash flow (in − out) | B21: =B11-B20 | C21: =C11-C20 | D21: =D11-D20 | E21: =E11-E20 | F21: =F11-F20 | G21: =G11-G20 | H21: =H11-H20 | I21: =I11-I20 | ... M21: =M11-M20 | N21: =SUM(B21:M21)
A22: CLOSING CASH (check against bank!) | B22: =B5+SUMIFS(Transactions!$E$5:$E$1504,Transactions!$L$5:$L$1504,B$4)-SUMIFS(Transactions!$F$5:$F$1504,Transactions!$L$5:$L$1504,B$4) | C22: =C5+SUMIFS(Transactions!$E$5:$E$1504,Transactions!$L$5:$L$1504,C$4)-SUMIFS(Transactions!$F$5:$F$1504,Transactions!$L$5:$L$1504,C$4) | D22: =D5+SUMIFS(Transactions!$E$5:$E$1504,Transactions!$L$5:$L$1504,D$4)-SUMIFS(Transactions!$F$5:$F$1504,Transactions!$L$5:$L$1504,D$4) | E22: =E5+SUMIFS(Transactions!$E$5:$E$1504,Transactions!$L$5:$L$1504,E$4)-SUMIFS(Transactions!$F$5:$F$1504,Transactions!$L$5:$L$1504,E$4) | F22: =F5+SUMIFS(Transactions!$E$5:$E$1504,Transactions!$L$5:$L$1504,F$4)-SUMIFS(Transactions!$F$5:$F$1504,Transactions!$L$5:$L$1504,F$4) | G22: =G5+SUMIFS(Transactions!$E$5:$E$1504,Transactions!$L$5:$L$1504,G$4)-SUMIFS(Transactions!$F$5:$F$1504,Transactions!$L$5:$L$1504,G$4) | H22: =H5+SUMIFS(Transactions!$E$5:$E$1504,Transactions!$L$5:$L$1504,H$4)-SUMIFS(Transactions!$F$5:$F$1504,Transactions!$L$5:$L$1504,H$4) | I22: =I5+SUMIFS(Transactions!$E$5:$E$1504,Transactions!$L$5:$L$1504,I$4)-SUMIFS(Transactions!$F$5:$F$1504,Transactions!$L$5:$L$1504,I$4) | ... M22: =M5+SUMIFS(Transactions!$E$5:$E$1504,Transactions!$L$5:$L$1504,M$4)-SUMIFS(Transactions!$F$5:$F$1504,Transactions!$L$5:$L$1504,M$4)
A23: Actual bank + cash at month end (type it)
A24: Difference (should be 0) | B24: =IF(B23="","",B23-B22) | C24: =IF(C23="","",C23-C22) | D24: =IF(D23="","",D23-D22) | E24: =IF(E23="","",E23-E22) | F24: =IF(F23="","",F23-F22) | G24: =IF(G23="","",G23-G22) | H24: =IF(H23="","",H23-H22) | I24: =IF(I23="","",I23-I22) | ... M24: =IF(M23="","",M23-M22)
A26: Why closing cash and profit differ: unpaid invoices, owner drawings, tax, equipment and loans move cash without being profit or cost. Transfers between your own accounts cancel out in the closing balance.

Sheet Dashboard
A1: Dashboard: the business on one page
A2: Pick a month in the yellow cell. Everything else is automatic.
A4: Month to review: | B4: 46266 | D4: Pick from the list (financial-year months).
A6: THIS MONTH | D6: MONEY OWED TO US
A7: Revenue | B7: =IFERROR(INDEX('Monthly P&L'!$B$11:$M$11,MATCH($B$4,'Monthly P&L'!$B$4:$M$4,0)),0) | D7: Total outstanding invoices | E7: =SUM(Invoices!$I$5:$I$404)
A8: Gross profit | B8: =IFERROR(INDEX('Monthly P&L'!$B$21:$M$21,MATCH($B$4,'Monthly P&L'!$B$4:$M$4,0)),0) | D8: Overdue amount | E8: =SUMIFS(Invoices!$I$5:$I$404,Invoices!$K$5:$K$404,"Overdue")
A9: Gross margin % | B9: =IFERROR(INDEX('Monthly P&L'!$B$22:$M$22,MATCH($B$4,'Monthly P&L'!$B$4:$M$4,0)),0) | D9: Number of overdue invoices | E9: =COUNTIF(Invoices!$K$5:$K$404,"Overdue")
A10: Overheads | B10: =IFERROR(INDEX('Monthly P&L'!$B$43:$M$43,MATCH($B$4,'Monthly P&L'!$B$4:$M$4,0)),0)
A11: Net profit | B11: =IFERROR(INDEX('Monthly P&L'!$B$45:$M$45,MATCH($B$4,'Monthly P&L'!$B$4:$M$4,0)),0) | D11: RISK & HEALTH
A12: Net margin % | B12: =IFERROR(INDEX('Monthly P&L'!$B$46:$M$46,MATCH($B$4,'Monthly P&L'!$B$4:$M$4,0)),0) | D12: Biggest client share of revenue | E12: =MAX(Clients!$G$5:$G$104)
A13: Owner drawings | B13: =IFERROR(INDEX('Monthly P&L'!$B$50:$M$50,MATCH($B$4,'Monthly P&L'!$B$4:$M$4,0)),0) | D13: Avg monthly spending (last 3 months) | E13: =SUMPRODUCT(('Monthly P&L'!$B$4:$M$4<=$B$4)*('Monthly P&L'!$B$4:$M$4>EDATE($B$4,-3))*('Monthly P&L'!$B$19:$M$19+'Monthly P&L'!$B$43:$M$43))/3
A14: Closing cash (Cash Flow) | B14: =IFERROR(INDEX('Cash Flow'!$B$22:$M$22,MATCH($B$4,'Cash Flow'!$B$4:$M$4,0)),0) | D14: Cash runway (months of spending covered) | E14: =IF(E13<=0,0,B14/E13)
D15: Tax reserve suggested YTD | E15: =SUMPRODUCT(('Monthly P&L'!$B$4:$M$4<=$B$4)*'Monthly P&L'!$B$47:$M$47)
A16: YEAR TO DATE (from April)
A17: Revenue YTD | B17: =SUMPRODUCT(('Monthly P&L'!$B$4:$M$4<=$B$4)*'Monthly P&L'!$B$11:$M$11) | D17: SALES
A18: Net profit YTD | B18: =SUMPRODUCT(('Monthly P&L'!$B$4:$M$4<=$B$4)*'Monthly P&L'!$B$45:$M$45) | D18: Open pipeline value | E18: ='Sales Pipeline'!C3
A19: Net margin YTD | B19: =IF(B17=0,0,B18/B17) | D19: Win rate | E19: ='Sales Pipeline'!E3
A20: Average monthly revenue YTD | B20: =IFERROR(B17/SUMPRODUCT(('Monthly P&L'!$B$4:$M$4<=$B$4)*1),0)
A23: ACCOUNT BALANCES TODAY | D23: WARNING SIGNS
A24: Account | B24: Balance (Rs) | D24: Net profit this month is negative | E24: =IF(B11<0,"⚠ YES","OK")
A25: =IF(Setup!$A$14="","",Setup!$A$14) | B25: =IF(A25="","",Setup!$B$14+SUMIFS(Transactions!$E$5:$E$1504,Transactions!$G$5:$G$1504,A25)-SUMIFS(Transactions!$F$5:$F$1504,Transactions!$G$5:$G$1504,A25)) | D25: Gross margin below 50% | E25: =IF(AND(B7<>0,B9<0.5),"⚠ YES","OK")
A26: =IF(Setup!$A$15="","",Setup!$A$15) | B26: =IF(A26="","",Setup!$B$15+SUMIFS(Transactions!$E$5:$E$1504,Transactions!$G$5:$G$1504,A26)-SUMIFS(Transactions!$F$5:$F$1504,Transactions!$G$5:$G$1504,A26)) | D26: One client is more than 30% of revenue | E26: =IF(E12>0.3,"⚠ YES","OK")
A27: =IF(Setup!$A$16="","",Setup!$A$16) | B27: =IF(A27="","",Setup!$B$16+SUMIFS(Transactions!$E$5:$E$1504,Transactions!$G$5:$G$1504,A27)-SUMIFS(Transactions!$F$5:$F$1504,Transactions!$G$5:$G$1504,A27)) | D27: Less than 3 months of cash runway | E27: =IF(AND(E13>0,E14<3),"⚠ YES","OK")
A28: =IF(Setup!$A$17="","",Setup!$A$17) | B28: =IF(A28="","",Setup!$B$17+SUMIFS(Transactions!$E$5:$E$1504,Transactions!$G$5:$G$1504,A28)-SUMIFS(Transactions!$F$5:$F$1504,Transactions!$G$5:$G$1504,A28)) | D28: Overdue invoices exist | E28: =IF(E9>0,"⚠ YES","OK")
A29: =IF(Setup!$A$18="","",Setup!$A$18) | B29: =IF(A29="","",Setup!$B$18+SUMIFS(Transactions!$E$5:$E$1504,Transactions!$G$5:$G$1504,A29)-SUMIFS(Transactions!$F$5:$F$1504,Transactions!$G$5:$G$1504,A29)) | D29: Transactions with a wrong category | E29: =IF(COUNTIF(Transactions!$K$5:$K$1504,"Check category")>0,"⚠ YES","OK")
A30: =IF(Setup!$A$19="","",Setup!$A$19) | B30: =IF(A30="","",Setup!$B$19+SUMIFS(Transactions!$E$5:$E$1504,Transactions!$G$5:$G$1504,A30)-SUMIFS(Transactions!$F$5:$F$1504,Transactions!$G$5:$G$1504,A30))
A33: Rules of thumb used above (assumptions, adjust to your business): services gross margin ≥ 50%; no client above 30% of revenue; keep at least 3 months of spending in cash.

Sheet Service Pricing
A1: Service Pricing: what does each service really earn?
A2: One row per service. Use it in Week 5 to find which services make money and what you should charge.
A3: Target gross margin: | C3: 0.5 | D3: Assumption: aim for at least 50% gross margin on services (a common rule of thumb). Change it to your target.
A5: Service | B5: Price you charge (Rs) | C5: Hours per job | D5: Cost per hour of whoever does it (Rs) | E5: Other direct costs per job (Rs) | F5: Labour cost (auto) | G5: Total cost per job (auto) | H5: Gross profit per job (auto) | I5: Gross margin (auto) | J5: Profit per hour worked (auto) | K5: Price for target margin (auto)
A6: EXAMPLE: Small business website | B6: 150000 | C6: 40 | D6: 1500 | E6: 10000 | F6: =IF(A6="","",N(C6)*N(D6)) | G6: =IF(A6="","",F6+N(E6)) | H6: =IF(A6="","",N(B6)-G6) | I6: =IF(OR(A6="",N(B6)=0),"",H6/B6) | J6: =IF(OR(A6="",N(C6)=0),"",H6/C6) | K6: =IF(A6="","",IF($C$3>=1,"",G6/(1-$C$3)))
F7: =IF(A7="","",N(C7)*N(D7)) | G7: =IF(A7="","",F7+N(E7)) | H7: =IF(A7="","",N(B7)-G7) | I7: =IF(OR(A7="",N(B7)=0),"",H7/B7) | J7: =IF(OR(A7="",N(C7)=0),"",H7/C7) | K7: =IF(A7="","",IF($C$3>=1,"",G7/(1-$C$3)))
F8: =IF(A8="","",N(C8)*N(D8)) | G8: =IF(A8="","",F8+N(E8)) | H8: =IF(A8="","",N(B8)-G8) | I8: =IF(OR(A8="",N(B8)=0),"",H8/B8) | J8: =IF(OR(A8="",N(C8)=0),"",H8/C8) | K8: =IF(A8="","",IF($C$3>=1,"",G8/(1-$C$3)))
F9: =IF(A9="","",N(C9)*N(D9)) | G9: =IF(A9="","",F9+N(E9)) | H9: =IF(A9="","",N(B9)-G9) | I9: =IF(OR(A9="",N(B9)=0),"",H9/B9) | J9: =IF(OR(A9="",N(C9)=0),"",H9/C9) | K9: =IF(A9="","",IF($C$3>=1,"",G9/(1-$C$3)))
F10: =IF(A10="","",N(C10)*N(D10)) | G10: =IF(A10="","",F10+N(E10)) | H10: =IF(A10="","",N(B10)-G10) | I10: =IF(OR(A10="",N(B10)=0),"",H10/B10) | J10: =IF(OR(A10="",N(C10)=0),"",H10/C10) | K10: =IF(A10="","",IF($C$3>=1,"",G10/(1-$C$3)))
F11: =IF(A11="","",N(C11)*N(D11)) | G11: =IF(A11="","",F11+N(E11)) | H11: =IF(A11="","",N(B11)-G11) | I11: =IF(OR(A11="",N(B11)=0),"",H11/B11) | J11: =IF(OR(A11="",N(C11)=0),"",H11/C11) | K11: =IF(A11="","",IF($C$3>=1,"",G11/(1-$C$3)))
F12: =IF(A12="","",N(C12)*N(D12)) | G12: =IF(A12="","",F12+N(E12)) | H12: =IF(A12="","",N(B12)-G12) | I12: =IF(OR(A12="",N(B12)=0),"",H12/B12) | J12: =IF(OR(A12="",N(C12)=0),"",H12/C12) | K12: =IF(A12="","",IF($C$3>=1,"",G12/(1-$C$3)))
F13: =IF(A13="","",N(C13)*N(D13)) | G13: =IF(A13="","",F13+N(E13)) | H13: =IF(A13="","",N(B13)-G13) | I13: =IF(OR(A13="",N(B13)=0),"",H13/B13) | J13: =IF(OR(A13="",N(C13)=0),"",H13/C13) | K13: =IF(A13="","",IF($C$3>=1,"",G13/(1-$C$3)))
F14: =IF(A14="","",N(C14)*N(D14)) | G14: =IF(A14="","",F14+N(E14)) | H14: =IF(A14="","",N(B14)-G14) | I14: =IF(OR(A14="",N(B14)=0),"",H14/B14) | J14: =IF(OR(A14="",N(C14)=0),"",H14/C14) | K14: =IF(A14="","",IF($C$3>=1,"",G14/(1-$C$3)))
F15: =IF(A15="","",N(C15)*N(D15)) | G15: =IF(A15="","",F15+N(E15)) | H15: =IF(A15="","",N(B15)-G15) | I15: =IF(OR(A15="",N(B15)=0),"",H15/B15) | J15: =IF(OR(A15="",N(C15)=0),"",H15/C15) | K15: =IF(A15="","",IF($C$3>=1,"",G15/(1-$C$3)))
F16: =IF(A16="","",N(C16)*N(D16)) | G16: =IF(A16="","",F16+N(E16)) | H16: =IF(A16="","",N(B16)-G16) | I16: =IF(OR(A16="",N(B16)=0),"",H16/B16) | J16: =IF(OR(A16="",N(C16)=0),"",H16/C16) | K16: =IF(A16="","",IF($C$3>=1,"",G16/(1-$C$3)))
F17: =IF(A17="","",N(C17)*N(D17)) | G17: =IF(A17="","",F17+N(E17)) | H17: =IF(A17="","",N(B17)-G17) | I17: =IF(OR(A17="",N(B17)=0),"",H17/B17) | J17: =IF(OR(A17="",N(C17)=0),"",H17/C17) | K17: =IF(A17="","",IF($C$3>=1,"",G17/(1-$C$3)))
A19: Cost per hour: if you do the work yourself, use the salary you want ÷ hours you work per month (e.g. Rs 200,000 ÷ 160 h = Rs 1,250/h). Red margin = below your target: raise the price, cut hours, or cut direct costs.

Sheet Forecast
A1: Forecast & Budget: October 2026 – March 2027
A2: Plan the next 6 months, then compare with what actually happened. Yellow = your assumptions.
A4: Rs | B4: 46296 | C4: =EDATE(B4,1) | D4: =EDATE(C4,1) | E4: =EDATE(D4,1) | F4: =EDATE(E4,1) | G4: =EDATE(F4,1) | H4: 6-month total
A5: REVENUE PLAN
A6: Number of jobs / paying clients | B6: 0 | C6: 0 | D6: 0 | E6: 0 | F6: 0 | G6: 0 | H6: =SUM(B6:G6)
A7: Average fee per job (Rs) | B7: 0 | C7: 0 | D7: 0 | E7: 0 | F7: 0 | G7: 0
A8: Forecast revenue | B8: =B6*B7 | C8: =C6*C7 | D8: =D6*D7 | E8: =E6*E7 | F8: =F6*F7 | G8: =G6*G7 | H8: =SUM(B8:G8)
A9: Direct costs as % of revenue | B9: 0.3 | C9: 0.3 | D9: 0.3 | E9: 0.3 | F9: 0.3 | G9: 0.3
A10: Forecast direct costs | B10: =B8*B9 | C10: =C8*C9 | D10: =D8*D9 | E10: =E8*E9 | F10: =F8*F9 | G10: =G8*G9 | H10: =SUM(B10:G10)
A11: Forecast gross profit | B11: =B8-B10 | C11: =C8-C10 | D11: =D8-D10 | E11: =E8-E10 | F11: =F8-F10 | G11: =G8-G10 | H11: =SUM(B11:G11)
A13: MONTHLY BUDGET FOR OVERHEADS
A14: Salaries – admin & sales (incl. EPF/ETF) | B14: 0 | C14: 0 | D14: 0 | E14: 0 | F14: 0 | G14: 0 | H14: =SUM(B14:G14)
A15: Rent & utilities | B15: 0 | C15: 0 | D15: 0 | E15: 0 | F15: 0 | G15: 0 | H15: =SUM(B15:G15)
A16: Internet, phone & software | B16: 0 | C16: 0 | D16: 0 | E16: 0 | F16: 0 | G16: 0 | H16: =SUM(B16:G16)
A17: Marketing & advertising | B17: 0 | C17: 0 | D17: 0 | E17: 0 | F17: 0 | G17: 0 | H17: =SUM(B17:G17)
A18: Professional fees (accountant) | B18: 0 | C18: 0 | D18: 0 | E18: 0 | F18: 0 | G18: 0 | H18: =SUM(B18:G18)
A19: Transport & other | B19: 0 | C19: 0 | D19: 0 | E19: 0 | F19: 0 | G19: 0 | H19: =SUM(B19:G19)
A20: Total overheads budget | B20: =SUM(B14:B19) | C20: =SUM(C14:C19) | D20: =SUM(D14:D19) | E20: =SUM(E14:E19) | F20: =SUM(F14:F19) | G20: =SUM(G14:G19) | H20: =SUM(B20:G20)
A22: FORECAST NET PROFIT | B22: =B11-B20 | C22: =C11-C20 | D22: =D11-D20 | E22: =E11-E20 | F22: =F11-F20 | G22: =G11-G20 | H22: =SUM(B22:G22)
A23: Owner salary (from Setup) | B23: =Setup!$B$9 | C23: =Setup!$B$9 | D23: =Setup!$B$9 | E23: =Setup!$B$9 | F23: =Setup!$B$9 | G23: =Setup!$B$9 | H23: =SUM(B23:G23)
A24: Tax reserve (Setup % of profit) | B24: =MAX(0,B22)*Setup!$B$8 | C24: =MAX(0,C22)*Setup!$B$8 | D24: =MAX(0,D22)*Setup!$B$8 | E24: =MAX(0,E22)*Setup!$B$8 | F24: =MAX(0,F22)*Setup!$B$8 | G24: =MAX(0,G22)*Setup!$B$8 | H24: =SUM(B24:G24)
A25: Left to reinvest or save | B25: =B22-B23-B24 | C25: =C22-C23-C24 | D25: =D22-D23-D24 | E25: =E22-E23-E24 | F25: =F22-F23-F24 | G25: =G22-G23-G24 | H25: =SUM(B25:G25)
A27: ACTUAL vs FORECAST (auto from Monthly P&L)
A28: Actual revenue | B28: =IFERROR(INDEX('Monthly P&L'!$B$11:$M$11,MATCH(B$4,'Monthly P&L'!$B$4:$M$4,0)),0) | C28: =IFERROR(INDEX('Monthly P&L'!$B$11:$M$11,MATCH(C$4,'Monthly P&L'!$B$4:$M$4,0)),0) | D28: =IFERROR(INDEX('Monthly P&L'!$B$11:$M$11,MATCH(D$4,'Monthly P&L'!$B$4:$M$4,0)),0) | E28: =IFERROR(INDEX('Monthly P&L'!$B$11:$M$11,MATCH(E$4,'Monthly P&L'!$B$4:$M$4,0)),0) | F28: =IFERROR(INDEX('Monthly P&L'!$B$11:$M$11,MATCH(F$4,'Monthly P&L'!$B$4:$M$4,0)),0) | G28: =IFERROR(INDEX('Monthly P&L'!$B$11:$M$11,MATCH(G$4,'Monthly P&L'!$B$4:$M$4,0)),0) | H28: =SUM(B28:G28)
A29: Revenue difference (actual − forecast) | B29: =B28-B8 | C29: =C28-C8 | D29: =D28-D8 | E29: =E28-E8 | F29: =F28-F8 | G29: =G28-G8 | H29: =SUM(B29:G29)
A30: Revenue achieved % | B30: =IF(B8=0,0,B28/B8) | C30: =IF(C8=0,0,C28/C8) | D30: =IF(D8=0,0,D28/D8) | E30: =IF(E8=0,0,E28/E8) | F30: =IF(F8=0,0,F28/F8) | G30: =IF(G8=0,0,G28/G8)
A31: Actual overheads | B31: =IFERROR(INDEX('Monthly P&L'!$B$43:$M$43,MATCH(B$4,'Monthly P&L'!$B$4:$M$4,0)),0) | C31: =IFERROR(INDEX('Monthly P&L'!$B$43:$M$43,MATCH(C$4,'Monthly P&L'!$B$4:$M$4,0)),0) | D31: =IFERROR(INDEX('Monthly P&L'!$B$43:$M$43,MATCH(D$4,'Monthly P&L'!$B$4:$M$4,0)),0) | E31: =IFERROR(INDEX('Monthly P&L'!$B$43:$M$43,MATCH(E$4,'Monthly P&L'!$B$4:$M$4,0)),0) | F31: =IFERROR(INDEX('Monthly P&L'!$B$43:$M$43,MATCH(F$4,'Monthly P&L'!$B$4:$M$4,0)),0) | G31: =IFERROR(INDEX('Monthly P&L'!$B$43:$M$43,MATCH(G$4,'Monthly P&L'!$B$4:$M$4,0)),0) | H31: =SUM(B31:G31)
A32: Overheads difference (actual − budget) | B32: =B31-B20 | C32: =C31-C20 | D32: =D31-D20 | E32: =E31-E20 | F32: =F31-F20 | G32: =G31-G20 | H32: =SUM(B32:G32)
A33: Actual net profit | B33: =IFERROR(INDEX('Monthly P&L'!$B$45:$M$45,MATCH(B$4,'Monthly P&L'!$B$4:$M$4,0)),0) | C33: =IFERROR(INDEX('Monthly P&L'!$B$45:$M$45,MATCH(C$4,'Monthly P&L'!$B$4:$M$4,0)),0) | D33: =IFERROR(INDEX('Monthly P&L'!$B$45:$M$45,MATCH(D$4,'Monthly P&L'!$B$4:$M$4,0)),0) | E33: =IFERROR(INDEX('Monthly P&L'!$B$45:$M$45,MATCH(E$4,'Monthly P&L'!$B$4:$M$4,0)),0) | F33: =IFERROR(INDEX('Monthly P&L'!$B$45:$M$45,MATCH(F$4,'Monthly P&L'!$B$4:$M$4,0)),0) | G33: =IFERROR(INDEX('Monthly P&L'!$B$45:$M$45,MATCH(G$4,'Monthly P&L'!$B$4:$M$4,0)),0) | H33: =SUM(B33:G33)
A34: Profit difference (actual − forecast) | B34: =B33-B22 | C34: =C33-C22 | D34: =D33-D22 | E34: =E33-E22 | F34: =F33-F22 | G34: =G33-G22 | H34: =SUM(B34:G34)
A36: How to use: fill rows 6–7, 9 and 14–19 in Week 8. Start with your real averages from the Monthly P&L, then decide what is realistic. Months with no actuals yet show 0 in the actual rows.

Sheet Sales Pipeline
A1: Sales Pipeline: every enquiry, until it is won or lost
A2: Add every lead the day it arrives. Always fill "Next action" and "Next action date".
A3: Open pipeline value: | C3: =SUMIFS(F5:F204,G5:G204,"<>Won",G5:G204,"<>Lost",G5:G204,"<>") | D3: Win rate: | E3: =IF(COUNTIF(G5:G204,"Won")+COUNTIF(G5:G204,"Lost")=0,0,COUNTIF(G5:G204,"Won")/(COUNTIF(G5:G204,"Won")+COUNTIF(G5:G204,"Lost")))
A4: Date in | B4: Lead / company | C4: Contact | D4: Source | E4: Service wanted | F4: Value (Rs) | G4: Stage | H4: Next action | I4: Next action date | J4: Overdue? (auto) | K4: Notes / reason lost
A5: 46297 | B5: EXAMPLE: XYZ Hotels | C5: Ms. Fernando | D5: Referral | E5: Social media management | F5: 80000 | G5: Proposal sent | H5: Call to answer questions on the proposal | I5: 46301 | J5: =IF(OR(I5="",G5="Won",G5="Lost"),"",IF(I5<TODAY(),"OVERDUE",""))
J6: =IF(OR(I6="",G6="Won",G6="Lost"),"",IF(I6<TODAY(),"OVERDUE",""))
J7: =IF(OR(I7="",G7="Won",G7="Lost"),"",IF(I7<TODAY(),"OVERDUE",""))
J8: =IF(OR(I8="",G8="Won",G8="Lost"),"",IF(I8<TODAY(),"OVERDUE",""))
J9: =IF(OR(I9="",G9="Won",G9="Lost"),"",IF(I9<TODAY(),"OVERDUE",""))
J10: =IF(OR(I10="",G10="Won",G10="Lost"),"",IF(I10<TODAY(),"OVERDUE",""))
J11: =IF(OR(I11="",G11="Won",G11="Lost"),"",IF(I11<TODAY(),"OVERDUE",""))
J12: =IF(OR(I12="",G12="Won",G12="Lost"),"",IF(I12<TODAY(),"OVERDUE",""))
J13: =IF(OR(I13="",G13="Won",G13="Lost"),"",IF(I13<TODAY(),"OVERDUE",""))
J14: =IF(OR(I14="",G14="Won",G14="Lost"),"",IF(I14<TODAY(),"OVERDUE",""))
J15: =IF(OR(I15="",G15="Won",G15="Lost"),"",IF(I15<TODAY(),"OVERDUE",""))
J16: =IF(OR(I16="",G16="Won",G16="Lost"),"",IF(I16<TODAY(),"OVERDUE",""))
J17: =IF(OR(I17="",G17="Won",G17="Lost"),"",IF(I17<TODAY(),"OVERDUE",""))
... J204: =IF(OR(I204="",G204="Won",G204="Lost"),"",IF(I204<TODAY(),"OVERDUE",""))

Sheet Weekly Review
A1: Weekly Review: 30 minutes every Sunday or Monday
A2: Answer Yes/No honestly. The money columns fill in automatically from Transactions.
A4: Week | B4: From | C4: To | D4: Money in (auto) | E4: Money out (auto) | F4: Net (auto) | G4: All transactions entered? | H4: Receipts saved? | I4: Invoices sent & chased? | J4: Bank matches sheet? | K4: Plan tasks done? | L4: Biggest win | M4: Biggest problem | N4: Focus for next week
A5: Week 0 | B5: 46296 | C5: 46299 | D5: =SUMIFS(Transactions!$E$5:$E$1504,Transactions!$A$5:$A$1504,">="&B5,Transactions!$A$5:$A$1504,"<="&C5)-SUMIFS(Transactions!$E$5:$E$1504,Transactions!$A$5:$A$1504,">="&B5,Transactions!$A$5:$A$1504,"<="&C5,Transactions!$K$5:$K$1504,"Transfer") | E5: =SUMIFS(Transactions!$F$5:$F$1504,Transactions!$A$5:$A$1504,">="&B5,Transactions!$A$5:$A$1504,"<="&C5)-SUMIFS(Transactions!$F$5:$F$1504,Transactions!$A$5:$A$1504,">="&B5,Transactions!$A$5:$A$1504,"<="&C5,Transactions!$K$5:$K$1504,"Transfer") | F5: =D5-E5
A6: Week 1 | B6: 46300 | C6: 46306 | D6: =SUMIFS(Transactions!$E$5:$E$1504,Transactions!$A$5:$A$1504,">="&B6,Transactions!$A$5:$A$1504,"<="&C6)-SUMIFS(Transactions!$E$5:$E$1504,Transactions!$A$5:$A$1504,">="&B6,Transactions!$A$5:$A$1504,"<="&C6,Transactions!$K$5:$K$1504,"Transfer") | E6: =SUMIFS(Transactions!$F$5:$F$1504,Transactions!$A$5:$A$1504,">="&B6,Transactions!$A$5:$A$1504,"<="&C6)-SUMIFS(Transactions!$F$5:$F$1504,Transactions!$A$5:$A$1504,">="&B6,Transactions!$A$5:$A$1504,"<="&C6,Transactions!$K$5:$K$1504,"Transfer") | F6: =D6-E6
A7: Week 2 | B7: 46307 | C7: 46313 | D7: =SUMIFS(Transactions!$E$5:$E$1504,Transactions!$A$5:$A$1504,">="&B7,Transactions!$A$5:$A$1504,"<="&C7)-SUMIFS(Transactions!$E$5:$E$1504,Transactions!$A$5:$A$1504,">="&B7,Transactions!$A$5:$A$1504,"<="&C7,Transactions!$K$5:$K$1504,"Transfer") | E7: =SUMIFS(Transactions!$F$5:$F$1504,Transactions!$A$5:$A$1504,">="&B7,Transactions!$A$5:$A$1504,"<="&C7)-SUMIFS(Transactions!$F$5:$F$1504,Transactions!$A$5:$A$1504,">="&B7,Transactions!$A$5:$A$1504,"<="&C7,Transactions!$K$5:$K$1504,"Transfer") | F7: =D7-E7
A8: Week 3 | B8: 46314 | C8: 46320 | D8: =SUMIFS(Transactions!$E$5:$E$1504,Transactions!$A$5:$A$1504,">="&B8,Transactions!$A$5:$A$1504,"<="&C8)-SUMIFS(Transactions!$E$5:$E$1504,Transactions!$A$5:$A$1504,">="&B8,Transactions!$A$5:$A$1504,"<="&C8,Transactions!$K$5:$K$1504,"Transfer") | E8: =SUMIFS(Transactions!$F$5:$F$1504,Transactions!$A$5:$A$1504,">="&B8,Transactions!$A$5:$A$1504,"<="&C8)-SUMIFS(Transactions!$F$5:$F$1504,Transactions!$A$5:$A$1504,">="&B8,Transactions!$A$5:$A$1504,"<="&C8,Transactions!$K$5:$K$1504,"Transfer") | F8: =D8-E8
A9: Week 4 | B9: 46321 | C9: 46327 | D9: =SUMIFS(Transactions!$E$5:$E$1504,Transactions!$A$5:$A$1504,">="&B9,Transactions!$A$5:$A$1504,"<="&C9)-SUMIFS(Transactions!$E$5:$E$1504,Transactions!$A$5:$A$1504,">="&B9,Transactions!$A$5:$A$1504,"<="&C9,Transactions!$K$5:$K$1504,"Transfer") | E9: =SUMIFS(Transactions!$F$5:$F$1504,Transactions!$A$5:$A$1504,">="&B9,Transactions!$A$5:$A$1504,"<="&C9)-SUMIFS(Transactions!$F$5:$F$1504,Transactions!$A$5:$A$1504,">="&B9,Transactions!$A$5:$A$1504,"<="&C9,Transactions!$K$5:$K$1504,"Transfer") | F9: =D9-E9
A10: Week 5 | B10: 46328 | C10: 46334 | D10: =SUMIFS(Transactions!$E$5:$E$1504,Transactions!$A$5:$A$1504,">="&B10,Transactions!$A$5:$A$1504,"<="&C10)-SUMIFS(Transactions!$E$5:$E$1504,Transactions!$A$5:$A$1504,">="&B10,Transactions!$A$5:$A$1504,"<="&C10,Transactions!$K$5:$K$1504,"Transfer") | E10: =SUMIFS(Transactions!$F$5:$F$1504,Transactions!$A$5:$A$1504,">="&B10,Transactions!$A$5:$A$1504,"<="&C10)-SUMIFS(Transactions!$F$5:$F$1504,Transactions!$A$5:$A$1504,">="&B10,Transactions!$A$5:$A$1504,"<="&C10,Transactions!$K$5:$K$1504,"Transfer") | F10: =D10-E10
A11: Week 6 | B11: 46335 | C11: 46341 | D11: =SUMIFS(Transactions!$E$5:$E$1504,Transactions!$A$5:$A$1504,">="&B11,Transactions!$A$5:$A$1504,"<="&C11)-SUMIFS(Transactions!$E$5:$E$1504,Transactions!$A$5:$A$1504,">="&B11,Transactions!$A$5:$A$1504,"<="&C11,Transactions!$K$5:$K$1504,"Transfer") | E11: =SUMIFS(Transactions!$F$5:$F$1504,Transactions!$A$5:$A$1504,">="&B11,Transactions!$A$5:$A$1504,"<="&C11)-SUMIFS(Transactions!$F$5:$F$1504,Transactions!$A$5:$A$1504,">="&B11,Transactions!$A$5:$A$1504,"<="&C11,Transactions!$K$5:$K$1504,"Transfer") | F11: =D11-E11
A12: Week 7 | B12: 46342 | C12: 46348 | D12: =SUMIFS(Transactions!$E$5:$E$1504,Transactions!$A$5:$A$1504,">="&B12,Transactions!$A$5:$A$1504,"<="&C12)-SUMIFS(Transactions!$E$5:$E$1504,Transactions!$A$5:$A$1504,">="&B12,Transactions!$A$5:$A$1504,"<="&C12,Transactions!$K$5:$K$1504,"Transfer") | E12: =SUMIFS(Transactions!$F$5:$F$1504,Transactions!$A$5:$A$1504,">="&B12,Transactions!$A$5:$A$1504,"<="&C12)-SUMIFS(Transactions!$F$5:$F$1504,Transactions!$A$5:$A$1504,">="&B12,Transactions!$A$5:$A$1504,"<="&C12,Transactions!$K$5:$K$1504,"Transfer") | F12: =D12-E12
A13: Week 8 | B13: 46349 | C13: 46355 | D13: =SUMIFS(Transactions!$E$5:$E$1504,Transactions!$A$5:$A$1504,">="&B13,Transactions!$A$5:$A$1504,"<="&C13)-SUMIFS(Transactions!$E$5:$E$1504,Transactions!$A$5:$A$1504,">="&B13,Transactions!$A$5:$A$1504,"<="&C13,Transactions!$K$5:$K$1504,"Transfer") | E13: =SUMIFS(Transactions!$F$5:$F$1504,Transactions!$A$5:$A$1504,">="&B13,Transactions!$A$5:$A$1504,"<="&C13)-SUMIFS(Transactions!$F$5:$F$1504,Transactions!$A$5:$A$1504,">="&B13,Transactions!$A$5:$A$1504,"<="&C13,Transactions!$K$5:$K$1504,"Transfer") | F13: =D13-E13
A14: Week 9 | B14: 46356 | C14: 46362 | D14: =SUMIFS(Transactions!$E$5:$E$1504,Transactions!$A$5:$A$1504,">="&B14,Transactions!$A$5:$A$1504,"<="&C14)-SUMIFS(Transactions!$E$5:$E$1504,Transactions!$A$5:$A$1504,">="&B14,Transactions!$A$5:$A$1504,"<="&C14,Transactions!$K$5:$K$1504,"Transfer") | E14: =SUMIFS(Transactions!$F$5:$F$1504,Transactions!$A$5:$A$1504,">="&B14,Transactions!$A$5:$A$1504,"<="&C14)-SUMIFS(Transactions!$F$5:$F$1504,Transactions!$A$5:$A$1504,">="&B14,Transactions!$A$5:$A$1504,"<="&C14,Transactions!$K$5:$K$1504,"Transfer") | F14: =D14-E14
A15: Week 10 | B15: 46363 | C15: 46369 | D15: =SUMIFS(Transactions!$E$5:$E$1504,Transactions!$A$5:$A$1504,">="&B15,Transactions!$A$5:$A$1504,"<="&C15)-SUMIFS(Transactions!$E$5:$E$1504,Transactions!$A$5:$A$1504,">="&B15,Transactions!$A$5:$A$1504,"<="&C15,Transactions!$K$5:$K$1504,"Transfer") | E15: =SUMIFS(Transactions!$F$5:$F$1504,Transactions!$A$5:$A$1504,">="&B15,Transactions!$A$5:$A$1504,"<="&C15)-SUMIFS(Transactions!$F$5:$F$1504,Transactions!$A$5:$A$1504,">="&B15,Transactions!$A$5:$A$1504,"<="&C15,Transactions!$K$5:$K$1504,"Transfer") | F15: =D15-E15
A16: Week 11 | B16: 46370 | C16: 46376 | D16: =SUMIFS(Transactions!$E$5:$E$1504,Transactions!$A$5:$A$1504,">="&B16,Transactions!$A$5:$A$1504,"<="&C16)-SUMIFS(Transactions!$E$5:$E$1504,Transactions!$A$5:$A$1504,">="&B16,Transactions!$A$5:$A$1504,"<="&C16,Transactions!$K$5:$K$1504,"Transfer") | E16: =SUMIFS(Transactions!$F$5:$F$1504,Transactions!$A$5:$A$1504,">="&B16,Transactions!$A$5:$A$1504,"<="&C16)-SUMIFS(Transactions!$F$5:$F$1504,Transactions!$A$5:$A$1504,">="&B16,Transactions!$A$5:$A$1504,"<="&C16,Transactions!$K$5:$K$1504,"Transfer") | F16: =D16-E16
... A18: Week 13 | B18: 46384 | C18: 46387 | D18: =SUMIFS(Transactions!$E$5:$E$1504,Transactions!$A$5:$A$1504,">="&B18,Transactions!$A$5:$A$1504,"<="&C18)-SUMIFS(Transactions!$E$5:$E$1504,Transactions!$A$5:$A$1504,">="&B18,Transactions!$A$5:$A$1504,"<="&C18,Transactions!$K$5:$K$1504,"Transfer") | E18: =SUMIFS(Transactions!$F$5:$F$1504,Transactions!$A$5:$A$1504,">="&B18,Transactions!$A$5:$A$1504,"<="&C18)-SUMIFS(Transactions!$F$5:$F$1504,Transactions!$A$5:$A$1504,">="&B18,Transactions!$A$5:$A$1504,"<="&C18,Transactions!$K$5:$K$1504,"Transfer") | F18: =D18-E18

Sheet 90-Day Plan
A1: 90-Day Plan: October – December 2026
A2: Your task list from the crash course. Change Status as you go; progress updates automatically.
A3: Progress: | B3: =COUNTIF(G6:G45,"Done")/COUNTA(E6:E45) | C3: =COUNTIF(G6:G45,"Done")&" of "&COUNTA(E6:E45)&" tasks done"
A5: Week | B5: Dates | C5: Theme | D5: Area | E5: Task | F5: Done when… | G5: Status
A6: Week 0 | B6: 1–4 Oct | C6: Kick-off | D6: Learn | E6: Read Part 1 of the crash course (the money language: revenue, costs, profit, cash). | F6: You can explain the difference between profit and cash in your own words. | G6: Not started
A7: Week 0 | B7: 1–4 Oct | C7: Kick-off | D7: Money | E7: Choose ONE bank account for the business only. Open a new one if needed. | F7: Every client payment from now on goes into that account. | G7: Not started
A8: Week 0 | B8: 1–4 Oct | C8: Kick-off | D8: Money | E8: Download bank statements from 1 April 2025 to today (the 2025/26 and 2026/27 tax years). | F8: PDF or Excel statements saved in one folder. | G8: Not started
A9: Week 0 | B9: 1–4 Oct | C9: Kick-off | D9: Tool | E9: Fill in the Setup sheet: business name, opening balances, categories, accounts. | F9: Setup sheet complete; no yellow cells left empty that apply to you. | G9: Not started
A10: Week 1 | B10: 5–11 Oct | C10: Rebuild the past (part 1) | D10: Tool | E10: Enter every transaction for April–June 2026 from the bank statements into the Transactions sheet. | F10: Closing balance on the Cash Flow sheet for June matches the bank statement. | G10: Not started
A11: Week 1 | B11: 5–11 Oct | C11: Rebuild the past (part 1) | D11: Learn | E11: Read Part 2: how bookkeeping works (categories, the cash book, receipts). | F11: You know which category every common expense goes into. | G11: Not started
A12: Week 1 | B12: 5–11 Oct | C12: Rebuild the past (part 1) | D12: Money | E12: Start a receipt habit: photograph every receipt into one phone album or folder named by month. | F12: This week's receipts are all saved. | G12: Not started
A13: Week 2 | B13: 12–18 Oct | C13: Rebuild the past (part 2) | D13: Tool | E13: Enter July–September 2026 transactions. | F13: September closing balance matches the bank. | G13: Not started
A14: Week 2 | B14: 12–18 Oct | C14: Rebuild the past (part 2) | D14: Tool | E14: List every client on the Clients sheet and every unpaid invoice on the Invoices sheet. | F14: You know exactly who owes you money and how much. | G14: Not started
A15: Week 2 | B15: 12–18 Oct | C15: Rebuild the past (part 2) | D15: People | E15: Shortlist 3 accountants (CA Sri Lanka or AAT Sri Lanka members, or a tax practitioner) and book short meetings. | F15: Meetings booked. | G15: Not started
A16: Week 3 | B16: 19–25 Oct | C16: Tax and legal health check | D16: Legal | E16: Get a TIN from the IRD e-Services portal if you don't already have one. It becomes compulsory for key transactions from 1 November 2026. | F16: TIN certificate saved. | G16: Not started
... A45: Week 13 | B45: 28–31 Dec | C45: Quarter close and Q1 2027 plan | D45: Legal | E45: Estimate the 3rd tax instalment (due 15 Feb 2027) with your accountant. | F45: Amount known and saved in the tax account. | G45: Not started

Sheet Tax Calendar
A1: Tax & Compliance Calendar (Sri Lanka)
A2: Researched October 2026 from IRD notices and tax-firm summaries. Rules change often: confirm every item with your accountant.
A4: Date | B4: What | C4: Who it applies to | D4: What to do | E4: Status
A5: Before 1 Nov 2026 | B5: TIN certificate compulsory for key transactions | C5: Every individual 18+ and every business | D5: Get your TIN on the IRD e-Services portal. Needed from 1 Nov 2026 to open bank accounts, register a business, vehicles, land, get credit cards. | E5: To check
A6: 15 Nov 2026 | B6: 2nd quarterly income tax instalment, Y/A 2026/27 (Jul–Sep) | C6: Anyone with taxable business income | D6: Accountant estimates the amount; pay and record it as "Income tax paid". | E6: To check
A7: 30 Nov 2026 | B7: Income tax return for Y/A 2025/26 (1 Apr 2025 – 31 Mar 2026) | C7: Individuals, partnerships, companies with taxable income | D7: File the return (usually via your accountant). Any balance tax was due by 30 Sep 2026: if unpaid, settle it now. | E7: To check
A8: 31 Dec 2026 | B8: Quarter end (Oct–Dec) | C8: Your business | D8: Close the books for the quarter; review Dashboard. | E8: To check
A9: 15 Feb 2027 | B9: 3rd quarterly instalment, Y/A 2026/27 (Oct–Dec) | C9: Anyone with taxable business income | D9: Pay the estimate. | E9: To check
A10: 31 Mar 2027 | B10: Financial / tax year ends | C10: Everyone | D10: Year-end close. Count assets, list unpaid invoices and bills. | E10: To check
A11: 15 May 2027 | B11: 4th quarterly instalment, Y/A 2026/27 (Jan–Mar) | C11: Anyone with taxable business income | D11: Pay the estimate. | E11: To check
A12: Monthly | B12: If you employ staff: EPF (8% employee + 12% employer) and ETF (3% employer) | C12: Employers | D12: Register with the Labour Department (EPF) and ETF Board; pay monthly. Confirm due dates with your accountant. | E12: To check
A13: Ongoing | B13: Withholding tax (WHT) on your fees | C13: Individuals earning service fees > Rs 100,000 per month from one payer | D13: Clients may deduct 5% WHT. Collect every WHT certificate: it is credited against your income tax. | E13: To check
A14: Watch | B14: VAT registration (18%) | C14: Turnover above Rs 60 million a year (Rs 15 million a quarter) | D14: The cut to Rs 36 million was proposed, then dropped in June 2026. Check if you are near the limit. | E14: To check
A15: Watch | B15: SSCL registration (2.5% levy on turnover) | C15: From 1 Jul 2026: turnover above Rs 9 million in a quarter or Rs 36 million over 4 quarters | D15: Check your quarterly revenue on the Monthly P&L against this threshold. | E15: To check
A16: Every payment | B16: Large cash payments | C16: Payments of Rs 500,000 or more | D16: From the 2026 amendment, these are not tax-deductible if paid in cash or through non-approved methods. Pay big bills by bank. | E16: To check
A18: Main sources: IRD notices; KPMG Sri Lanka tax alerts (2025–2026); Inland Revenue (Amendment) Act No. 11 of 2026; VAT (Amendment) Act No. 14 of 2026; IRD Circular SEC/2026/E/04 (WHT). Personal income tax: Rs 1.8m relief, then 6% / 18% / 24% / 30% / 36% slabs (from Y/A 2025/26).
